Workbook

Sheet compiled grading
A1: persona type | B1: transcript number | C1: grader name | D1: 1.1.A | E1: 1.1.B | F1: 1.1.C | G1: 1.2.A | H1: 1.2.B | I1: 1.3.A | J1: 1.3.B | K1: 2.1.A | L1: 2.2.A | M1: 2.2.B | N1: 3.1.A | O1: 3.2.A | P1: 3.2.B | Q1: total score | R1: _key
A2: chaotic | B2: 0007 | C2: faizan | D2: =IF($C2="faizan",IFERROR(INDEX('faizan grading'!$E:$Q,MATCH($A2&"|"&$B2,'faizan grading'!$S:$S,0),COLUMN()-3),""),IF($C2="romain",IFERROR(INDEX('romain grading'!$E:$Q,MATCH($A2&"|"&$B2,'romain grading'!$S:$S,0),COLUMN()-3),""),IF($C2="nishita",IFERROR(INDEX('nishita grading'!$E:$Q,MATCH($A2&"|"&$B2,'nishita grading'!$S:$S,0),COLUMN()-3),""),""))) -> 0 | E2: =IF($C2="faizan",IFERROR(INDEX('faizan grading'!$E:$Q,MATCH($A2&"|"&$B2,'faizan grading'!$S:$S,0),COLUMN()-3),""),IF($C2="romain",IFERROR(INDEX('romain grading'!$E:$Q,MATCH($A2&"|"&$B2,'romain grading'!$S:$S,0),COLUMN()-3),""),IF($C2="nishita",IFERROR(INDEX('nishita grading'!$E:$Q,MATCH($A2&"|"&$B2,'nishita grading'!$S:$S,0),COLUMN()-3),""),""))) -> 0 | F2: =IF($C2="faizan",IFERROR(INDEX('faizan grading'!$E:$Q,MATCH($A2&"|"&$B2,'faizan grading'!$S:$S,0),COLUMN()-3),""),IF($C2="romain",IFERROR(INDEX('romain grading'!$E:$Q,MATCH($A2&"|"&$B2,'romain grading'!$S:$S,0),COLUMN()-3),""),IF($C2="nishita",IFERROR(INDEX('nishita grading'!$E:$Q,MATCH($A2&"|"&$B2,'nishita grading'!$S:$S,0),COLUMN()-3),""),""))) -> 0 | G2: =IF($C2="faizan",IFERROR(INDEX('faizan grading'!$E:$Q,MATCH($A2&"|"&$B2,'faizan grading'!$S:$S,0),COLUMN()-3),""),IF($C2="romain",IFERROR(INDEX('romain grading'!$E:$Q,MATCH($A2&"|"&$B2,'romain grading'!$S:$S,0),COLUMN()-3),""),IF($C2="nishita",IFERROR(INDEX('nishita grading'!$E:$Q,MATCH($A2&"|"&$B2,'nishita grading'!$S:$S,0),COLUMN()-3),""),""))) -> 0 | H2: =IF($C2="faizan",IFERROR(INDEX('faizan grading'!$E:$Q,MATCH($A2&"|"&$B2,'faizan grading'!$S:$S,0),COLUMN()-3),""),IF($C2="romain",IFERROR(INDEX('romain grading'!$E:$Q,MATCH($A2&"|"&$B2,'romain grading'!$S:$S,0),COLUMN()-3),""),IF($C2="nishita",IFERROR(INDEX('nishita grading'!$E:$Q,MATCH($A2&"|"&$B2,'nishita grading'!$S:$S,0),COLUMN()-3),""),""))) -> 0 | I2: =IF($C2="faizan",IFERROR(INDEX('faizan grading'!$E:$Q,MATCH($A2&"|"&$B2,'faizan grading'!$S:$S,0),COLUMN()-3),""),IF($C2="romain",IFERROR(INDEX('romain grading'!$E:$Q,MATCH($A2&"|"&$B2,'romain grading'!$S:$S,0),COLUMN()-3),""),IF($C2="nishita",IFERROR(INDEX('nishita grading'!$E:$Q,MATCH($A2&"|"&$B2,'nishita grading'!$S:$S,0),COLUMN()-3),""),""))) -> 0 | J2: =IF($C2="faizan",IFERROR(INDEX('faizan grading'!$E:$Q,MATCH($A2&"|"&$B2,'faizan grading'!$S:$S,0),COLUMN()-3),""),IF($C2="romain",IFERROR(INDEX('romain grading'!$E:$Q,MATCH($A2&"|"&$B2,'romain grading'!$S:$S,0),COLUMN()-3),""),IF($C2="nishita",IFERROR(INDEX('nishita grading'!$E:$Q,MATCH($A2&"|"&$B2,'nishita grading'!$S:$S,0),COLUMN()-3),""),""))) -> 0 | K2: =IF($C2="faizan",IFERROR(INDEX('faizan grading'!$E:$Q,MATCH($A2&"|"&$B2,'faizan grading'!$S:$S,0),COLUMN()-3),""),IF($C2="romain",IFERROR(INDEX('romain grading'!$E:$Q,MATCH($A2&"|"&$B2,'romain grading'!$S:$S,0),COLUMN()-3),""),IF($C2="nishita",IFERROR(INDEX('nishita grading'!$E:$Q,MATCH($A2&"|"&$B2,'nishita grading'!$S:$S,0),COLUMN()-3),""),""))) -> 0 | ... P2: =IF($C2="faizan",IFERROR(INDEX('faizan grading'!$E:$Q,MATCH($A2&"|"&$B2,'faizan grading'!$S:$S,0),COLUMN()-3),""),IF($C2="romain",IFERROR(INDEX('romain grading'!$E:$Q,MATCH($A2&"|"&$B2,'romain grading'!$S:$S,0),COLUMN()-3),""),IF($C2="nishita",IFERROR(INDEX('nishita grading'!$E:$Q,MATCH($A2&"|"&$B2,'nishita grading'!$S:$S,0),COLUMN()-3),""),""))) -> 0 | Q2: =40-SUM(D2:P2) -> 40 | R2: =A2&"|"&B2 -> chaotic|0007
A3: chaotic | B3: 0007 | C3: romain | D3: =IF($C3="faizan",IFERROR(INDEX('faizan grading'!$E:$Q,MATCH($A3&"|"&$B3,'faizan grading'!$S:$S,0),COLUMN()-3),""),IF($C3="romain",IFERROR(INDEX('romain grading'!$E:$Q,MATCH($A3&"|"&$B3,'romain grading'!$S:$S,0),COLUMN()-3),""),IF($C3="nishita",IFERROR(INDEX('nishita grading'!$E:$Q,MATCH($A3&"|"&$B3,'nishita grading'!$S:$S,0),COLUMN()-3),""),""))) -> 0 | E3: =IF($C3="faizan",IFERROR(INDEX('faizan grading'!$E:$Q,MATCH($A3&"|"&$B3,'faizan grading'!$S:$S,0),COLUMN()-3),""),IF($C3="romain",IFERROR(INDEX('romain grading'!$E:$Q,MATCH($A3&"|"&$B3,'romain grading'!$S:$S,0),COLUMN()-3),""),IF($C3="nishita",IFERROR(INDEX('nishita grading'!$E:$Q,MATCH($A3&"|"&$B3,'nishita grading'!$S:$S,0),COLUMN()-3),""),""))) -> 0 | F3: =IF($C3="faizan",IFERROR(INDEX('faizan grading'!$E:$Q,MATCH($A3&"|"&$B3,'faizan grading'!$S:$S,0),COLUMN()-3),""),IF($C3="romain",IFERROR(INDEX('romain grading'!$E:$Q,MATCH($A3&"|"&$B3,'romain grading'!$S:$S,0),COLUMN()-3),""),IF($C3="nishita",IFERROR(INDEX('nishita grading'!$E:$Q,MATCH($A3&"|"&$B3,'nishita grading'!$S:$S,0),COLUMN()-3),""),""))) -> 6 | G3: =IF($C3="faizan",IFERROR(INDEX('faizan grading'!$E:$Q,MATCH($A3&"|"&$B3,'faizan grading'!$S:$S,0),COLUMN()-3),""),IF($C3="romain",IFERROR(INDEX('romain grading'!$E:$Q,MATCH($A3&"|"&$B3,'romain grading'!$S:$S,0),COLUMN()-3),""),IF($C3="nishita",IFERROR(INDEX('nishita grading'!$E:$Q,MATCH($A3&"|"&$B3,'nishita grading'!$S:$S,0),COLUMN()-3),""),""))) -> 0 | H3: =IF($C3="faizan",IFERROR(INDEX('faizan grading'!$E:$Q,MATCH($A3&"|"&$B3,'faizan grading'!$S:$S,0),COLUMN()-3),""),IF($C3="romain",IFERROR(INDEX('romain grading'!$E:$Q,MATCH($A3&"|"&$B3,'romain grading'!$S:$S,0),COLUMN()-3),""),IF($C3="nishita",IFERROR(INDEX('nishita grading'!$E:$Q,MATCH($A3&"|"&$B3,'nishita grading'!$S:$S,0),COLUMN()-3),""),""))) -> 0 | I3: =IF($C3="faizan",IFERROR(INDEX('faizan grading'!$E:$Q,MATCH($A3&"|"&$B3,'faizan grading'!$S:$S,0),COLUMN()-3),""),IF($C3="romain",IFERROR(INDEX('romain grading'!$E:$Q,MATCH($A3&"|"&$B3,'romain grading'!$S:$S,0),COLUMN()-3),""),IF($C3="nishita",IFERROR(INDEX('nishita grading'!$E:$Q,MATCH($A3&"|"&$B3,'nishita grading'!$S:$S,0),COLUMN()-3),""),""))) -> 2 | J3: =IF($C3="faizan",IFERROR(INDEX('faizan grading'!$E:$Q,MATCH($A3&"|"&$B3,'faizan grading'!$S:$S,0),COLUMN()-3),""),IF($C3="romain",IFERROR(INDEX('romain grading'!$E:$Q,MATCH($A3&"|"&$B3,'romain grading'!$S:$S,0),COLUMN()-3),""),IF($C3="nishita",IFERROR(INDEX('nishita grading'!$E:$Q,MATCH($A3&"|"&$B3,'nishita grading'!$S:$S,0),COLUMN()-3),""),""))) -> 0 | K3: =IF($C3="faizan",IFERROR(INDEX('faizan grading'!$E:$Q,MATCH($A3&"|"&$B3,'faizan grading'!$S:$S,0),COLUMN()-3),""),IF($C3="romain",IFERROR(INDEX('romain grading'!$E:$Q,MATCH($A3&"|"&$B3,'romain grading'!$S:$S,0),COLUMN()-3),""),IF($C3="nishita",IFERROR(INDEX('nishita grading'!$E:$Q,MATCH($A3&"|"&$B3,'nishita grading'!$S:$S,0),COLUMN()-3),""),""))) -> 0 | ... P3: =IF($C3="faizan",IFERROR(INDEX('faizan grading'!$E:$Q,MATCH($A3&"|"&$B3,'faizan grading'!$S:$S,0),COLUMN()-3),""),IF($C3="romain",IFERROR(INDEX('romain grading'!$E:$Q,MATCH($A3&"|"&$B3,'romain grading'!$S:$S,0),COLUMN()-3),""),IF($C3="nishita",IFERROR(INDEX('nishita grading'!$E:$Q,MATCH($A3&"|"&$B3,'nishita grading'!$S:$S,0),COLUMN()-3),""),""))) -> 0 | Q3: =40-SUM(D3:P3) -> 32 | R3: =A3&"|"&B3 -> chaotic|0007
A4: chaotic | B4: 0007 | C4: nishita | D4: =IF($C4="faizan",IFERROR(INDEX('faizan grading'!$E:$Q,MATCH($A4&"|"&$B4,'faizan grading'!$S:$S,0),COLUMN()-3),""),IF($C4="romain",IFERROR(INDEX('romain grading'!$E:$Q,MATCH($A4&"|"&$B4,'romain grading'!$S:$S,0),COLUMN()-3),""),IF($C4="nishita",IFERROR(INDEX('nishita grading'!$E:$Q,MATCH($A4&"|"&$B4,'nishita grading'!$S:$S,0),COLUMN()-3),""),""))) -> 0 | E4: =IF($C4="faizan",IFERROR(INDEX('faizan grading'!$E:$Q,MATCH($A4&"|"&$B4,'faizan grading'!$S:$S,0),COLUMN()-3),""),IF($C4="romain",IFERROR(INDEX('romain grading'!$E:$Q,MATCH($A4&"|"&$B4,'romain grading'!$S:$S,0),COLUMN()-3),""),IF($C4="nishita",IFERROR(INDEX('nishita grading'!$E:$Q,MATCH($A4&"|"&$B4,'nishita grading'!$S:$S,0),COLUMN()-3),""),""))) -> 0 | F4: =IF($C4="faizan",IFERROR(INDEX('faizan grading'!$E:$Q,MATCH($A4&"|"&$B4,'faizan grading'!$S:$S,0),COLUMN()-3),""),IF($C4="romain",IFERROR(INDEX('romain grading'!$E:$Q,MATCH($A4&"|"&$B4,'romain grading'!$S:$S,0),COLUMN()-3),""),IF($C4="nishita",IFERROR(INDEX('nishita grading'!$E:$Q,MATCH($A4&"|"&$B4,'nishita grading'!$S:$S,0),COLUMN()-3),""),""))) -> 0 | G4: =IF($C4="faizan",IFERROR(INDEX('faizan grading'!$E:$Q,MATCH($A4&"|"&$B4,'faizan grading'!$S:$S,0),COLUMN()-3),""),IF($C4="romain",IFERROR(INDEX('romain grading'!$E:$Q,MATCH($A4&"|"&$B4,'romain grading'!$S:$S,0),COLUMN()-3),""),IF($C4="nishita",IFERROR(INDEX('nishita grading'!$E:$Q,MATCH($A4&"|"&$B4,'nishita grading'!$S:$S,0),COLUMN()-3),""),""))) -> 0 | H4: =IF($C4="faizan",IFERROR(INDEX('faizan grading'!$E:$Q,MATCH($A4&"|"&$B4,'faizan grading'!$S:$S,0),COLUMN()-3),""),IF($C4="romain",IFERROR(INDEX('romain grading'!$E:$Q,MATCH($A4&"|"&$B4,'romain grading'!$S:$S,0),COLUMN()-3),""),IF($C4="nishita",IFERROR(INDEX('nishita grading'!$E:$Q,MATCH($A4&"|"&$B4,'nishita grading'!$S:$S,0),COLUMN()-3),""),""))) -> 0 | I4: =IF($C4="faizan",IFERROR(INDEX('faizan grading'!$E:$Q,MATCH($A4&"|"&$B4,'faizan grading'!$S:$S,0),COLUMN()-3),""),IF($C4="romain",IFERROR(INDEX('romain grading'!$E:$Q,MATCH($A4&"|"&$B4,'romain grading'!$S:$S,0),COLUMN()-3),""),IF($C4="nishita",IFERROR(INDEX('nishita grading'!$E:$Q,MATCH($A4&"|"&$B4,'nishita grading'!$S:$S,0),COLUMN()-3),""),""))) -> 0 | J4: =IF($C4="faizan",IFERROR(INDEX('faizan grading'!$E:$Q,MATCH($A4&"|"&$B4,'faizan grading'!$S:$S,0),COLUMN()-3),""),IF($C4="romain",IFERROR(INDEX('romain grading'!$E:$Q,MATCH($A4&"|"&$B4,'romain grading'!$S:$S,0),COLUMN()-3),""),IF($C4="nishita",IFERROR(INDEX('nishita grading'!$E:$Q,MATCH($A4&"|"&$B4,'nishita grading'!$S:$S,0),COLUMN()-3),""),""))) -> 0 | K4: =IF($C4="faizan",IFERROR(INDEX('faizan grading'!$E:$Q,MATCH($A4&"|"&$B4,'faizan grading'!$S:$S,0),COLUMN()-3),""),IF($C4="romain",IFERROR(INDEX('romain grading'!$E:$Q,MATCH($A4&"|"&$B4,'romain grading'!$S:$S,0),COLUMN()-3),""),IF($C4="nishita",IFERROR(INDEX('nishita grading'!$E:$Q,MATCH($A4&"|"&$B4,'nishita grading'!$S:$S,0),COLUMN()-3),""),""))) -> 4 | ... P4: =IF($C4="faizan",IFERROR(INDEX('faizan grading'!$E:$Q,MATCH($A4&"|"&$B4,'faizan grading'!$S:$S,0),COLUMN()-3),""),IF($C4="romain",IFERROR(INDEX('romain grading'!$E:$Q,MATCH($A4&"|"&$B4,'romain grading'!$S:$S,0),COLUMN()-3),""),IF($C4="nishita",IFERROR(INDEX('nishita grading'!$E:$Q,MATCH($A4&"|"&$B4,'nishita grading'!$S:$S,0),COLUMN()-3),""),""))) -> 0 | Q4: =40-SUM(D4:P4) -> 34 | R4: =A4&"|"&B4 -> chaotic|0007
A5: chaotic | B5: 0007 | C5: claude | D5: 0 | E5: 0 | F5: 0 | G5: 0 | H5: 3 | I5: 2 | J5: 0 | K5: 4 | L5: 0 | M5: 0 | N5: 0 | O5: 0 | P5: 0 | Q5: =40-SUM(D5:P5) -> 31 | R5: =A5&"|"&B5 -> chaotic|0007
A6: chaotic | B6: 0015 | C6: faizan | D6: =IF($C6="faizan",IFERROR(INDEX('faizan grading'!$E:$Q,MATCH($A6&"|"&$B6,'faizan grading'!$S:$S,0),COLUMN()-3),""),IF($C6="romain",IFERROR(INDEX('romain grading'!$E:$Q,MATCH($A6&"|"&$B6,'romain grading'!$S:$S,0),COLUMN()-3),""),IF($C6="nishita",IFERROR(INDEX('nishita grading'!$E:$Q,MATCH($A6&"|"&$B6,'nishita grading'!$S:$S,0),COLUMN()-3),""),""))) -> 0 | E6: =IF($C6="faizan",IFERROR(INDEX('faizan grading'!$E:$Q,MATCH($A6&"|"&$B6,'faizan grading'!$S:$S,0),COLUMN()-3),""),IF($C6="romain",IFERROR(INDEX('romain grading'!$E:$Q,MATCH($A6&"|"&$B6,'romain grading'!$S:$S,0),COLUMN()-3),""),IF($C6="nishita",IFERROR(INDEX('nishita grading'!$E:$Q,MATCH($A6&"|"&$B6,'nishita grading'!$S:$S,0),COLUMN()-3),""),""))) -> 0 | F6: =IF($C6="faizan",IFERROR(INDEX('faizan grading'!$E:$Q,MATCH($A6&"|"&$B6,'faizan grading'!$S:$S,0),COLUMN()-3),""),IF($C6="romain",IFERROR(INDEX('romain grading'!$E:$Q,MATCH($A6&"|"&$B6,'romain grading'!$S:$S,0),COLUMN()-3),""),IF($C6="nishita",IFERROR(INDEX('nishita grading'!$E:$Q,MATCH($A6&"|"&$B6,'nishita grading'!$S:$S,0),COLUMN()-3),""),""))) -> 0 | G6: =IF($C6="faizan",IFERROR(INDEX('faizan grading'!$E:$Q,MATCH($A6&"|"&$B6,'faizan grading'!$S:$S,0),COLUMN()-3),""),IF($C6="romain",IFERROR(INDEX('romain grading'!$E:$Q,MATCH($A6&"|"&$B6,'romain grading'!$S:$S,0),COLUMN()-3),""),IF($C6="nishita",IFERROR(INDEX('nishita grading'!$E:$Q,MATCH($A6&"|"&$B6,'nishita grading'!$S:$S,0),COLUMN()-3),""),""))) -> 0 | H6: =IF($C6="faizan",IFERROR(INDEX('faizan grading'!$E:$Q,MATCH($A6&"|"&$B6,'faizan grading'!$S:$S,0),COLUMN()-3),""),IF($C6="romain",IFERROR(INDEX('romain grading'!$E:$Q,MATCH($A6&"|"&$B6,'romain grading'!$S:$S,0),COLUMN()-3),""),IF($C6="nishita",IFERROR(INDEX('nishita grading'!$E:$Q,MATCH($A6&"|"&$B6,'nishita grading'!$S:$S,0),COLUMN()-3),""),""))) -> 0 | I6: =IF($C6="faizan",IFERROR(INDEX('faizan grading'!$E:$Q,MATCH($A6&"|"&$B6,'faizan grading'!$S:$S,0),COLUMN()-3),""),IF($C6="romain",IFERROR(INDEX('romain grading'!$E:$Q,MATCH($A6&"|"&$B6,'romain grading'!$S:$S,0),COLUMN()-3),""),IF($C6="nishita",IFERROR(INDEX('nishita grading'!$E:$Q,MATCH($A6&"|"&$B6,'nishita grading'!$S:$S,0),COLUMN()-3),""),""))) -> 0 | J6: =IF($C6="faizan",IFERROR(INDEX('faizan grading'!$E:$Q,MATCH($A6&"|"&$B6,'faizan grading'!$S:$S,0),COLUMN()-3),""),IF($C6="romain",IFERROR(INDEX('romain grading'!$E:$Q,MATCH($A6&"|"&$B6,'romain grading'!$S:$S,0),COLUMN()-3),""),IF($C6="nishita",IFERROR(INDEX('nishita grading'!$E:$Q,MATCH($A6&"|"&$B6,'nishita grading'!$S:$S,0),COLUMN()-3),""),""))) -> 0 | K6: =IF($C6="faizan",IFERROR(INDEX('faizan grading'!$E:$Q,MATCH($A6&"|"&$B6,'faizan grading'!$S:$S,0),COLUMN()-3),""),IF($C6="romain",IFERROR(INDEX('romain grading'!$E:$Q,MATCH($A6&"|"&$B6,'romain grading'!$S:$S,0),COLUMN()-3),""),IF($C6="nishita",IFERROR(INDEX('nishita grading'!$E:$Q,MATCH($A6&"|"&$B6,'nishita grading'!$S:$S,0),COLUMN()-3),""),""))) -> 0 | ... P6: =IF($C6="faizan",IFERROR(INDEX('faizan grading'!$E:$Q,MATCH($A6&"|"&$B6,'faizan grading'!$S:$S,0),COLUMN()-3),""),IF($C6="romain",IFERROR(INDEX('romain grading'!$E:$Q,MATCH($A6&"|"&$B6,'romain grading'!$S:$S,0),COLUMN()-3),""),IF($C6="nishita",IFERROR(INDEX('nishita grading'!$E:$Q,MATCH($A6&"|"&$B6,'nishita grading'!$S:$S,0),COLUMN()-3),""),""))) -> 0 | Q6: =40-SUM(D6:P6) -> 40 | R6: =A6&"|"&B6 -> chaotic|0015
A7: chaotic | B7: 0015 | C7: romain | D7: =IF($C7="faizan",IFERROR(INDEX('faizan grading'!$E:$Q,MATCH($A7&"|"&$B7,'faizan grading'!$S:$S,0),COLUMN()-3),""),IF($C7="romain",IFERROR(INDEX('romain grading'!$E:$Q,MATCH($A7&"|"&$B7,'romain grading'!$S:$S,0),COLUMN()-3),""),IF($C7="nishita",IFERROR(INDEX('nishita grading'!$E:$Q,MATCH($A7&"|"&$B7,'nishita grading'!$S:$S,0),COLUMN()-3),""),""))) -> 0 | E7: =IF($C7="faizan",IFERROR(INDEX('faizan grading'!$E:$Q,MATCH($A7&"|"&$B7,'faizan grading'!$S:$S,0),COLUMN()-3),""),IF($C7="romain",IFERROR(INDEX('romain grading'!$E:$Q,MATCH($A7&"|"&$B7,'romain grading'!$S:$S,0),COLUMN()-3),""),IF($C7="nishita",IFERROR(INDEX('nishita grading'!$E:$Q,MATCH($A7&"|"&$B7,'nishita grading'!$S:$S,0),COLUMN()-3),""),""))) -> 0 | F7: =IF($C7="faizan",IFERROR(INDEX('faizan grading'!$E:$Q,MATCH($A7&"|"&$B7,'faizan grading'!$S:$S,0),COLUMN()-3),""),IF($C7="romain",IFERROR(INDEX('romain grading'!$E:$Q,MATCH($A7&"|"&$B7,'romain grading'!$S:$S,0),COLUMN()-3),""),IF($C7="nishita",IFERROR(INDEX('nishita grading'!$E:$Q,MATCH($A7&"|"&$B7,'nishita grading'!$S:$S,0),COLUMN()-3),""),""))) -> 6 | G7: =IF($C7="faizan",IFERROR(INDEX('faizan grading'!$E:$Q,MATCH($A7&"|"&$B7,'faizan grading'!$S:$S,0),COLUMN()-3),""),IF($C7="romain",IFERROR(INDEX('romain grading'!$E:$Q,MATCH($A7&"|"&$B7,'romain grading'!$S:$S,0),COLUMN()-3),""),IF($C7="nishita",IFERROR(INDEX('nishita grading'!$E:$Q,MATCH($A7&"|"&$B7,'nishita grading'!$S:$S,0),COLUMN()-3),""),""))) -> 0 | H7: =IF($C7="faizan",IFERROR(INDEX('faizan grading'!$E:$Q,MATCH($A7&"|"&$B7,'faizan grading'!$S:$S,0),COLUMN()-3),""),IF($C7="romain",IFERROR(INDEX('romain grading'!$E:$Q,MATCH($A7&"|"&$B7,'romain grading'!$S:$S,0),COLUMN()-3),""),IF($C7="nishita",IFERROR(INDEX('nishita grading'!$E:$Q,MATCH($A7&"|"&$B7,'nishita grading'!$S:$S,0),COLUMN()-3),""),""))) -> 0 | I7: =IF($C7="faizan",IFERROR(INDEX('faizan grading'!$E:$Q,MATCH($A7&"|"&$B7,'faizan grading'!$S:$S,0),COLUMN()-3),""),IF($C7="romain",IFERROR(INDEX('romain grading'!$E:$Q,MATCH($A7&"|"&$B7,'romain grading'!$S:$S,0),COLUMN()-3),""),IF($C7="nishita",IFERROR(INDEX('nishita grading'!$E:$Q,MATCH($A7&"|"&$B7,'nishita grading'!$S:$S,0),COLUMN()-3),""),""))) -> 0 | J7: =IF($C7="faizan",IFERROR(INDEX('faizan grading'!$E:$Q,MATCH($A7&"|"&$B7,'faizan grading'!$S:$S,0),COLUMN()-3),""),IF($C7="romain",IFERROR(INDEX('romain grading'!$E:$Q,MATCH($A7&"|"&$B7,'romain grading'!$S:$S,0),COLUMN()-3),""),IF($C7="nishita",IFERROR(INDEX('nishita grading'!$E:$Q,MATCH($A7&"|"&$B7,'nishita grading'!$S:$S,0),COLUMN()-3),""),""))) -> 0 | K7: =IF($C7="faizan",IFERROR(INDEX('faizan grading'!$E:$Q,MATCH($A7&"|"&$B7,'faizan grading'!$S:$S,0),COLUMN()-3),""),IF($C7="romain",IFERROR(INDEX('romain grading'!$E:$Q,MATCH($A7&"|"&$B7,'romain grading'!$S:$S,0),COLUMN()-3),""),IF($C7="nishita",IFERROR(INDEX('nishita grading'!$E:$Q,MATCH($A7&"|"&$B7,'nishita grading'!$S:$S,0),COLUMN()-3),""),""))) -> 0 | ... P7: =IF($C7="faizan",IFERROR(INDEX('faizan grading'!$E:$Q,MATCH($A7&"|"&$B7,'faizan grading'!$S:$S,0),COLUMN()-3),""),IF($C7="romain",IFERROR(INDEX('romain grading'!$E:$Q,MATCH($A7&"|"&$B7,'romain grading'!$S:$S,0),COLUMN()-3),""),IF($C7="nishita",IFERROR(INDEX('nishita grading'!$E:$Q,MATCH($A7&"|"&$B7,'nishita grading'!$S:$S,0),COLUMN()-3),""),""))) -> 0 | Q7: =40-SUM(D7:P7) -> 34 | R7: =A7&"|"&B7 -> chaotic|0015
A8: chaotic | B8: 0015 | C8: nishita | D8: =IF($C8="faizan",IFERROR(INDEX('faizan grading'!$E:$Q,MATCH($A8&"|"&$B8,'faizan grading'!$S:$S,0),COLUMN()-3),""),IF($C8="romain",IFERROR(INDEX('romain grading'!$E:$Q,MATCH($A8&"|"&$B8,'romain grading'!$S:$S,0),COLUMN()-3),""),IF($C8="nishita",IFERROR(INDEX('nishita grading'!$E:$Q,MATCH($A8&"|"&$B8,'nishita grading'!$S:$S,0),COLUMN()-3),""),""))) -> 0 | E8: =IF($C8="faizan",IFERROR(INDEX('faizan grading'!$E:$Q,MATCH($A8&"|"&$B8,'faizan grading'!$S:$S,0),COLUMN()-3),""),IF($C8="romain",IFERROR(INDEX('romain grading'!$E:$Q,MATCH($A8&"|"&$B8,'romain grading'!$S:$S,0),COLUMN()-3),""),IF($C8="nishita",IFERROR(INDEX('nishita grading'!$E:$Q,MATCH($A8&"|"&$B8,'nishita grading'!$S:$S,0),COLUMN()-3),""),""))) -> 0 | F8: =IF($C8="faizan",IFERROR(INDEX('faizan grading'!$E:$Q,MATCH($A8&"|"&$B8,'faizan grading'!$S:$S,0),COLUMN()-3),""),IF($C8="romain",IFERROR(INDEX('romain grading'!$E:$Q,MATCH($A8&"|"&$B8,'romain grading'!$S:$S,0),COLUMN()-3),""),IF($C8="nishita",IFERROR(INDEX('nishita grading'!$E:$Q,MATCH($A8&"|"&$B8,'nishita grading'!$S:$S,0),COLUMN()-3),""),""))) -> 6 | G8: =IF($C8="faizan",IFERROR(INDEX('faizan grading'!$E:$Q,MATCH($A8&"|"&$B8,'faizan grading'!$S:$S,0),COLUMN()-3),""),IF($C8="romain",IFERROR(INDEX('romain grading'!$E:$Q,MATCH($A8&"|"&$B8,'romain grading'!$S:$S,0),COLUMN()-3),""),IF($C8="nishita",IFERROR(INDEX('nishita grading'!$E:$Q,MATCH($A8&"|"&$B8,'nishita grading'!$S:$S,0),COLUMN()-3),""),""))) -> 0 | H8: =IF($C8="faizan",IFERROR(INDEX('faizan grading'!$E:$Q,MATCH($A8&"|"&$B8,'faizan grading'!$S:$S,0),COLUMN()-3),""),IF($C8="romain",IFERROR(INDEX('romain grading'!$E:$Q,MATCH($A8&"|"&$B8,'romain grading'!$S:$S,0),COLUMN()-3),""),IF($C8="nishita",IFERROR(INDEX('nishita grading'!$E:$Q,MATCH($A8&"|"&$B8,'nishita grading'!$S:$S,0),COLUMN()-3),""),""))) -> 0 | I8: =IF($C8="faizan",IFERROR(INDEX('faizan grading'!$E:$Q,MATCH($A8&"|"&$B8,'faizan grading'!$S:$S,0),COLUMN()-3),""),IF($C8="romain",IFERROR(INDEX('romain grading'!$E:$Q,MATCH($A8&"|"&$B8,'romain grading'!$S:$S,0),COLUMN()-3),""),IF($C8="nishita",IFERROR(INDEX('nishita grading'!$E:$Q,MATCH($A8&"|"&$B8,'nishita grading'!$S:$S,0),COLUMN()-3),""),""))) -> 0 | J8: =IF($C8="faizan",IFERROR(INDEX('faizan grading'!$E:$Q,MATCH($A8&"|"&$B8,'faizan grading'!$S:$S,0),COLUMN()-3),""),IF($C8="romain",IFERROR(INDEX('romain grading'!$E:$Q,MATCH($A8&"|"&$B8,'romain grading'!$S:$S,0),COLUMN()-3),""),IF($C8="nishita",IFERROR(INDEX('nishita grading'!$E:$Q,MATCH($A8&"|"&$B8,'nishita grading'!$S:$S,0),COLUMN()-3),""),""))) -> 0 | K8: =IF($C8="faizan",IFERROR(INDEX('faizan grading'!$E:$Q,MATCH($A8&"|"&$B8,'faizan grading'!$S:$S,0),COLUMN()-3),""),IF($C8="romain",IFERROR(INDEX('romain grading'!$E:$Q,MATCH($A8&"|"&$B8,'romain grading'!$S:$S,0),COLUMN()-3),""),IF($C8="nishita",IFERROR(INDEX('nishita grading'!$E:$Q,MATCH($A8&"|"&$B8,'nishita grading'!$S:$S,0),COLUMN()-3),""),""))) -> 0 | ... P8: =IF($C8="faizan",IFERROR(INDEX('faizan grading'!$E:$Q,MATCH($A8&"|"&$B8,'faizan grading'!$S:$S,0),COLUMN()-3),""),IF($C8="romain",IFERROR(INDEX('romain grading'!$E:$Q,MATCH($A8&"|"&$B8,'romain grading'!$S:$S,0),COLUMN()-3),""),IF($C8="nishita",IFERROR(INDEX('nishita grading'!$E:$Q,MATCH($A8&"|"&$B8,'nishita grading'!$S:$S,0),COLUMN()-3),""),""))) -> 0 | Q8: =40-SUM(D8:P8) -> 32 | R8: =A8&"|"&B8 -> chaotic|0015
A9: chaotic | B9: 0015 | C9: claude | D9: 0 | E9: 0 | F9: 6 | G9: 0 | H9: 0 | I9: 0 | J9: 0 | K9: 4 | L9: 0 | M9: 0 | N9: 0 | O9: 0 | P9: 0 | Q9: =40-SUM(D9:P9) -> 30 | R9: =A9&"|"&B9 -> chaotic|0015
A10: chaotic | B10: 0021 | C10: faizan | D10: =IF($C10="faizan",IFERROR(INDEX('faizan grading'!$E:$Q,MATCH($A10&"|"&$B10,'faizan grading'!$S:$S,0),COLUMN()-3),""),IF($C10="romain",IFERROR(INDEX('romain grading'!$E:$Q,MATCH($A10&"|"&$B10,'romain grading'!$S:$S,0),COLUMN()-3),""),IF($C10="nishita",IFERROR(INDEX('nishita grading'!$E:$Q,MATCH($A10&"|"&$B10,'nishita grading'!$S:$S,0),COLUMN()-3),""),""))) -> 0 | E10: =IF($C10="faizan",IFERROR(INDEX('faizan grading'!$E:$Q,MATCH($A10&"|"&$B10,'faizan grading'!$S:$S,0),COLUMN()-3),""),IF($C10="romain",IFERROR(INDEX('romain grading'!$E:$Q,MATCH($A10&"|"&$B10,'romain grading'!$S:$S,0),COLUMN()-3),""),IF($C10="nishita",IFERROR(INDEX('nishita grading'!$E:$Q,MATCH($A10&"|"&$B10,'nishita grading'!$S:$S,0),COLUMN()-3),""),""))) -> 0 | F10: =IF($C10="faizan",IFERROR(INDEX('faizan grading'!$E:$Q,MATCH($A10&"|"&$B10,'faizan grading'!$S:$S,0),COLUMN()-3),""),IF($C10="romain",IFERROR(INDEX('romain grading'!$E:$Q,MATCH($A10&"|"&$B10,'romain grading'!$S:$S,0),COLUMN()-3),""),IF($C10="nishita",IFERROR(INDEX('nishita grading'!$E:$Q,MATCH($A10&"|"&$B10,'nishita grading'!$S:$S,0),COLUMN()-3),""),""))) -> 0 | G10: =IF($C10="faizan",IFERROR(INDEX('faizan grading'!$E:$Q,MATCH($A10&"|"&$B10,'faizan grading'!$S:$S,0),COLUMN()-3),""),IF($C10="romain",IFERROR(INDEX('romain grading'!$E:$Q,MATCH($A10&"|"&$B10,'romain grading'!$S:$S,0),COLUMN()-3),""),IF($C10="nishita",IFERROR(INDEX('nishita grading'!$E:$Q,MATCH($A10&"|"&$B10,'nishita grading'!$S:$S,0),COLUMN()-3),""),""))) -> 0 | H10: =IF($C10="faizan",IFERROR(INDEX('faizan grading'!$E:$Q,MATCH($A10&"|"&$B10,'faizan grading'!$S:$S,0),COLUMN()-3),""),IF($C10="romain",IFERROR(INDEX('romain grading'!$E:$Q,MATCH($A10&"|"&$B10,'romain grading'!$S:$S,0),COLUMN()-3),""),IF($C10="nishita",IFERROR(INDEX('nishita grading'!$E:$Q,MATCH($A10&"|"&$B10,'nishita grading'!$S:$S,0),COLUMN()-3),""),""))) -> 0 | I10: =IF($C10="faizan",IFERROR(INDEX('faizan grading'!$E:$Q,MATCH($A10&"|"&$B10,'faizan grading'!$S:$S,0),COLUMN()-3),""),IF($C10="romain",IFERROR(INDEX('romain grading'!$E:$Q,MATCH($A10&"|"&$B10,'romain grading'!$S:$S,0),COLUMN()-3),""),IF($C10="nishita",IFERROR(INDEX('nishita grading'!$E:$Q,MATCH($A10&"|"&$B10,'nishita grading'!$S:$S,0),COLUMN()-3),""),""))) -> 0 | J10: =IF($C10="faizan",IFERROR(INDEX('faizan grading'!$E:$Q,MATCH($A10&"|"&$B10,'faizan grading'!$S:$S,0),COLUMN()-3),""),IF($C10="romain",IFERROR(INDEX('romain grading'!$E:$Q,MATCH($A10&"|"&$B10,'romain grading'!$S:$S,0),COLUMN()-3),""),IF($C10="nishita",IFERROR(INDEX('nishita grading'!$E:$Q,MATCH($A10&"|"&$B10,'nishita grading'!$S:$S,0),COLUMN()-3),""),""))) -> 0 | K10: =IF($C10="faizan",IFERROR(INDEX('faizan grading'!$E:$Q,MATCH($A10&"|"&$B10,'faizan grading'!$S:$S,0),COLUMN()-3),""),IF($C10="romain",IFERROR(INDEX('romain grading'!$E:$Q,MATCH($A10&"|"&$B10,'romain grading'!$S:$S,0),COLUMN()-3),""),IF($C10="nishita",IFERROR(INDEX('nishita grading'!$E:$Q,MATCH($A10&"|"&$B10,'nishita grading'!$S:$S,0),COLUMN()-3),""),""))) -> 0 | ... P10: =IF($C10="faizan",IFERROR(INDEX('faizan grading'!$E:$Q,MATCH($A10&"|"&$B10,'faizan grading'!$S:$S,0),COLUMN()-3),""),IF($C10="romain",IFERROR(INDEX('romain grading'!$E:$Q,MATCH($A10&"|"&$B10,'romain grading'!$S:$S,0),COLUMN()-3),""),IF($C10="nishita",IFERROR(INDEX('nishita grading'!$E:$Q,MATCH($A10&"|"&$B10,'nishita grading'!$S:$S,0),COLUMN()-3),""),""))) -> 0 | Q10: =40-SUM(D10:P10) -> 40 | R10: =A10&"|"&B10 -> chaotic|0021
A11: chaotic | B11: 0021 | C11: romain | D11: =IF($C11="faizan",IFERROR(INDEX('faizan grading'!$E:$Q,MATCH($A11&"|"&$B11,'faizan grading'!$S:$S,0),COLUMN()-3),""),IF($C11="romain",IFERROR(INDEX('romain grading'!$E:$Q,MATCH($A11&"|"&$B11,'romain grading'!$S:$S,0),COLUMN()-3),""),IF($C11="nishita",IFERROR(INDEX('nishita grading'!$E:$Q,MATCH($A11&"|"&$B11,'nishita grading'!$S:$S,0),COLUMN()-3),""),""))) -> 0 | E11: =IF($C11="faizan",IFERROR(INDEX('faizan grading'!$E:$Q,MATCH($A11&"|"&$B11,'faizan grading'!$S:$S,0),COLUMN()-3),""),IF($C11="romain",IFERROR(INDEX('romain grading'!$E:$Q,MATCH($A11&"|"&$B11,'romain grading'!$S:$S,0),COLUMN()-3),""),IF($C11="nishita",IFERROR(INDEX('nishita grading'!$E:$Q,MATCH($A11&"|"&$B11,'nishita grading'!$S:$S,0),COLUMN()-3),""),""))) -> 0 | F11: =IF($C11="faizan",IFERROR(INDEX('faizan grading'!$E:$Q,MATCH($A11&"|"&$B11,'faizan grading'!$S:$S,0),COLUMN()-3),""),IF($C11="romain",IFERROR(INDEX('romain grading'!$E:$Q,MATCH($A11&"|"&$B11,'romain grading'!$S:$S,0),COLUMN()-3),""),IF($C11="nishita",IFERROR(INDEX('nishita grading'!$E:$Q,MATCH($A11&"|"&$B11,'nishita grading'!$S:$S,0),COLUMN()-3),""),""))) -> 0 | G11: =IF($C11="faizan",IFERROR(INDEX('faizan grading'!$E:$Q,MATCH($A11&"|"&$B11,'faizan grading'!$S:$S,0),COLUMN()-3),""),IF($C11="romain",IFERROR(INDEX('romain grading'!$E:$Q,MATCH($A11&"|"&$B11,'romain grading'!$S:$S,0),COLUMN()-3),""),IF($C11="nishita",IFERROR(INDEX('nishita grading'!$E:$Q,MATCH($A11&"|"&$B11,'nishita grading'!$S:$S,0),COLUMN()-3),""),""))) -> 0 | H11: =IF($C11="faizan",IFERROR(INDEX('faizan grading'!$E:$Q,MATCH($A11&"|"&$B11,'faizan grading'!$S:$S,0),COLUMN()-3),""),IF($C11="romain",IFERROR(INDEX('romain grading'!$E:$Q,MATCH($A11&"|"&$B11,'romain grading'!$S:$S,0),COLUMN()-3),""),IF($C11="nishita",IFERROR(INDEX('nishita grading'!$E:$Q,MATCH($A11&"|"&$B11,'nishita grading'!$S:$S,0),COLUMN()-3),""),""))) -> 0 | I11: =IF($C11="faizan",IFERROR(INDEX('faizan grading'!$E:$Q,MATCH($A11&"|"&$B11,'faizan grading'!$S:$S,0),COLUMN()-3),""),IF($C11="romain",IFERROR(INDEX('romain grading'!$E:$Q,MATCH($A11&"|"&$B11,'romain grading'!$S:$S,0),COLUMN()-3),""),IF($C11="nishita",IFERROR(INDEX('nishita grading'!$E:$Q,MATCH($A11&"|"&$B11,'nishita grading'!$S:$S,0),COLUMN()-3),""),""))) -> 0 | J11: =IF($C11="faizan",IFERROR(INDEX('faizan grading'!$E:$Q,MATCH($A11&"|"&$B11,'faizan grading'!$S:$S,0),COLUMN()-3),""),IF($C11="romain",IFERROR(INDEX('romain grading'!$E:$Q,MATCH($A11&"|"&$B11,'romain grading'!$S:$S,0),COLUMN()-3),""),IF($C11="nishita",IFERROR(INDEX('nishita grading'!$E:$Q,MATCH($A11&"|"&$B11,'nishita grading'!$S:$S,0),COLUMN()-3),""),""))) -> 0 | K11: =IF($C11="faizan",IFERROR(INDEX('faizan grading'!$E:$Q,MATCH($A11&"|"&$B11,'faizan grading'!$S:$S,0),COLUMN()-3),""),IF($C11="romain",IFERROR(INDEX('romain grading'!$E:$Q,MATCH($A11&"|"&$B11,'romain grading'!$S:$S,0),COLUMN()-3),""),IF($C11="nishita",IFERROR(INDEX('nishita grading'!$E:$Q,MATCH($A11&"|"&$B11,'nishita grading'!$S:$S,0),COLUMN()-3),""),""))) -> 0 | ... P11: =IF($C11="faizan",IFERROR(INDEX('faizan grading'!$E:$Q,MATCH($A11&"|"&$B11,'faizan grading'!$S:$S,0),COLUMN()-3),""),IF($C11="romain",IFERROR(INDEX('romain grading'!$E:$Q,MATCH($A11&"|"&$B11,'romain grading'!$S:$S,0),COLUMN()-3),""),IF($C11="nishita",IFERROR(INDEX('nishita grading'!$E:$Q,MATCH($A11&"|"&$B11,'nishita grading'!$S:$S,0),COLUMN()-3),""),""))) -> 0 | Q11: =40-SUM(D11:P11) -> 40 | R11: =A11&"|"&B11 -> chaotic|0021
A12: chaotic | B12: 0021 | C12: nishita | D12: =IF($C12="faizan",IFERROR(INDEX('faizan grading'!$E:$Q,MATCH($A12&"|"&$B12,'faizan grading'!$S:$S,0),COLUMN()-3),""),IF($C12="romain",IFERROR(INDEX('romain grading'!$E:$Q,MATCH($A12&"|"&$B12,'romain grading'!$S:$S,0),COLUMN()-3),""),IF($C12="nishita",IFERROR(INDEX('nishita grading'!$E:$Q,MATCH($A12&"|"&$B12,'nishita grading'!$S:$S,0),COLUMN()-3),""),""))) -> 0 | E12: =IF($C12="faizan",IFERROR(INDEX('faizan grading'!$E:$Q,MATCH($A12&"|"&$B12,'faizan grading'!$S:$S,0),COLUMN()-3),""),IF($C12="romain",IFERROR(INDEX('romain grading'!$E:$Q,MATCH($A12&"|"&$B12,'romain grading'!$S:$S,0),COLUMN()-3),""),IF($C12="nishita",IFERROR(INDEX('nishita grading'!$E:$Q,MATCH($A12&"|"&$B12,'nishita grading'!$S:$S,0),COLUMN()-3),""),""))) -> 0 | F12: =IF($C12="faizan",IFERROR(INDEX('faizan grading'!$E:$Q,MATCH($A12&"|"&$B12,'faizan grading'!$S:$S,0),COLUMN()-3),""),IF($C12="romain",IFERROR(INDEX('romain grading'!$E:$Q,MATCH($A12&"|"&$B12,'romain grading'!$S:$S,0),COLUMN()-3),""),IF($C12="nishita",IFERROR(INDEX('nishita grading'!$E:$Q,MATCH($A12&"|"&$B12,'nishita grading'!$S:$S,0),COLUMN()-3),""),""))) -> 6 | G12: =IF($C12="faizan",IFERROR(INDEX('faizan grading'!$E:$Q,MATCH($A12&"|"&$B12,'faizan grading'!$S:$S,0),COLUMN()-3),""),IF($C12="romain",IFERROR(INDEX('romain grading'!$E:$Q,MATCH($A12&"|"&$B12,'romain grading'!$S:$S,0),COLUMN()-3),""),IF($C12="nishita",IFERROR(INDEX('nishita grading'!$E:$Q,MATCH($A12&"|"&$B12,'nishita grading'!$S:$S,0),COLUMN()-3),""),""))) -> 0 | H12: =IF($C12="faizan",IFERROR(INDEX('faizan grading'!$E:$Q,MATCH($A12&"|"&$B12,'faizan grading'!$S:$S,0),COLUMN()-3),""),IF($C12="romain",IFERROR(INDEX('romain grading'!$E:$Q,MATCH($A12&"|"&$B12,'romain grading'!$S:$S,0),COLUMN()-3),""),IF($C12="nishita",IFERROR(INDEX('nishita grading'!$E:$Q,MATCH($A12&"|"&$B12,'nishita grading'!$S:$S,0),COLUMN()-3),""),""))) -> 0 | I12: =IF($C12="faizan",IFERROR(INDEX('faizan grading'!$E:$Q,MATCH($A12&"|"&$B12,'faizan grading'!$S:$S,0),COLUMN()-3),""),IF($C12="romain",IFERROR(INDEX('romain grading'!$E:$Q,MATCH($A12&"|"&$B12,'romain grading'!$S:$S,0),COLUMN()-3),""),IF($C12="nishita",IFERROR(INDEX('nishita grading'!$E:$Q,MATCH($A12&"|"&$B12,'nishita grading'!$S:$S,0),COLUMN()-3),""),""))) -> 0 | J12: =IF($C12="faizan",IFERROR(INDEX('faizan grading'!$E:$Q,MATCH($A12&"|"&$B12,'faizan grading'!$S:$S,0),COLUMN()-3),""),IF($C12="romain",IFERROR(INDEX('romain grading'!$E:$Q,MATCH($A12&"|"&$B12,'romain grading'!$S:$S,0),COLUMN()-3),""),IF($C12="nishita",IFERROR(INDEX('nishita grading'!$E:$Q,MATCH($A12&"|"&$B12,'nishita grading'!$S:$S,0),COLUMN()-3),""),""))) -> 0 | K12: =IF($C12="faizan",IFERROR(INDEX('faizan grading'!$E:$Q,MATCH($A12&"|"&$B12,'faizan grading'!$S:$S,0),COLUMN()-3),""),IF($C12="romain",IFERROR(INDEX('romain grading'!$E:$Q,MATCH($A12&"|"&$B12,'romain grading'!$S:$S,0),COLUMN()-3),""),IF($C12="nishita",IFERROR(INDEX('nishita grading'!$E:$Q,MATCH($A12&"|"&$B12,'nishita grading'!$S:$S,0),COLUMN()-3),""),""))) -> 4 | ... P12: =IF($C12="faizan",IFERROR(INDEX('faizan grading'!$E:$Q,MATCH($A12&"|"&$B12,'faizan grading'!$S:$S,0),COLUMN()-3),""),IF($C12="romain",IFERROR(INDEX('romain grading'!$E:$Q,MATCH($A12&"|"&$B12,'romain grading'!$S:$S,0),COLUMN()-3),""),IF($C12="nishita",IFERROR(INDEX('nishita grading'!$E:$Q,MATCH($A12&"|"&$B12,'nishita grading'!$S:$S,0),COLUMN()-3),""),""))) -> 0 | Q12: =40-SUM(D12:P12) -> 30 | R12: =A12&"|"&B12 -> chaotic|0021
A13: chaotic | B13: 0021 | C13: claude | D13: 0 | E13: 0 | F13: 6 | G13: 0 | H13: 0 | I13: 0 | J13: 0 | K13: 0 | L13: 0 | M13: 0 | N13: 0 | O13: 0 | P13: 2 | Q13: =40-SUM(D13:P13) -> 32 | R13: =A13&"|"&B13 -> chaotic|0021
A14: chaotic | B14: 0039 | C14: faizan | D14: =IF($C14="faizan",IFERROR(INDEX('faizan grading'!$E:$Q,MATCH($A14&"|"&$B14,'faizan grading'!$S:$S,0),COLUMN()-3),""),IF($C14="romain",IFERROR(INDEX('romain grading'!$E:$Q,MATCH($A14&"|"&$B14,'romain grading'!$S:$S,0),COLUMN()-3),""),IF($C14="nishita",IFERROR(INDEX('nishita grading'!$E:$Q,MATCH($A14&"|"&$B14,'nishita grading'!$S:$S,0),COLUMN()-3),""),""))) -> 0 | E14: =IF($C14="faizan",IFERROR(INDEX('faizan grading'!$E:$Q,MATCH($A14&"|"&$B14,'faizan grading'!$S:$S,0),COLUMN()-3),""),IF($C14="romain",IFERROR(INDEX('romain grading'!$E:$Q,MATCH($A14&"|"&$B14,'romain grading'!$S:$S,0),COLUMN()-3),""),IF($C14="nishita",IFERROR(INDEX('nishita grading'!$E:$Q,MATCH($A14&"|"&$B14,'nishita grading'!$S:$S,0),COLUMN()-3),""),""))) -> 0 | F14: =IF($C14="faizan",IFERROR(INDEX('faizan grading'!$E:$Q,MATCH($A14&"|"&$B14,'faizan grading'!$S:$S,0),COLUMN()-3),""),IF($C14="romain",IFERROR(INDEX('romain grading'!$E:$Q,MATCH($A14&"|"&$B14,'romain grading'!$S:$S,0),COLUMN()-3),""),IF($C14="nishita",IFERROR(INDEX('nishita grading'!$E:$Q,MATCH($A14&"|"&$B14,'nishita grading'!$S:$S,0),COLUMN()-3),""),""))) -> 0 | G14: =IF($C14="faizan",IFERROR(INDEX('faizan grading'!$E:$Q,MATCH($A14&"|"&$B14,'faizan grading'!$S:$S,0),COLUMN()-3),""),IF($C14="romain",IFERROR(INDEX('romain grading'!$E:$Q,MATCH($A14&"|"&$B14,'romain grading'!$S:$S,0),COLUMN()-3),""),IF($C14="nishita",IFERROR(INDEX('nishita grading'!$E:$Q,MATCH($A14&"|"&$B14,'nishita grading'!$S:$S,0),COLUMN()-3),""),""))) -> 0 | H14: =IF($C14="faizan",IFERROR(INDEX('faizan grading'!$E:$Q,MATCH($A14&"|"&$B14,'faizan grading'!$S:$S,0),COLUMN()-3),""),IF($C14="romain",IFERROR(INDEX('romain grading'!$E:$Q,MATCH($A14&"|"&$B14,'romain grading'!$S:$S,0),COLUMN()-3),""),IF($C14="nishita",IFERROR(INDEX('nishita grading'!$E:$Q,MATCH($A14&"|"&$B14,'nishita grading'!$S:$S,0),COLUMN()-3),""),""))) -> 0 | I14: =IF($C14="faizan",IFERROR(INDEX('faizan grading'!$E:$Q,MATCH($A14&"|"&$B14,'faizan grading'!$S:$S,0),COLUMN()-3),""),IF($C14="romain",IFERROR(INDEX('romain grading'!$E:$Q,MATCH($A14&"|"&$B14,'romain grading'!$S:$S,0),COLUMN()-3),""),IF($C14="nishita",IFERROR(INDEX('nishita grading'!$E:$Q,MATCH($A14&"|"&$B14,'nishita grading'!$S:$S,0),COLUMN()-3),""),""))) -> 0 | J14: =IF($C14="faizan",IFERROR(INDEX('faizan grading'!$E:$Q,MATCH($A14&"|"&$B14,'faizan grading'!$S:$S,0),COLUMN()-3),""),IF($C14="romain",IFERROR(INDEX('romain grading'!$E:$Q,MATCH($A14&"|"&$B14,'romain grading'!$S:$S,0),COLUMN()-3),""),IF($C14="nishita",IFERROR(INDEX('nishita grading'!$E:$Q,MATCH($A14&"|"&$B14,'nishita grading'!$S:$S,0),COLUMN()-3),""),""))) -> 0 | K14: =IF($C14="faizan",IFERROR(INDEX('faizan grading'!$E:$Q,MATCH($A14&"|"&$B14,'faizan grading'!$S:$S,0),COLUMN()-3),""),IF($C14="romain",IFERROR(INDEX('romain grading'!$E:$Q,MATCH($A14&"|"&$B14,'romain grading'!$S:$S,0),COLUMN()-3),""),IF($C14="nishita",IFERROR(INDEX('nishita grading'!$E:$Q,MATCH($A14&"|"&$B14,'nishita grading'!$S:$S,0),COLUMN()-3),""),""))) -> 0 | ... P14: =IF($C14="faizan",IFERROR(INDEX('faizan grading'!$E:$Q,MATCH($A14&"|"&$B14,'faizan grading'!$S:$S,0),COLUMN()-3),""),IF($C14="romain",IFERROR(INDEX('romain grading'!$E:$Q,MATCH($A14&"|"&$B14,'romain grading'!$S:$S,0),COLUMN()-3),""),IF($C14="nishita",IFERROR(INDEX('nishita grading'!$E:$Q,MATCH($A14&"|"&$B14,'nishita grading'!$S:$S,0),COLUMN()-3),""),""))) -> 0 | Q14: =40-SUM(D14:P14) -> 40 | R14: =A14&"|"&B14 -> chaotic|0039
A15: chaotic | B15: 0039 | C15: romain | D15: =IF($C15="faizan",IFERROR(INDEX('faizan grading'!$E:$Q,MATCH($A15&"|"&$B15,'faizan grading'!$S:$S,0),COLUMN()-3),""),IF($C15="romain",IFERROR(INDEX('romain grading'!$E:$Q,MATCH($A15&"|"&$B15,'romain grading'!$S:$S,0),COLUMN()-3),""),IF($C15="nishita",IFERROR(INDEX('nishita grading'!$E:$Q,MATCH($A15&"|"&$B15,'nishita grading'!$S:$S,0),COLUMN()-3),""),""))) -> 0 | E15: =IF($C15="faizan",IFERROR(INDEX('faizan grading'!$E:$Q,MATCH($A15&"|"&$B15,'faizan grading'!$S:$S,0),COLUMN()-3),""),IF($C15="romain",IFERROR(INDEX('romain grading'!$E:$Q,MATCH($A15&"|"&$B15,'romain grading'!$S:$S,0),COLUMN()-3),""),IF($C15="nishita",IFERROR(INDEX('nishita grading'!$E:$Q,MATCH($A15&"|"&$B15,'nishita grading'!$S:$S,0),COLUMN()-3),""),""))) -> 0 | F15: =IF($C15="faizan",IFERROR(INDEX('faizan grading'!$E:$Q,MATCH($A15&"|"&$B15,'faizan grading'!$S:$S,0),COLUMN()-3),""),IF($C15="romain",IFERROR(INDEX('romain grading'!$E:$Q,MATCH($A15&"|"&$B15,'romain grading'!$S:$S,0),COLUMN()-3),""),IF($C15="nishita",IFERROR(INDEX('nishita grading'!$E:$Q,MATCH($A15&"|"&$B15,'nishita grading'!$S:$S,0),COLUMN()-3),""),""))) -> 0 | G15: =IF($C15="faizan",IFERROR(INDEX('faizan grading'!$E:$Q,MATCH($A15&"|"&$B15,'faizan grading'!$S:$S,0),COLUMN()-3),""),IF($C15="romain",IFERROR(INDEX('romain grading'!$E:$Q,MATCH($A15&"|"&$B15,'romain grading'!$S:$S,0),COLUMN()-3),""),IF($C15="nishita",IFERROR(INDEX('nishita grading'!$E:$Q,MATCH($A15&"|"&$B15,'nishita grading'!$S:$S,0),COLUMN()-3),""),""))) -> 0 | H15: =IF($C15="faizan",IFERROR(INDEX('faizan grading'!$E:$Q,MATCH($A15&"|"&$B15,'faizan grading'!$S:$S,0),COLUMN()-3),""),IF($C15="romain",IFERROR(INDEX('romain grading'!$E:$Q,MATCH($A15&"|"&$B15,'romain grading'!$S:$S,0),COLUMN()-3),""),IF($C15="nishita",IFERROR(INDEX('nishita grading'!$E:$Q,MATCH($A15&"|"&$B15,'nishita grading'!$S:$S,0),COLUMN()-3),""),""))) -> 0 | I15: =IF($C15="faizan",IFERROR(INDEX('faizan grading'!$E:$Q,MATCH($A15&"|"&$B15,'faizan grading'!$S:$S,0),COLUMN()-3),""),IF($C15="romain",IFERROR(INDEX('romain grading'!$E:$Q,MATCH($A15&"|"&$B15,'romain grading'!$S:$S,0),COLUMN()-3),""),IF($C15="nishita",IFERROR(INDEX('nishita grading'!$E:$Q,MATCH($A15&"|"&$B15,'nishita grading'!$S:$S,0),COLUMN()-3),""),""))) -> 0 | J15: =IF($C15="faizan",IFERROR(INDEX('faizan grading'!$E:$Q,MATCH($A15&"|"&$B15,'faizan grading'!$S:$S,0),COLUMN()-3),""),IF($C15="romain",IFERROR(INDEX('romain grading'!$E:$Q,MATCH($A15&"|"&$B15,'romain grading'!$S:$S,0),COLUMN()-3),""),IF($C15="nishita",IFERROR(INDEX('nishita grading'!$E:$Q,MATCH($A15&"|"&$B15,'nishita grading'!$S:$S,0),COLUMN()-3),""),""))) -> 0 | K15: =IF($C15="faizan",IFERROR(INDEX('faizan grading'!$E:$Q,MATCH($A15&"|"&$B15,'faizan grading'!$S:$S,0),COLUMN()-3),""),IF($C15="romain",IFERROR(INDEX('romain grading'!$E:$Q,MATCH($A15&"|"&$B15,'romain grading'!$S:$S,0),COLUMN()-3),""),IF($C15="nishita",IFERROR(INDEX('nishita grading'!$E:$Q,MATCH($A15&"|"&$B15,'nishita grading'!$S:$S,0),COLUMN()-3),""),""))) -> 0 | ... P15: =IF($C15="faizan",IFERROR(INDEX('faizan grading'!$E:$Q,MATCH($A15&"|"&$B15,'faizan grading'!$S:$S,0),COLUMN()-3),""),IF($C15="romain",IFERROR(INDEX('romain grading'!$E:$Q,MATCH($A15&"|"&$B15,'romain grading'!$S:$S,0),COLUMN()-3),""),IF($C15="nishita",IFERROR(INDEX('nishita grading'!$E:$Q,MATCH($A15&"|"&$B15,'nishita grading'!$S:$S,0),COLUMN()-3),""),""))) -> 0 | Q15: =40-SUM(D15:P15) -> 40 | R15: =A15&"|"&B15 -> chaotic|0039
A16: chaotic | B16: 0039 | C16: nishita | D16: =IF($C16="faizan",IFERROR(INDEX('faizan grading'!$E:$Q,MATCH($A16&"|"&$B16,'faizan grading'!$S:$S,0),COLUMN()-3),""),IF($C16="romain",IFERROR(INDEX('romain grading'!$E:$Q,MATCH($A16&"|"&$B16,'romain grading'!$S:$S,0),COLUMN()-3),""),IF($C16="nishita",IFERROR(INDEX('nishita grading'!$E:$Q,MATCH($A16&"|"&$B16,'nishita grading'!$S:$S,0),COLUMN()-3),""),""))) -> 0 | E16: =IF($C16="faizan",IFERROR(INDEX('faizan grading'!$E:$Q,MATCH($A16&"|"&$B16,'faizan grading'!$S:$S,0),COLUMN()-3),""),IF($C16="romain",IFERROR(INDEX('romain grading'!$E:$Q,MATCH($A16&"|"&$B16,'romain grading'!$S:$S,0),COLUMN()-3),""),IF($C16="nishita",IFERROR(INDEX('nishita grading'!$E:$Q,MATCH($A16&"|"&$B16,'nishita grading'!$S:$S,0),COLUMN()-3),""),""))) -> 0 | F16: =IF($C16="faizan",IFERROR(INDEX('faizan grading'!$E:$Q,MATCH($A16&"|"&$B16,'faizan grading'!$S:$S,0),COLUMN()-3),""),IF($C16="romain",IFERROR(INDEX('romain grading'!$E:$Q,MATCH($A16&"|"&$B16,'romain grading'!$S:$S,0),COLUMN()-3),""),IF($C16="nishita",IFERROR(INDEX('nishita grading'!$E:$Q,MATCH($A16&"|"&$B16,'nishita grading'!$S:$S,0),COLUMN()-3),""),""))) -> 6 | G16: =IF($C16="faizan",IFERROR(INDEX('faizan grading'!$E:$Q,MATCH($A16&"|"&$B16,'faizan grading'!$S:$S,0),COLUMN()-3),""),IF($C16="romain",IFERROR(INDEX('romain grading'!$E:$Q,MATCH($A16&"|"&$B16,'romain grading'!$S:$S,0),COLUMN()-3),""),IF($C16="nishita",IFERROR(INDEX('nishita grading'!$E:$Q,MATCH($A16&"|"&$B16,'nishita grading'!$S:$S,0),COLUMN()-3),""),""))) -> 0 | H16: =IF($C16="faizan",IFERROR(INDEX('faizan grading'!$E:$Q,MATCH($A16&"|"&$B16,'faizan grading'!$S:$S,0),COLUMN()-3),""),IF($C16="romain",IFERROR(INDEX('romain grading'!$E:$Q,MATCH($A16&"|"&$B16,'romain grading'!$S:$S,0),COLUMN()-3),""),IF($C16="nishita",IFERROR(INDEX('nishita grading'!$E:$Q,MATCH($A16&"|"&$B16,'nishita grading'!$S:$S,0),COLUMN()-3),""),""))) -> 0 | I16: =IF($C16="faizan",IFERROR(INDEX('faizan grading'!$E:$Q,MATCH($A16&"|"&$B16,'faizan grading'!$S:$S,0),COLUMN()-3),""),IF($C16="romain",IFERROR(INDEX('romain grading'!$E:$Q,MATCH($A16&"|"&$B16,'romain grading'!$S:$S,0),COLUMN()-3),""),IF($C16="nishita",IFERROR(INDEX('nishita grading'!$E:$Q,MATCH($A16&"|"&$B16,'nishita grading'!$S:$S,0),COLUMN()-3),""),""))) -> 0 | J16: =IF($C16="faizan",IFERROR(INDEX('faizan grading'!$E:$Q,MATCH($A16&"|"&$B16,'faizan grading'!$S:$S,0),COLUMN()-3),""),IF($C16="romain",IFERROR(INDEX('romain grading'!$E:$Q,MATCH($A16&"|"&$B16,'romain grading'!$S:$S,0),COLUMN()-3),""),IF($C16="nishita",IFERROR(INDEX('nishita grading'!$E:$Q,MATCH($A16&"|"&$B16,'nishita grading'!$S:$S,0),COLUMN()-3),""),""))) -> 0 | K16: =IF($C16="faizan",IFERROR(INDEX('faizan grading'!$E:$Q,MATCH($A16&"|"&$B16,'faizan grading'!$S:$S,0),COLUMN()-3),""),IF($C16="romain",IFERROR(INDEX('romain grading'!$E:$Q,MATCH($A16&"|"&$B16,'romain grading'!$S:$S,0),COLUMN()-3),""),IF($C16="nishita",IFERROR(INDEX('nishita grading'!$E:$Q,MATCH($A16&"|"&$B16,'nishita grading'!$S:$S,0),COLUMN()-3),""),""))) -> 4 | ... P16: =IF($C16="faizan",IFERROR(INDEX('faizan grading'!$E:$Q,MATCH($A16&"|"&$B16,'faizan grading'!$S:$S,0),COLUMN()-3),""),IF($C16="romain",IFERROR(INDEX('romain grading'!$E:$Q,MATCH($A16&"|"&$B16,'romain grading'!$S:$S,0),COLUMN()-3),""),IF($C16="nishita",IFERROR(INDEX('nishita grading'!$E:$Q,MATCH($A16&"|"&$B16,'nishita grading'!$S:$S,0),COLUMN()-3),""),""))) -> 0 | Q16: =40-SUM(D16:P16) -> 30 | R16: =A16&"|"&B16 -> chaotic|0039
A17: chaotic | B17: 0039 | C17: claude | D17: 0 | E17: 0 | F17: 6 | G17: 0 | H17: 0 | I17: 0 | J17: 0 | K17: 0 | L17: 0 | M17: 0 | N17: 0 | O17: 0 | P17: 0 | Q17: =40-SUM(D17:P17) -> 34 | R17: =A17&"|"&B17 -> chaotic|0039
A18: chaotic | B18: 0062 | C18: faizan | D18: =IF($C18="faizan",IFERROR(INDEX('faizan grading'!$E:$Q,MATCH($A18&"|"&$B18,'faizan grading'!$S:$S,0),COLUMN()-3),""),IF($C18="romain",IFERROR(INDEX('romain grading'!$E:$Q,MATCH($A18&"|"&$B18,'romain grading'!$S:$S,0),COLUMN()-3),""),IF($C18="nishita",IFERROR(INDEX('nishita grading'!$E:$Q,MATCH($A18&"|"&$B18,'nishita grading'!$S:$S,0),COLUMN()-3),""),""))) -> 0 | E18: =IF($C18="faizan",IFERROR(INDEX('faizan grading'!$E:$Q,MATCH($A18&"|"&$B18,'faizan grading'!$S:$S,0),COLUMN()-3),""),IF($C18="romain",IFERROR(INDEX('romain grading'!$E:$Q,MATCH($A18&"|"&$B18,'romain grading'!$S:$S,0),COLUMN()-3),""),IF($C18="nishita",IFERROR(INDEX('nishita grading'!$E:$Q,MATCH($A18&"|"&$B18,'nishita grading'!$S:$S,0),COLUMN()-3),""),""))) -> 0 | F18: =IF($C18="faizan",IFERROR(INDEX('faizan grading'!$E:$Q,MATCH($A18&"|"&$B18,'faizan grading'!$S:$S,0),COLUMN()-3),""),IF($C18="romain",IFERROR(INDEX('romain grading'!$E:$Q,MATCH($A18&"|"&$B18,'romain grading'!$S:$S,0),COLUMN()-3),""),IF($C18="nishita",IFERROR(INDEX('nishita grading'!$E:$Q,MATCH($A18&"|"&$B18,'nishita grading'!$S:$S,0),COLUMN()-3),""),""))) -> 0 | G18: =IF($C18="faizan",IFERROR(INDEX('faizan grading'!$E:$Q,MATCH($A18&"|"&$B18,'faizan grading'!$S:$S,0),COLUMN()-3),""),IF($C18="romain",IFERROR(INDEX('romain grading'!$E:$Q,MATCH($A18&"|"&$B18,'romain grading'!$S:$S,0),COLUMN()-3),""),IF($C18="nishita",IFERROR(INDEX('nishita grading'!$E:$Q,MATCH($A18&"|"&$B18,'nishita grading'!$S:$S,0),COLUMN()-3),""),""))) -> 0 | H18: =IF($C18="faizan",IFERROR(INDEX('faizan grading'!$E:$Q,MATCH($A18&"|"&$B18,'faizan grading'!$S:$S,0),COLUMN()-3),""),IF($C18="romain",IFERROR(INDEX('romain grading'!$E:$Q,MATCH($A18&"|"&$B18,'romain grading'!$S:$S,0),COLUMN()-3),""),IF($C18="nishita",IFERROR(INDEX('nishita grading'!$E:$Q,MATCH($A18&"|"&$B18,'nishita grading'!$S:$S,0),COLUMN()-3),""),""))) -> 0 | I18: =IF($C18="faizan",IFERROR(INDEX('faizan grading'!$E:$Q,MATCH($A18&"|"&$B18,'faizan grading'!$S:$S,0),COLUMN()-3),""),IF($C18="romain",IFERROR(INDEX('romain grading'!$E:$Q,MATCH($A18&"|"&$B18,'romain grading'!$S:$S,0),COLUMN()-3),""),IF($C18="nishita",IFERROR(INDEX('nishita grading'!$E:$Q,MATCH($A18&"|"&$B18,'nishita grading'!$S:$S,0),COLUMN()-3),""),""))) -> 0 | J18: =IF($C18="faizan",IFERROR(INDEX('faizan grading'!$E:$Q,MATCH($A18&"|"&$B18,'faizan grading'!$S:$S,0),COLUMN()-3),""),IF($C18="romain",IFERROR(INDEX('romain grading'!$E:$Q,MATCH($A18&"|"&$B18,'romain grading'!$S:$S,0),COLUMN()-3),""),IF($C18="nishita",IFERROR(INDEX('nishita grading'!$E:$Q,MATCH($A18&"|"&$B18,'nishita grading'!$S:$S,0),COLUMN()-3),""),""))) -> 0 | K18: =IF($C18="faizan",IFERROR(INDEX('faizan grading'!$E:$Q,MATCH($A18&"|"&$B18,'faizan grading'!$S:$S,0),COLUMN()-3),""),IF($C18="romain",IFERROR(INDEX('romain grading'!$E:$Q,MATCH($A18&"|"&$B18,'romain grading'!$S:$S,0),COLUMN()-3),""),IF($C18="nishita",IFERROR(INDEX('nishita grading'!$E:$Q,MATCH($A18&"|"&$B18,'nishita grading'!$S:$S,0),COLUMN()-3),""),""))) -> 0 | ... P18: =IF($C18="faizan",IFERROR(INDEX('faizan grading'!$E:$Q,MATCH($A18&"|"&$B18,'faizan grading'!$S:$S,0),COLUMN()-3),""),IF($C18="romain",IFERROR(INDEX('romain grading'!$E:$Q,MATCH($A18&"|"&$B18,'romain grading'!$S:$S,0),COLUMN()-3),""),IF($C18="nishita",IFERROR(INDEX('nishita grading'!$E:$Q,MATCH($A18&"|"&$B18,'nishita grading'!$S:$S,0),COLUMN()-3),""),""))) -> 0 | Q18: =40-SUM(D18:P18) -> 40 | R18: =A18&"|"&B18 -> chaotic|0062
A19: chaotic | B19: 0062 | C19: romain | D19: =IF($C19="faizan",IFERROR(INDEX('faizan grading'!$E:$Q,MATCH($A19&"|"&$B19,'faizan grading'!$S:$S,0),COLUMN()-3),""),IF($C19="romain",IFERROR(INDEX('romain grading'!$E:$Q,MATCH($A19&"|"&$B19,'romain grading'!$S:$S,0),COLUMN()-3),""),IF($C19="nishita",IFERROR(INDEX('nishita grading'!$E:$Q,MATCH($A19&"|"&$B19,'nishita grading'!$S:$S,0),COLUMN()-3),""),""))) -> 0 | E19: =IF($C19="faizan",IFERROR(INDEX('faizan grading'!$E:$Q,MATCH($A19&"|"&$B19,'faizan grading'!$S:$S,0),COLUMN()-3),""),IF($C19="romain",IFERROR(INDEX('romain grading'!$E:$Q,MATCH($A19&"|"&$B19,'romain grading'!$S:$S,0),COLUMN()-3),""),IF($C19="nishita",IFERROR(INDEX('nishita grading'!$E:$Q,MATCH($A19&"|"&$B19,'nishita grading'!$S:$S,0),COLUMN()-3),""),""))) -> 0 | F19: =IF($C19="faizan",IFERROR(INDEX('faizan grading'!$E:$Q,MATCH($A19&"|"&$B19,'faizan grading'!$S:$S,0),COLUMN()-3),""),IF($C19="romain",IFERROR(INDEX('romain grading'!$E:$Q,MATCH($A19&"|"&$B19,'romain grading'!$S:$S,0),COLUMN()-3),""),IF($C19="nishita",IFERROR(INDEX('nishita grading'!$E:$Q,MATCH($A19&"|"&$B19,'nishita grading'!$S:$S,0),COLUMN()-3),""),""))) -> 0 | G19: =IF($C19="faizan",IFERROR(INDEX('faizan grading'!$E:$Q,MATCH($A19&"|"&$B19,'faizan grading'!$S:$S,0),COLUMN()-3),""),IF($C19="romain",IFERROR(INDEX('romain grading'!$E:$Q,MATCH($A19&"|"&$B19,'romain grading'!$S:$S,0),COLUMN()-3),""),IF($C19="nishita",IFERROR(INDEX('nishita grading'!$E:$Q,MATCH($A19&"|"&$B19,'nishita grading'!$S:$S,0),COLUMN()-3),""),""))) -> 0 | H19: =IF($C19="faizan",IFERROR(INDEX('faizan grading'!$E:$Q,MATCH($A19&"|"&$B19,'faizan grading'!$S:$S,0),COLUMN()-3),""),IF($C19="romain",IFERROR(INDEX('romain grading'!$E:$Q,MATCH($A19&"|"&$B19,'romain grading'!$S:$S,0),COLUMN()-3),""),IF($C19="nishita",IFERROR(INDEX('nishita grading'!$E:$Q,MATCH($A19&"|"&$B19,'nishita grading'!$S:$S,0),COLUMN()-3),""),""))) -> 0 | I19: =IF($C19="faizan",IFERROR(INDEX('faizan grading'!$E:$Q,MATCH($A19&"|"&$B19,'faizan grading'!$S:$S,0),COLUMN()-3),""),IF($C19="romain",IFERROR(INDEX('romain grading'!$E:$Q,MATCH($A19&"|"&$B19,'romain grading'!$S:$S,0),COLUMN()-3),""),IF($C19="nishita",IFERROR(INDEX('nishita grading'!$E:$Q,MATCH($A19&"|"&$B19,'nishita grading'!$S:$S,0),COLUMN()-3),""),""))) -> 0 | J19: =IF($C19="faizan",IFERROR(INDEX('faizan grading'!$E:$Q,MATCH($A19&"|"&$B19,'faizan grading'!$S:$S,0),COLUMN()-3),""),IF($C19="romain",IFERROR(INDEX('romain grading'!$E:$Q,MATCH($A19&"|"&$B19,'romain grading'!$S:$S,0),COLUMN()-3),""),IF($C19="nishita",IFERROR(INDEX('nishita grading'!$E:$Q,MATCH($A19&"|"&$B19,'nishita grading'!$S:$S,0),COLUMN()-3),""),""))) -> 0 | K19: =IF($C19="faizan",IFERROR(INDEX('faizan grading'!$E:$Q,MATCH($A19&"|"&$B19,'faizan grading'!$S:$S,0),COLUMN()-3),""),IF($C19="romain",IFERROR(INDEX('romain grading'!$E:$Q,MATCH($A19&"|"&$B19,'romain grading'!$S:$S,0),COLUMN()-3),""),IF($C19="nishita",IFERROR(INDEX('nishita grading'!$E:$Q,MATCH($A19&"|"&$B19,'nishita grading'!$S:$S,0),COLUMN()-3),""),""))) -> 0 | ... P19: =IF($C19="faizan",IFERROR(INDEX('faizan grading'!$E:$Q,MATCH($A19&"|"&$B19,'faizan grading'!$S:$S,0),COLUMN()-3),""),IF($C19="romain",IFERROR(INDEX('romain grading'!$E:$Q,MATCH($A19&"|"&$B19,'romain grading'!$S:$S,0),COLUMN()-3),""),IF($C19="nishita",IFERROR(INDEX('nishita grading'!$E:$Q,MATCH($A19&"|"&$B19,'nishita grading'!$S:$S,0),COLUMN()-3),""),""))) -> 0 | Q19: =40-SUM(D19:P19) -> 40 | R19: =A19&"|"&B19 -> chaotic|0062
A20: chaotic | B20: 0062 | C20: nishita | D20: =IF($C20="faizan",IFERROR(INDEX('faizan grading'!$E:$Q,MATCH($A20&"|"&$B20,'faizan grading'!$S:$S,0),COLUMN()-3),""),IF($C20="romain",IFERROR(INDEX('romain grading'!$E:$Q,MATCH($A20&"|"&$B20,'romain grading'!$S:$S,0),COLUMN()-3),""),IF($C20="nishita",IFERROR(INDEX('nishita grading'!$E:$Q,MATCH($A20&"|"&$B20,'nishita grading'!$S:$S,0),COLUMN()-3),""),""))) -> 0 | E20: =IF($C20="faizan",IFERROR(INDEX('faizan grading'!$E:$Q,MATCH($A20&"|"&$B20,'faizan grading'!$S:$S,0),COLUMN()-3),""),IF($C20="romain",IFERROR(INDEX('romain grading'!$E:$Q,MATCH($A20&"|"&$B20,'romain grading'!$S:$S,0),COLUMN()-3),""),IF($C20="nishita",IFERROR(INDEX('nishita grading'!$E:$Q,MATCH($A20&"|"&$B20,'nishita grading'!$S:$S,0),COLUMN()-3),""),""))) -> 0 | F20: =IF($C20="faizan",IFERROR(INDEX('faizan grading'!$E:$Q,MATCH($A20&"|"&$B20,'faizan grading'!$S:$S,0),COLUMN()-3),""),IF($C20="romain",IFERROR(INDEX('romain grading'!$E:$Q,MATCH($A20&"|"&$B20,'romain grading'!$S:$S,0),COLUMN()-3),""),IF($C20="nishita",IFERROR(INDEX('nishita grading'!$E:$Q,MATCH($A20&"|"&$B20,'nishita grading'!$S:$S,0),COLUMN()-3),""),""))) -> 6 | G20: =IF($C20="faizan",IFERROR(INDEX('faizan grading'!$E:$Q,MATCH($A20&"|"&$B20,'faizan grading'!$S:$S,0),COLUMN()-3),""),IF($C20="romain",IFERROR(INDEX('romain grading'!$E:$Q,MATCH($A20&"|"&$B20,'romain grading'!$S:$S,0),COLUMN()-3),""),IF($C20="nishita",IFERROR(INDEX('nishita grading'!$E:$Q,MATCH($A20&"|"&$B20,'nishita grading'!$S:$S,0),COLUMN()-3),""),""))) -> 0 | H20: =IF($C20="faizan",IFERROR(INDEX('faizan grading'!$E:$Q,MATCH($A20&"|"&$B20,'faizan grading'!$S:$S,0),COLUMN()-3),""),IF($C20="romain",IFERROR(INDEX('romain grading'!$E:$Q,MATCH($A20&"|"&$B20,'romain grading'!$S:$S,0),COLUMN()-3),""),IF($C20="nishita",IFERROR(INDEX('nishita grading'!$E:$Q,MATCH($A20&"|"&$B20,'nishita grading'!$S:$S,0),COLUMN()-3),""),""))) -> 0 | I20: =IF($C20="faizan",IFERROR(INDEX('faizan grading'!$E:$Q,MATCH($A20&"|"&$B20,'faizan grading'!$S:$S,0),COLUMN()-3),""),IF($C20="romain",IFERROR(INDEX('romain grading'!$E:$Q,MATCH($A20&"|"&$B20,'romain grading'!$S:$S,0),COLUMN()-3),""),IF($C20="nishita",IFERROR(INDEX('nishita grading'!$E:$Q,MATCH($A20&"|"&$B20,'nishita grading'!$S:$S,0),COLUMN()-3),""),""))) -> 0 | J20: =IF($C20="faizan",IFERROR(INDEX('faizan grading'!$E:$Q,MATCH($A20&"|"&$B20,'faizan grading'!$S:$S,0),COLUMN()-3),""),IF($C20="romain",IFERROR(INDEX('romain grading'!$E:$Q,MATCH($A20&"|"&$B20,'romain grading'!$S:$S,0),COLUMN()-3),""),IF($C20="nishita",IFERROR(INDEX('nishita grading'!$E:$Q,MATCH($A20&"|"&$B20,'nishita grading'!$S:$S,0),COLUMN()-3),""),""))) -> 0 | K20: =IF($C20="faizan",IFERROR(INDEX('faizan grading'!$E:$Q,MATCH($A20&"|"&$B20,'faizan grading'!$S:$S,0),COLUMN()-3),""),IF($C20="romain",IFERROR(INDEX('romain grading'!$E:$Q,MATCH($A20&"|"&$B20,'romain grading'!$S:$S,0),COLUMN()-3),""),IF($C20="nishita",IFERROR(INDEX('nishita grading'!$E:$Q,MATCH($A20&"|"&$B20,'nishita grading'!$S:$S,0),COLUMN()-3),""),""))) -> 4 | ... P20: =IF($C20="faizan",IFERROR(INDEX('faizan grading'!$E:$Q,MATCH($A20&"|"&$B20,'faizan grading'!$S:$S,0),COLUMN()-3),""),IF($C20="romain",IFERROR(INDEX('romain grading'!$E:$Q,MATCH($A20&"|"&$B20,'romain grading'!$S:$S,0),COLUMN()-3),""),IF($C20="nishita",IFERROR(INDEX('nishita grading'!$E:$Q,MATCH($A20&"|"&$B20,'nishita grading'!$S:$S,0),COLUMN()-3),""),""))) -> 0 | Q20: =40-SUM(D20:P20) -> 30 | R20: =A20&"|"&B20 -> chaotic|0062
A21: chaotic | B21: 0062 | C21: claude | D21: 0 | E21: 0 | F21: 0 | G21: 0 | H21: 3 | I21: 0 | J21: 0 | K21: 0 | L21: 0 | M21: 0 | N21: 0 | O21: 0 | P21: 0 | Q21: =40-SUM(D21:P21) -> 37 | R21: =A21&"|"&B21 -> chaotic|0062
A22: chaotic | B22: 0079 | C22: faizan | D22: =IF($C22="faizan",IFERROR(INDEX('faizan grading'!$E:$Q,MATCH($A22&"|"&$B22,'faizan grading'!$S:$S,0),COLUMN()-3),""),IF($C22="romain",IFERROR(INDEX('romain grading'!$E:$Q,MATCH($A22&"|"&$B22,'romain grading'!$S:$S,0),COLUMN()-3),""),IF($C22="nishita",IFERROR(INDEX('nishita grading'!$E:$Q,MATCH($A22&"|"&$B22,'nishita grading'!$S:$S,0),COLUMN()-3),""),""))) -> 0 | E22: =IF($C22="faizan",IFERROR(INDEX('faizan grading'!$E:$Q,MATCH($A22&"|"&$B22,'faizan grading'!$S:$S,0),COLUMN()-3),""),IF($C22="romain",IFERROR(INDEX('romain grading'!$E:$Q,MATCH($A22&"|"&$B22,'romain grading'!$S:$S,0),COLUMN()-3),""),IF($C22="nishita",IFERROR(INDEX('nishita grading'!$E:$Q,MATCH($A22&"|"&$B22,'nishita grading'!$S:$S,0),COLUMN()-3),""),""))) -> 0 | F22: =IF($C22="faizan",IFERROR(INDEX('faizan grading'!$E:$Q,MATCH($A22&"|"&$B22,'faizan grading'!$S:$S,0),COLUMN()-3),""),IF($C22="romain",IFERROR(INDEX('romain grading'!$E:$Q,MATCH($A22&"|"&$B22,'romain grading'!$S:$S,0),COLUMN()-3),""),IF($C22="nishita",IFERROR(INDEX('nishita grading'!$E:$Q,MATCH($A22&"|"&$B22,'nishita grading'!$S:$S,0),COLUMN()-3),""),""))) -> 0 | G22: =IF($C22="faizan",IFERROR(INDEX('faizan grading'!$E:$Q,MATCH($A22&"|"&$B22,'faizan grading'!$S:$S,0),COLUMN()-3),""),IF($C22="romain",IFERROR(INDEX('romain grading'!$E:$Q,MATCH($A22&"|"&$B22,'romain grading'!$S:$S,0),COLUMN()-3),""),IF($C22="nishita",IFERROR(INDEX('nishita grading'!$E:$Q,MATCH($A22&"|"&$B22,'nishita grading'!$S:$S,0),COLUMN()-3),""),""))) -> 0 | H22: =IF($C22="faizan",IFERROR(INDEX('faizan grading'!$E:$Q,MATCH($A22&"|"&$B22,'faizan grading'!$S:$S,0),COLUMN()-3),""),IF($C22="romain",IFERROR(INDEX('romain grading'!$E:$Q,MATCH($A22&"|"&$B22,'romain grading'!$S:$S,0),COLUMN()-3),""),IF($C22="nishita",IFERROR(INDEX('nishita grading'!$E:$Q,MATCH($A22&"|"&$B22,'nishita grading'!$S:$S,0),COLUMN()-3),""),""))) -> 0 | I22: =IF($C22="faizan",IFERROR(INDEX('faizan grading'!$E:$Q,MATCH($A22&"|"&$B22,'faizan grading'!$S:$S,0),COLUMN()-3),""),IF($C22="romain",IFERROR(INDEX('romain grading'!$E:$Q,MATCH($A22&"|"&$B22,'romain grading'!$S:$S,0),COLUMN()-3),""),IF($C22="nishita",IFERROR(INDEX('nishita grading'!$E:$Q,MATCH($A22&"|"&$B22,'nishita grading'!$S:$S,0),COLUMN()-3),""),""))) -> 0 | J22: =IF($C22="faizan",IFERROR(INDEX('faizan grading'!$E:$Q,MATCH($A22&"|"&$B22,'faizan grading'!$S:$S,0),COLUMN()-3),""),IF($C22="romain",IFERROR(INDEX('romain grading'!$E:$Q,MATCH($A22&"|"&$B22,'romain grading'!$S:$S,0),COLUMN()-3),""),IF($C22="nishita",IFERROR(INDEX('nishita grading'!$E:$Q,MATCH($A22&"|"&$B22,'nishita grading'!$S:$S,0),COLUMN()-3),""),""))) -> 0 | K22: =IF($C22="faizan",IFERROR(INDEX('faizan grading'!$E:$Q,MATCH($A22&"|"&$B22,'faizan grading'!$S:$S,0),COLUMN()-3),""),IF($C22="romain",IFERROR(INDEX('romain grading'!$E:$Q,MATCH($A22&"|"&$B22,'romain grading'!$S:$S,0),COLUMN()-3),""),IF($C22="nishita",IFERROR(INDEX('nishita grading'!$E:$Q,MATCH($A22&"|"&$B22,'nishita grading'!$S:$S,0),COLUMN()-3),""),""))) -> 0 | ... P22: =IF($C22="faizan",IFERROR(INDEX('faizan grading'!$E:$Q,MATCH($A22&"|"&$B22,'faizan grading'!$S:$S,0),COLUMN()-3),""),IF($C22="romain",IFERROR(INDEX('romain grading'!$E:$Q,MATCH($A22&"|"&$B22,'romain grading'!$S:$S,0),COLUMN()-3),""),IF($C22="nishita",IFERROR(INDEX('nishita grading'!$E:$Q,MATCH($A22&"|"&$B22,'nishita grading'!$S:$S,0),COLUMN()-3),""),""))) -> 0 | Q22: =40-SUM(D22:P22) -> 40 | R22: =A22&"|"&B22 -> chaotic|0079
A23: chaotic | B23: 0079 | C23: romain | D23: =IF($C23="faizan",IFERROR(INDEX('faizan grading'!$E:$Q,MATCH($A23&"|"&$B23,'faizan grading'!$S:$S,0),COLUMN()-3),""),IF($C23="romain",IFERROR(INDEX('romain grading'!$E:$Q,MATCH($A23&"|"&$B23,'romain grading'!$S:$S,0),COLUMN()-3),""),IF($C23="nishita",IFERROR(INDEX('nishita grading'!$E:$Q,MATCH($A23&"|"&$B23,'nishita grading'!$S:$S,0),COLUMN()-3),""),""))) -> 0 | E23: =IF($C23="faizan",IFERROR(INDEX('faizan grading'!$E:$Q,MATCH($A23&"|"&$B23,'faizan grading'!$S:$S,0),COLUMN()-3),""),IF($C23="romain",IFERROR(INDEX('romain grading'!$E:$Q,MATCH($A23&"|"&$B23,'romain grading'!$S:$S,0),COLUMN()-3),""),IF($C23="nishita",IFERROR(INDEX('nishita grading'!$E:$Q,MATCH($A23&"|"&$B23,'nishita grading'!$S:$S,0),COLUMN()-3),""),""))) -> 0 | F23: =IF($C23="faizan",IFERROR(INDEX('faizan grading'!$E:$Q,MATCH($A23&"|"&$B23,'faizan grading'!$S:$S,0),COLUMN()-3),""),IF($C23="romain",IFERROR(INDEX('romain grading'!$E:$Q,MATCH($A23&"|"&$B23,'romain grading'!$S:$S,0),COLUMN()-3),""),IF($C23="nishita",IFERROR(INDEX('nishita grading'!$E:$Q,MATCH($A23&"|"&$B23,'nishita grading'!$S:$S,0),COLUMN()-3),""),""))) -> 0 | G23: =IF($C23="faizan",IFERROR(INDEX('faizan grading'!$E:$Q,MATCH($A23&"|"&$B23,'faizan grading'!$S:$S,0),COLUMN()-3),""),IF($C23="romain",IFERROR(INDEX('romain grading'!$E:$Q,MATCH($A23&"|"&$B23,'romain grading'!$S:$S,0),COLUMN()-3),""),IF($C23="nishita",IFERROR(INDEX('nishita grading'!$E:$Q,MATCH($A23&"|"&$B23,'nishita grading'!$S:$S,0),COLUMN()-3),""),""))) -> 0 | H23: =IF($C23="faizan",IFERROR(INDEX('faizan grading'!$E:$Q,MATCH($A23&"|"&$B23,'faizan grading'!$S:$S,0),COLUMN()-3),""),IF($C23="romain",IFERROR(INDEX('romain grading'!$E:$Q,MATCH($A23&"|"&$B23,'romain grading'!$S:$S,0),COLUMN()-3),""),IF($C23="nishita",IFERROR(INDEX('nishita grading'!$E:$Q,MATCH($A23&"|"&$B23,'nishita grading'!$S:$S,0),COLUMN()-3),""),""))) -> 0 | I23: =IF($C23="faizan",IFERROR(INDEX('faizan grading'!$E:$Q,MATCH($A23&"|"&$B23,'faizan grading'!$S:$S,0),COLUMN()-3),""),IF($C23="romain",IFERROR(INDEX('romain grading'!$E:$Q,MATCH($A23&"|"&$B23,'romain grading'!$S:$S,0),COLUMN()-3),""),IF($C23="nishita",IFERROR(INDEX('nishita grading'!$E:$Q,MATCH($A23&"|"&$B23,'nishita grading'!$S:$S,0),COLUMN()-3),""),""))) -> 0 | J23: =IF($C23="faizan",IFERROR(INDEX('faizan grading'!$E:$Q,MATCH($A23&"|"&$B23,'faizan grading'!$S:$S,0),COLUMN()-3),""),IF($C23="romain",IFERROR(INDEX('romain grading'!$E:$Q,MATCH($A23&"|"&$B23,'romain grading'!$S:$S,0),COLUMN()-3),""),IF($C23="nishita",IFERROR(INDEX('nishita grading'!$E:$Q,MATCH($A23&"|"&$B23,'nishita grading'!$S:$S,0),COLUMN()-3),""),""))) -> 0 | K23: =IF($C23="faizan",IFERROR(INDEX('faizan grading'!$E:$Q,MATCH($A23&"|"&$B23,'faizan grading'!$S:$S,0),COLUMN()-3),""),IF($C23="romain",IFERROR(INDEX('romain grading'!$E:$Q,MATCH($A23&"|"&$B23,'romain grading'!$S:$S,0),COLUMN()-3),""),IF($C23="nishita",IFERROR(INDEX('nishita grading'!$E:$Q,MATCH($A23&"|"&$B23,'nishita grading'!$S:$S,0),COLUMN()-3),""),""))) -> 0 | ... P23: =IF($C23="faizan",IFERROR(INDEX('faizan grading'!$E:$Q,MATCH($A23&"|"&$B23,'faizan grading'!$S:$S,0),COLUMN()-3),""),IF($C23="romain",IFERROR(INDEX('romain grading'!$E:$Q,MATCH($A23&"|"&$B23,'romain grading'!$S:$S,0),COLUMN()-3),""),IF($C23="nishita",IFERROR(INDEX('nishita grading'!$E:$Q,MATCH($A23&"|"&$B23,'nishita grading'!$S:$S,0),COLUMN()-3),""),""))) -> 0 | Q23: =40-SUM(D23:P23) -> 40 | R23: =A23&"|"&B23 -> chaotic|0079
A24: chaotic | B24: 0079 | C24: nishita | D24: =IF($C24="faizan",IFERROR(INDEX('faizan grading'!$E:$Q,MATCH($A24&"|"&$B24,'faizan grading'!$S:$S,0),COLUMN()-3),""),IF($C24="romain",IFERROR(INDEX('romain grading'!$E:$Q,MATCH($A24&"|"&$B24,'romain grading'!$S:$S,0),COLUMN()-3),""),IF($C24="nishita",IFERROR(INDEX('nishita grading'!$E:$Q,MATCH($A24&"|"&$B24,'nishita grading'!$S:$S,0),COLUMN()-3),""),""))) -> 0 | E24: =IF($C24="faizan",IFERROR(INDEX('faizan grading'!$E:$Q,MATCH($A24&"|"&$B24,'faizan grading'!$S:$S,0),COLUMN()-3),""),IF($C24="romain",IFERROR(INDEX('romain grading'!$E:$Q,MATCH($A24&"|"&$B24,'romain grading'!$S:$S,0),COLUMN()-3),""),IF($C24="nishita",IFERROR(INDEX('nishita grading'!$E:$Q,MATCH($A24&"|"&$B24,'nishita grading'!$S:$S,0),COLUMN()-3),""),""))) -> 0 | F24: =IF($C24="faizan",IFERROR(INDEX('faizan grading'!$E:$Q,MATCH($A24&"|"&$B24,'faizan grading'!$S:$S,0),COLUMN()-3),""),IF($C24="romain",IFERROR(INDEX('romain grading'!$E:$Q,MATCH($A24&"|"&$B24,'romain grading'!$S:$S,0),COLUMN()-3),""),IF($C24="nishita",IFERROR(INDEX('nishita grading'!$E:$Q,MATCH($A24&"|"&$B24,'nishita grading'!$S:$S,0),COLUMN()-3),""),""))) -> 6 | G24: =IF($C24="faizan",IFERROR(INDEX('faizan grading'!$E:$Q,MATCH($A24&"|"&$B24,'faizan grading'!$S:$S,0),COLUMN()-3),""),IF($C24="romain",IFERROR(INDEX('romain grading'!$E:$Q,MATCH($A24&"|"&$B24,'romain grading'!$S:$S,0),COLUMN()-3),""),IF($C24="nishita",IFERROR(INDEX('nishita grading'!$E:$Q,MATCH($A24&"|"&$B24,'nishita grading'!$S:$S,0),COLUMN()-3),""),""))) -> 0 | H24: =IF($C24="faizan",IFERROR(INDEX('faizan grading'!$E:$Q,MATCH($A24&"|"&$B24,'faizan grading'!$S:$S,0),COLUMN()-3),""),IF($C24="romain",IFERROR(INDEX('romain grading'!$E:$Q,MATCH($A24&"|"&$B24,'romain grading'!$S:$S,0),COLUMN()-3),""),IF($C24="nishita",IFERROR(INDEX('nishita grading'!$E:$Q,MATCH($A24&"|"&$B24,'nishita grading'!$S:$S,0),COLUMN()-3),""),""))) -> 0 | I24: =IF($C24="faizan",IFERROR(INDEX('faizan grading'!$E:$Q,MATCH($A24&"|"&$B24,'faizan grading'!$S:$S,0),COLUMN()-3),""),IF($C24="romain",IFERROR(INDEX('romain grading'!$E:$Q,MATCH($A24&"|"&$B24,'romain grading'!$S:$S,0),COLUMN()-3),""),IF($C24="nishita",IFERROR(INDEX('nishita grading'!$E:$Q,MATCH($A24&"|"&$B24,'nishita grading'!$S:$S,0),COLUMN()-3),""),""))) -> 0 | J24: =IF($C24="faizan",IFERROR(INDEX('faizan grading'!$E:$Q,MATCH($A24&"|"&$B24,'faizan grading'!$S:$S,0),COLUMN()-3),""),IF($C24="romain",IFERROR(INDEX('romain grading'!$E:$Q,MATCH($A24&"|"&$B24,'romain grading'!$S:$S,0),COLUMN()-3),""),IF($C24="nishita",IFERROR(INDEX('nishita grading'!$E:$Q,MATCH($A24&"|"&$B24,'nishita grading'!$S:$S,0),COLUMN()-3),""),""))) -> 0 | K24: =IF($C24="faizan",IFERROR(INDEX('faizan grading'!$E:$Q,MATCH($A24&"|"&$B24,'faizan grading'!$S:$S,0),COLUMN()-3),""),IF($C24="romain",IFERROR(INDEX('romain grading'!$E:$Q,MATCH($A24&"|"&$B24,'romain grading'!$S:$S,0),COLUMN()-3),""),IF($C24="nishita",IFERROR(INDEX('nishita grading'!$E:$Q,MATCH($A24&"|"&$B24,'nishita grading'!$S:$S,0),COLUMN()-3),""),""))) -> 0 | ... P24: =IF($C24="faizan",IFERROR(INDEX('faizan grading'!$E:$Q,MATCH($A24&"|"&$B24,'faizan grading'!$S:$S,0),COLUMN()-3),""),IF($C24="romain",IFERROR(INDEX('romain grading'!$E:$Q,MATCH($A24&"|"&$B24,'romain grading'!$S:$S,0),COLUMN()-3),""),IF($C24="nishita",IFERROR(INDEX('nishita grading'!$E:$Q,MATCH($A24&"|"&$B24,'nishita grading'!$S:$S,0),COLUMN()-3),""),""))) -> 0 | Q24: =40-SUM(D24:P24) -> 32 | R24: =A24&"|"&B24 -> chaotic|0079
A25: chaotic | B25: 0079 | C25: claude | D25: 12 | E25: 0 | F25: 0 | G25: 0 | H25: 0 | I25: 0 | J25: 0 | K25: 0 | L25: 0 | M25: 0 | N25: 0 | O25: 0 | P25: 0 | Q25: =40-SUM(D25:P25) -> 28 | R25: =A25&"|"&B25 -> chaotic|0079
A26: chaotic | B26: 0085 | C26: faizan | D26: =IF($C26="faizan",IFERROR(INDEX('faizan grading'!$E:$Q,MATCH($A26&"|"&$B26,'faizan grading'!$S:$S,0),COLUMN()-3),""),IF($C26="romain",IFERROR(INDEX('romain grading'!$E:$Q,MATCH($A26&"|"&$B26,'romain grading'!$S:$S,0),COLUMN()-3),""),IF($C26="nishita",IFERROR(INDEX('nishita grading'!$E:$Q,MATCH($A26&"|"&$B26,'nishita grading'!$S:$S,0),COLUMN()-3),""),""))) -> 0 | E26: =IF($C26="faizan",IFERROR(INDEX('faizan grading'!$E:$Q,MATCH($A26&"|"&$B26,'faizan grading'!$S:$S,0),COLUMN()-3),""),IF($C26="romain",IFERROR(INDEX('romain grading'!$E:$Q,MATCH($A26&"|"&$B26,'romain grading'!$S:$S,0),COLUMN()-3),""),IF($C26="nishita",IFERROR(INDEX('nishita grading'!$E:$Q,MATCH($A26&"|"&$B26,'nishita grading'!$S:$S,0),COLUMN()-3),""),""))) -> 0 | F26: =IF($C26="faizan",IFERROR(INDEX('faizan grading'!$E:$Q,MATCH($A26&"|"&$B26,'faizan grading'!$S:$S,0),COLUMN()-3),""),IF($C26="romain",IFERROR(INDEX('romain grading'!$E:$Q,MATCH($A26&"|"&$B26,'romain grading'!$S:$S,0),COLUMN()-3),""),IF($C26="nishita",IFERROR(INDEX('nishita grading'!$E:$Q,MATCH($A26&"|"&$B26,'nishita grading'!$S:$S,0),COLUMN()-3),""),""))) -> 0 | G26: =IF($C26="faizan",IFERROR(INDEX('faizan grading'!$E:$Q,MATCH($A26&"|"&$B26,'faizan grading'!$S:$S,0),COLUMN()-3),""),IF($C26="romain",IFERROR(INDEX('romain grading'!$E:$Q,MATCH($A26&"|"&$B26,'romain grading'!$S:$S,0),COLUMN()-3),""),IF($C26="nishita",IFERROR(INDEX('nishita grading'!$E:$Q,MATCH($A26&"|"&$B26,'nishita grading'!$S:$S,0),COLUMN()-3),""),""))) -> 0 | H26: =IF($C26="faizan",IFERROR(INDEX('faizan grading'!$E:$Q,MATCH($A26&"|"&$B26,'faizan grading'!$S:$S,0),COLUMN()-3),""),IF($C26="romain",IFERROR(INDEX('romain grading'!$E:$Q,MATCH($A26&"|"&$B26,'romain grading'!$S:$S,0),COLUMN()-3),""),IF($C26="nishita",IFERROR(INDEX('nishita grading'!$E:$Q,MATCH($A26&"|"&$B26,'nishita grading'!$S:$S,0),COLUMN()-3),""),""))) -> 0 | I26: =IF($C26="faizan",IFERROR(INDEX('faizan grading'!$E:$Q,MATCH($A26&"|"&$B26,'faizan grading'!$S:$S,0),COLUMN()-3),""),IF($C26="romain",IFERROR(INDEX('romain grading'!$E:$Q,MATCH($A26&"|"&$B26,'romain grading'!$S:$S,0),COLUMN()-3),""),IF($C26="nishita",IFERROR(INDEX('nishita grading'!$E:$Q,MATCH($A26&"|"&$B26,'nishita grading'!$S:$S,0),COLUMN()-3),""),""))) -> 0 | J26: =IF($C26="faizan",IFERROR(INDEX('faizan grading'!$E:$Q,MATCH($A26&"|"&$B26,'faizan grading'!$S:$S,0),COLUMN()-3),""),IF($C26="romain",IFERROR(INDEX('romain grading'!$E:$Q,MATCH($A26&"|"&$B26,'romain grading'!$S:$S,0),COLUMN()-3),""),IF($C26="nishita",IFERROR(INDEX('nishita grading'!$E:$Q,MATCH($A26&"|"&$B26,'nishita grading'!$S:$S,0),COLUMN()-3),""),""))) -> 0 | K26: =IF($C26="faizan",IFERROR(INDEX('faizan grading'!$E:$Q,MATCH($A26&"|"&$B26,'faizan grading'!$S:$S,0),COLUMN()-3),""),IF($C26="romain",IFERROR(INDEX('romain grading'!$E:$Q,MATCH($A26&"|"&$B26,'romain grading'!$S:$S,0),COLUMN()-3),""),IF($C26="nishita",IFERROR(INDEX('nishita grading'!$E:$Q,MATCH($A26&"|"&$B26,'nishita grading'!$S:$S,0),COLUMN()-3),""),""))) -> 0 | ... P26: =IF($C26="faizan",IFERROR(INDEX('faizan grading'!$E:$Q,MATCH($A26&"|"&$B26,'faizan grading'!$S:$S,0),COLUMN()-3),""),IF($C26="romain",IFERROR(INDEX('romain grading'!$E:$Q,MATCH($A26&"|"&$B26,'romain grading'!$S:$S,0),COLUMN()-3),""),IF($C26="nishita",IFERROR(INDEX('nishita grading'!$E:$Q,MATCH($A26&"|"&$B26,'nishita grading'!$S:$S,0),COLUMN()-3),""),""))) -> 0 | Q26: =40-SUM(D26:P26) -> 40 | R26: =A26&"|"&B26 -> chaotic|0085
A27: chaotic | B27: 0085 | C27: romain | D27: =IF($C27="faizan",IFERROR(INDEX('faizan grading'!$E:$Q,MATCH($A27&"|"&$B27,'faizan grading'!$S:$S,0),COLUMN()-3),""),IF($C27="romain",IFERROR(INDEX('romain grading'!$E:$Q,MATCH($A27&"|"&$B27,'romain grading'!$S:$S,0),COLUMN()-3),""),IF($C27="nishita",IFERROR(INDEX('nishita grading'!$E:$Q,MATCH($A27&"|"&$B27,'nishita grading'!$S:$S,0),COLUMN()-3),""),""))) -> 0 | E27: =IF($C27="faizan",IFERROR(INDEX('faizan grading'!$E:$Q,MATCH($A27&"|"&$B27,'faizan grading'!$S:$S,0),COLUMN()-3),""),IF($C27="romain",IFERROR(INDEX('romain grading'!$E:$Q,MATCH($A27&"|"&$B27,'romain grading'!$S:$S,0),COLUMN()-3),""),IF($C27="nishita",IFERROR(INDEX('nishita grading'!$E:$Q,MATCH($A27&"|"&$B27,'nishita grading'!$S:$S,0),COLUMN()-3),""),""))) -> 0 | F27: =IF($C27="faizan",IFERROR(INDEX('faizan grading'!$E:$Q,MATCH($A27&"|"&$B27,'faizan grading'!$S:$S,0),COLUMN()-3),""),IF($C27="romain",IFERROR(INDEX('romain grading'!$E:$Q,MATCH($A27&"|"&$B27,'romain grading'!$S:$S,0),COLUMN()-3),""),IF($C27="nishita",IFERROR(INDEX('nishita grading'!$E:$Q,MATCH($A27&"|"&$B27,'nishita grading'!$S:$S,0),COLUMN()-3),""),""))) -> 0 | G27: =IF($C27="faizan",IFERROR(INDEX('faizan grading'!$E:$Q,MATCH($A27&"|"&$B27,'faizan grading'!$S:$S,0),COLUMN()-3),""),IF($C27="romain",IFERROR(INDEX('romain grading'!$E:$Q,MATCH($A27&"|"&$B27,'romain grading'!$S:$S,0),COLUMN()-3),""),IF($C27="nishita",IFERROR(INDEX('nishita grading'!$E:$Q,MATCH($A27&"|"&$B27,'nishita grading'!$S:$S,0),COLUMN()-3),""),""))) -> 0 | H27: =IF($C27="faizan",IFERROR(INDEX('faizan grading'!$E:$Q,MATCH($A27&"|"&$B27,'faizan grading'!$S:$S,0),COLUMN()-3),""),IF($C27="romain",IFERROR(INDEX('romain grading'!$E:$Q,MATCH($A27&"|"&$B27,'romain grading'!$S:$S,0),COLUMN()-3),""),IF($C27="nishita",IFERROR(INDEX('nishita grading'!$E:$Q,MATCH($A27&"|"&$B27,'nishita grading'!$S:$S,0),COLUMN()-3),""),""))) -> 0 | I27: =IF($C27="faizan",IFERROR(INDEX('faizan grading'!$E:$Q,MATCH($A27&"|"&$B27,'faizan grading'!$S:$S,0),COLUMN()-3),""),IF($C27="romain",IFERROR(INDEX('romain grading'!$E:$Q,MATCH($A27&"|"&$B27,'romain grading'!$S:$S,0),COLUMN()-3),""),IF($C27="nishita",IFERROR(INDEX('nishita grading'!$E:$Q,MATCH($A27&"|"&$B27,'nishita grading'!$S:$S,0),COLUMN()-3),""),""))) -> 0 | J27: =IF($C27="faizan",IFERROR(INDEX('faizan grading'!$E:$Q,MATCH($A27&"|"&$B27,'faizan grading'!$S:$S,0),COLUMN()-3),""),IF($C27="romain",IFERROR(INDEX('romain grading'!$E:$Q,MATCH($A27&"|"&$B27,'romain grading'!$S:$S,0),COLUMN()-3),""),IF($C27="nishita",IFERROR(INDEX('nishita grading'!$E:$Q,MATCH($A27&"|"&$B27,'nishita grading'!$S:$S,0),COLUMN()-3),""),""))) -> 0 | K27: =IF($C27="faizan",IFERROR(INDEX('faizan grading'!$E:$Q,MATCH($A27&"|"&$B27,'faizan grading'!$S:$S,0),COLUMN()-3),""),IF($C27="romain",IFERROR(INDEX('romain grading'!$E:$Q,MATCH($A27&"|"&$B27,'romain grading'!$S:$S,0),COLUMN()-3),""),IF($C27="nishita",IFERROR(INDEX('nishita grading'!$E:$Q,MATCH($A27&"|"&$B27,'nishita grading'!$S:$S,0),COLUMN()-3),""),""))) -> 0 | ... P27: =IF($C27="faizan",IFERROR(INDEX('faizan grading'!$E:$Q,MATCH($A27&"|"&$B27,'faizan grading'!$S:$S,0),COLUMN()-3),""),IF($C27="romain",IFERROR(INDEX('romain grading'!$E:$Q,MATCH($A27&"|"&$B27,'romain grading'!$S:$S,0),COLUMN()-3),""),IF($C27="nishita",IFERROR(INDEX('nishita grading'!$E:$Q,MATCH($A27&"|"&$B27,'nishita grading'!$S:$S,0),COLUMN()-3),""),""))) -> 0 | Q27: =40-SUM(D27:P27) -> 40 | R27: =A27&"|"&B27 -> chaotic|0085
A28: chaotic | B28: 0085 | C28: nishita | D28: =IF($C28="faizan",IFERROR(INDEX('faizan grading'!$E:$Q,MATCH($A28&"|"&$B28,'faizan grading'!$S:$S,0),COLUMN()-3),""),IF($C28="romain",IFERROR(INDEX('romain grading'!$E:$Q,MATCH($A28&"|"&$B28,'romain grading'!$S:$S,0),COLUMN()-3),""),IF($C28="nishita",IFERROR(INDEX('nishita grading'!$E:$Q,MATCH($A28&"|"&$B28,'nishita grading'!$S:$S,0),COLUMN()-3),""),""))) -> 0 | E28: =IF($C28="faizan",IFERROR(INDEX('faizan grading'!$E:$Q,MATCH($A28&"|"&$B28,'faizan grading'!$S:$S,0),COLUMN()-3),""),IF($C28="romain",IFERROR(INDEX('romain grading'!$E:$Q,MATCH($A28&"|"&$B28,'romain grading'!$S:$S,0),COLUMN()-3),""),IF($C28="nishita",IFERROR(INDEX('nishita grading'!$E:$Q,MATCH($A28&"|"&$B28,'nishita grading'!$S:$S,0),COLUMN()-3),""),""))) -> 0 | F28: =IF($C28="faizan",IFERROR(INDEX('faizan grading'!$E:$Q,MATCH($A28&"|"&$B28,'faizan grading'!$S:$S,0),COLUMN()-3),""),IF($C28="romain",IFERROR(INDEX('romain grading'!$E:$Q,MATCH($A28&"|"&$B28,'romain grading'!$S:$S,0),COLUMN()-3),""),IF($C28="nishita",IFERROR(INDEX('nishita grading'!$E:$Q,MATCH($A28&"|"&$B28,'nishita grading'!$S:$S,0),COLUMN()-3),""),""))) -> 6 | G28: =IF($C28="faizan",IFERROR(INDEX('faizan grading'!$E:$Q,MATCH($A28&"|"&$B28,'faizan grading'!$S:$S,0),COLUMN()-3),""),IF($C28="romain",IFERROR(INDEX('romain grading'!$E:$Q,MATCH($A28&"|"&$B28,'romain grading'!$S:$S,0),COLUMN()-3),""),IF($C28="nishita",IFERROR(INDEX('nishita grading'!$E:$Q,MATCH($A28&"|"&$B28,'nishita grading'!$S:$S,0),COLUMN()-3),""),""))) -> 0 | H28: =IF($C28="faizan",IFERROR(INDEX('faizan grading'!$E:$Q,MATCH($A28&"|"&$B28,'faizan grading'!$S:$S,0),COLUMN()-3),""),IF($C28="romain",IFERROR(INDEX('romain grading'!$E:$Q,MATCH($A28&"|"&$B28,'romain grading'!$S:$S,0),COLUMN()-3),""),IF($C28="nishita",IFERROR(INDEX('nishita grading'!$E:$Q,MATCH($A28&"|"&$B28,'nishita grading'!$S:$S,0),COLUMN()-3),""),""))) -> 0 | I28: =IF($C28="faizan",IFERROR(INDEX('faizan grading'!$E:$Q,MATCH($A28&"|"&$B28,'faizan grading'!$S:$S,0),COLUMN()-3),""),IF($C28="romain",IFERROR(INDEX('romain grading'!$E:$Q,MATCH($A28&"|"&$B28,'romain grading'!$S:$S,0),COLUMN()-3),""),IF($C28="nishita",IFERROR(INDEX('nishita grading'!$E:$Q,MATCH($A28&"|"&$B28,'nishita grading'!$S:$S,0),COLUMN()-3),""),""))) -> 0 | J28: =IF($C28="faizan",IFERROR(INDEX('faizan grading'!$E:$Q,MATCH($A28&"|"&$B28,'faizan grading'!$S:$S,0),COLUMN()-3),""),IF($C28="romain",IFERROR(INDEX('romain grading'!$E:$Q,MATCH($A28&"|"&$B28,'romain grading'!$S:$S,0),COLUMN()-3),""),IF($C28="nishita",IFERROR(INDEX('nishita grading'!$E:$Q,MATCH($A28&"|"&$B28,'nishita grading'!$S:$S,0),COLUMN()-3),""),""))) -> 0 | K28: =IF($C28="faizan",IFERROR(INDEX('faizan grading'!$E:$Q,MATCH($A28&"|"&$B28,'faizan grading'!$S:$S,0),COLUMN()-3),""),IF($C28="romain",IFERROR(INDEX('romain grading'!$E:$Q,MATCH($A28&"|"&$B28,'romain grading'!$S:$S,0),COLUMN()-3),""),IF($C28="nishita",IFERROR(INDEX('nishita grading'!$E:$Q,MATCH($A28&"|"&$B28,'nishita grading'!$S:$S,0),COLUMN()-3),""),""))) -> 0 | ... P28: =IF($C28="faizan",IFERROR(INDEX('faizan grading'!$E:$Q,MATCH($A28&"|"&$B28,'faizan grading'!$S:$S,0),COLUMN()-3),""),IF($C28="romain",IFERROR(INDEX('romain grading'!$E:$Q,MATCH($A28&"|"&$B28,'romain grading'!$S:$S,0),COLUMN()-3),""),IF($C28="nishita",IFERROR(INDEX('nishita grading'!$E:$Q,MATCH($A28&"|"&$B28,'nishita grading'!$S:$S,0),COLUMN()-3),""),""))) -> 0 | Q28: =40-SUM(D28:P28) -> 32 | R28: =A28&"|"&B28 -> chaotic|0085
A29: chaotic | B29: 0085 | C29: claude | D29: 12 | E29: 0 | F29: 0 | G29: 0 | H29: 0 | I29: 0 | J29: 0 | K29: 0 | L29: 0 | M29: 0 | N29: 0 | O29: 0 | P29: 0 | Q29: =40-SUM(D29:P29) -> 28 | R29: =A29&"|"&B29 -> chaotic|0085
A30: chaotic | B30: 0097 | C30: faizan | D30: =IF($C30="faizan",IFERROR(INDEX('faizan grading'!$E:$Q,MATCH($A30&"|"&$B30,'faizan grading'!$S:$S,0),COLUMN()-3),""),IF($C30="romain",IFERROR(INDEX('romain grading'!$E:$Q,MATCH($A30&"|"&$B30,'romain grading'!$S:$S,0),COLUMN()-3),""),IF($C30="nishita",IFERROR(INDEX('nishita grading'!$E:$Q,MATCH($A30&"|"&$B30,'nishita grading'!$S:$S,0),COLUMN()-3),""),""))) -> 0 | E30: =IF($C30="faizan",IFERROR(INDEX('faizan grading'!$E:$Q,MATCH($A30&"|"&$B30,'faizan grading'!$S:$S,0),COLUMN()-3),""),IF($C30="romain",IFERROR(INDEX('romain grading'!$E:$Q,MATCH($A30&"|"&$B30,'romain grading'!$S:$S,0),COLUMN()-3),""),IF($C30="nishita",IFERROR(INDEX('nishita grading'!$E:$Q,MATCH($A30&"|"&$B30,'nishita grading'!$S:$S,0),COLUMN()-3),""),""))) -> 0 | F30: =IF($C30="faizan",IFERROR(INDEX('faizan grading'!$E:$Q,MATCH($A30&"|"&$B30,'faizan grading'!$S:$S,0),COLUMN()-3),""),IF($C30="romain",IFERROR(INDEX('romain grading'!$E:$Q,MATCH($A30&"|"&$B30,'romain grading'!$S:$S,0),COLUMN()-3),""),IF($C30="nishita",IFERROR(INDEX('nishita grading'!$E:$Q,MATCH($A30&"|"&$B30,'nishita grading'!$S:$S,0),COLUMN()-3),""),""))) -> 0 | G30: =IF($C30="faizan",IFERROR(INDEX('faizan grading'!$E:$Q,MATCH($A30&"|"&$B30,'faizan grading'!$S:$S,0),COLUMN()-3),""),IF($C30="romain",IFERROR(INDEX('romain grading'!$E:$Q,MATCH($A30&"|"&$B30,'romain grading'!$S:$S,0),COLUMN()-3),""),IF($C30="nishita",IFERROR(INDEX('nishita grading'!$E:$Q,MATCH($A30&"|"&$B30,'nishita grading'!$S:$S,0),COLUMN()-3),""),""))) -> 0 | H30: =IF($C30="faizan",IFERROR(INDEX('faizan grading'!$E:$Q,MATCH($A30&"|"&$B30,'faizan grading'!$S:$S,0),COLUMN()-3),""),IF($C30="romain",IFERROR(INDEX('romain grading'!$E:$Q,MATCH($A30&"|"&$B30,'romain grading'!$S:$S,0),COLUMN()-3),""),IF($C30="nishita",IFERROR(INDEX('nishita grading'!$E:$Q,MATCH($A30&"|"&$B30,'nishita grading'!$S:$S,0),COLUMN()-3),""),""))) -> 0 | I30: =IF($C30="faizan",IFERROR(INDEX('faizan grading'!$E:$Q,MATCH($A30&"|"&$B30,'faizan grading'!$S:$S,0),COLUMN()-3),""),IF($C30="romain",IFERROR(INDEX('romain grading'!$E:$Q,MATCH($A30&"|"&$B30,'romain grading'!$S:$S,0),COLUMN()-3),""),IF($C30="nishita",IFERROR(INDEX('nishita grading'!$E:$Q,MATCH($A30&"|"&$B30,'nishita grading'!$S:$S,0),COLUMN()-3),""),""))) -> 0 | J30: =IF($C30="faizan",IFERROR(INDEX('faizan grading'!$E:$Q,MATCH($A30&"|"&$B30,'faizan grading'!$S:$S,0),COLUMN()-3),""),IF($C30="romain",IFERROR(INDEX('romain grading'!$E:$Q,MATCH($A30&"|"&$B30,'romain grading'!$S:$S,0),COLUMN()-3),""),IF($C30="nishita",IFERROR(INDEX('nishita grading'!$E:$Q,MATCH($A30&"|"&$B30,'nishita grading'!$S:$S,0),COLUMN()-3),""),""))) -> 0 | K30: =IF($C30="faizan",IFERROR(INDEX('faizan grading'!$E:$Q,MATCH($A30&"|"&$B30,'faizan grading'!$S:$S,0),COLUMN()-3),""),IF($C30="romain",IFERROR(INDEX('romain grading'!$E:$Q,MATCH($A30&"|"&$B30,'romain grading'!$S:$S,0),COLUMN()-3),""),IF($C30="nishita",IFERROR(INDEX('nishita grading'!$E:$Q,MATCH($A30&"|"&$B30,'nishita grading'!$S:$S,0),COLUMN()-3),""),""))) -> 0 | ... P30: =IF($C30="faizan",IFERROR(INDEX('faizan grading'!$E:$Q,MATCH($A30&"|"&$B30,'faizan grading'!$S:$S,0),COLUMN()-3),""),IF($C30="romain",IFERROR(INDEX('romain grading'!$E:$Q,MATCH($A30&"|"&$B30,'romain grading'!$S:$S,0),COLUMN()-3),""),IF($C30="nishita",IFERROR(INDEX('nishita grading'!$E:$Q,MATCH($A30&"|"&$B30,'nishita grading'!$S:$S,0),COLUMN()-3),""),""))) -> 0 | Q30: =40-SUM(D30:P30) -> 40 | R30: =A30&"|"&B30 -> chaotic|0097
A31: chaotic | B31: 0097 | C31: romain | D31: =IF($C31="faizan",IFERROR(INDEX('faizan grading'!$E:$Q,MATCH($A31&"|"&$B31,'faizan grading'!$S:$S,0),COLUMN()-3),""),IF($C31="romain",IFERROR(INDEX('romain grading'!$E:$Q,MATCH($A31&"|"&$B31,'romain grading'!$S:$S,0),COLUMN()-3),""),IF($C31="nishita",IFERROR(INDEX('nishita grading'!$E:$Q,MATCH($A31&"|"&$B31,'nishita grading'!$S:$S,0),COLUMN()-3),""),""))) -> 0 | E31: =IF($C31="faizan",IFERROR(INDEX('faizan grading'!$E:$Q,MATCH($A31&"|"&$B31,'faizan grading'!$S:$S,0),COLUMN()-3),""),IF($C31="romain",IFERROR(INDEX('romain grading'!$E:$Q,MATCH($A31&"|"&$B31,'romain grading'!$S:$S,0),COLUMN()-3),""),IF($C31="nishita",IFERROR(INDEX('nishita grading'!$E:$Q,MATCH($A31&"|"&$B31,'nishita grading'!$S:$S,0),COLUMN()-3),""),""))) -> 0 | F31: =IF($C31="faizan",IFERROR(INDEX('faizan grading'!$E:$Q,MATCH($A31&"|"&$B31,'faizan grading'!$S:$S,0),COLUMN()-3),""),IF($C31="romain",IFERROR(INDEX('romain grading'!$E:$Q,MATCH($A31&"|"&$B31,'romain grading'!$S:$S,0),COLUMN()-3),""),IF($C31="nishita",IFERROR(INDEX('nishita grading'!$E:$Q,MATCH($A31&"|"&$B31,'nishita grading'!$S:$S,0),COLUMN()-3),""),""))) -> 6 | G31: =IF($C31="faizan",IFERROR(INDEX('faizan grading'!$E:$Q,MATCH($A31&"|"&$B31,'faizan grading'!$S:$S,0),COLUMN()-3),""),IF($C31="romain",IFERROR(INDEX('romain grading'!$E:$Q,MATCH($A31&"|"&$B31,'romain grading'!$S:$S,0),COLUMN()-3),""),IF($C31="nishita",IFERROR(INDEX('nishita grading'!$E:$Q,MATCH($A31&"|"&$B31,'nishita grading'!$S:$S,0),COLUMN()-3),""),""))) -> 0 | H31: =IF($C31="faizan",IFERROR(INDEX('faizan grading'!$E:$Q,MATCH($A31&"|"&$B31,'faizan grading'!$S:$S,0),COLUMN()-3),""),IF($C31="romain",IFERROR(INDEX('romain grading'!$E:$Q,MATCH($A31&"|"&$B31,'romain grading'!$S:$S,0),COLUMN()-3),""),IF($C31="nishita",IFERROR(INDEX('nishita grading'!$E:$Q,MATCH($A31&"|"&$B31,'nishita grading'!$S:$S,0),COLUMN()-3),""),""))) -> 0 | I31: =IF($C31="faizan",IFERROR(INDEX('faizan grading'!$E:$Q,MATCH($A31&"|"&$B31,'faizan grading'!$S:$S,0),COLUMN()-3),""),IF($C31="romain",IFERROR(INDEX('romain grading'!$E:$Q,MATCH($A31&"|"&$B31,'romain grading'!$S:$S,0),COLUMN()-3),""),IF($C31="nishita",IFERROR(INDEX('nishita grading'!$E:$Q,MATCH($A31&"|"&$B31,'nishita grading'!$S:$S,0),COLUMN()-3),""),""))) -> 0 | J31: =IF($C31="faizan",IFERROR(INDEX('faizan grading'!$E:$Q,MATCH($A31&"|"&$B31,'faizan grading'!$S:$S,0),COLUMN()-3),""),IF($C31="romain",IFERROR(INDEX('romain grading'!$E:$Q,MATCH($A31&"|"&$B31,'romain grading'!$S:$S,0),COLUMN()-3),""),IF($C31="nishita",IFERROR(INDEX('nishita grading'!$E:$Q,MATCH($A31&"|"&$B31,'nishita grading'!$S:$S,0),COLUMN()-3),""),""))) -> 0 | K31: =IF($C31="faizan",IFERROR(INDEX('faizan grading'!$E:$Q,MATCH($A31&"|"&$B31,'faizan grading'!$S:$S,0),COLUMN()-3),""),IF($C31="romain",IFERROR(INDEX('romain grading'!$E:$Q,MATCH($A31&"|"&$B31,'romain grading'!$S:$S,0),COLUMN()-3),""),IF($C31="nishita",IFERROR(INDEX('nishita grading'!$E:$Q,MATCH($A31&"|"&$B31,'nishita grading'!$S:$S,0),COLUMN()-3),""),""))) -> 0 | ... P31: =IF($C31="faizan",IFERROR(INDEX('faizan grading'!$E:$Q,MATCH($A31&"|"&$B31,'faizan grading'!$S:$S,0),COLUMN()-3),""),IF($C31="romain",IFERROR(INDEX('romain grading'!$E:$Q,MATCH($A31&"|"&$B31,'romain grading'!$S:$S,0),COLUMN()-3),""),IF($C31="nishita",IFERROR(INDEX('nishita grading'!$E:$Q,MATCH($A31&"|"&$B31,'nishita grading'!$S:$S,0),COLUMN()-3),""),""))) -> 0 | Q31: =40-SUM(D31:P31) -> 34 | R31: =A31&"|"&B31 -> chaotic|0097
A32: chaotic | B32: 0097 | C32: nishita | D32: =IF($C32="faizan",IFERROR(INDEX('faizan grading'!$E:$Q,MATCH($A32&"|"&$B32,'faizan grading'!$S:$S,0),COLUMN()-3),""),IF($C32="romain",IFERROR(INDEX('romain grading'!$E:$Q,MATCH($A32&"|"&$B32,'romain grading'!$S:$S,0),COLUMN()-3),""),IF($C32="nishita",IFERROR(INDEX('nishita grading'!$E:$Q,MATCH($A32&"|"&$B32,'nishita grading'!$S:$S,0),COLUMN()-3),""),""))) -> 12 | E32: =IF($C32="faizan",IFERROR(INDEX('faizan grading'!$E:$Q,MATCH($A32&"|"&$B32,'faizan grading'!$S:$S,0),COLUMN()-3),""),IF($C32="romain",IFERROR(INDEX('romain grading'!$E:$Q,MATCH($A32&"|"&$B32,'romain grading'!$S:$S,0),COLUMN()-3),""),IF($C32="nishita",IFERROR(INDEX('nishita grading'!$E:$Q,MATCH($A32&"|"&$B32,'nishita grading'!$S:$S,0),COLUMN()-3),""),""))) -> 0 | F32: =IF($C32="faizan",IFERROR(INDEX('faizan grading'!$E:$Q,MATCH($A32&"|"&$B32,'faizan grading'!$S:$S,0),COLUMN()-3),""),IF($C32="romain",IFERROR(INDEX('romain grading'!$E:$Q,MATCH($A32&"|"&$B32,'romain grading'!$S:$S,0),COLUMN()-3),""),IF($C32="nishita",IFERROR(INDEX('nishita grading'!$E:$Q,MATCH($A32&"|"&$B32,'nishita grading'!$S:$S,0),COLUMN()-3),""),""))) -> 0 | G32: =IF($C32="faizan",IFERROR(INDEX('faizan grading'!$E:$Q,MATCH($A32&"|"&$B32,'faizan grading'!$S:$S,0),COLUMN()-3),""),IF($C32="romain",IFERROR(INDEX('romain grading'!$E:$Q,MATCH($A32&"|"&$B32,'romain grading'!$S:$S,0),COLUMN()-3),""),IF($C32="nishita",IFERROR(INDEX('nishita grading'!$E:$Q,MATCH($A32&"|"&$B32,'nishita grading'!$S:$S,0),COLUMN()-3),""),""))) -> 0 | H32: =IF($C32="faizan",IFERROR(INDEX('faizan grading'!$E:$Q,MATCH($A32&"|"&$B32,'faizan grading'!$S:$S,0),COLUMN()-3),""),IF($C32="romain",IFERROR(INDEX('romain grading'!$E:$Q,MATCH($A32&"|"&$B32,'romain grading'!$S:$S,0),COLUMN()-3),""),IF($C32="nishita",IFERROR(INDEX('nishita grading'!$E:$Q,MATCH($A32&"|"&$B32,'nishita grading'!$S:$S,0),COLUMN()-3),""),""))) -> 0 | I32: =IF($C32="faizan",IFERROR(INDEX('faizan grading'!$E:$Q,MATCH($A32&"|"&$B32,'faizan grading'!$S:$S,0),COLUMN()-3),""),IF($C32="romain",IFERROR(INDEX('romain grading'!$E:$Q,MATCH($A32&"|"&$B32,'romain grading'!$S:$S,0),COLUMN()-3),""),IF($C32="nishita",IFERROR(INDEX('nishita grading'!$E:$Q,MATCH($A32&"|"&$B32,'nishita grading'!$S:$S,0),COLUMN()-3),""),""))) -> 0 | J32: =IF($C32="faizan",IFERROR(INDEX('faizan grading'!$E:$Q,MATCH($A32&"|"&$B32,'faizan grading'!$S:$S,0),COLUMN()-3),""),IF($C32="romain",IFERROR(INDEX('romain grading'!$E:$Q,MATCH($A32&"|"&$B32,'romain grading'!$S:$S,0),COLUMN()-3),""),IF($C32="nishita",IFERROR(INDEX('nishita grading'!$E:$Q,MATCH($A32&"|"&$B32,'nishita grading'!$S:$S,0),COLUMN()-3),""),""))) -> 0 | K32: =IF($C32="faizan",IFERROR(INDEX('faizan grading'!$E:$Q,MATCH($A32&"|"&$B32,'faizan grading'!$S:$S,0),COLUMN()-3),""),IF($C32="romain",IFERROR(INDEX('romain grading'!$E:$Q,MATCH($A32&"|"&$B32,'romain grading'!$S:$S,0),COLUMN()-3),""),IF($C32="nishita",IFERROR(INDEX('nishita grading'!$E:$Q,MATCH($A32&"|"&$B32,'nishita grading'!$S:$S,0),COLUMN()-3),""),""))) -> 4 | ... P32: =IF($C32="faizan",IFERROR(INDEX('faizan grading'!$E:$Q,MATCH($A32&"|"&$B32,'faizan grading'!$S:$S,0),COLUMN()-3),""),IF($C32="romain",IFERROR(INDEX('romain grading'!$E:$Q,MATCH($A32&"|"&$B32,'romain grading'!$S:$S,0),COLUMN()-3),""),IF($C32="nishita",IFERROR(INDEX('nishita grading'!$E:$Q,MATCH($A32&"|"&$B32,'nishita grading'!$S:$S,0),COLUMN()-3),""),""))) -> 0 | Q32: =40-SUM(D32:P32) -> 24 | R32: =A32&"|"&B32 -> chaotic|0097
A33: chaotic | B33: 0097 | C33: claude | D33: 12 | E33: 0 | F33: 0 | G33: 0 | H33: 0 | I33: 0 | J33: 0 | K33: 0 | L33: 0 | M33: 0 | N33: 0 | O33: 0 | P33: 2 | Q33: =40-SUM(D33:P33) -> 26 | R33: =A33&"|"&B33 -> chaotic|0097
A34: chaotic | B34: 0198 | C34: faizan | D34: =IF($C34="faizan",IFERROR(INDEX('faizan grading'!$E:$Q,MATCH($A34&"|"&$B34,'faizan grading'!$S:$S,0),COLUMN()-3),""),IF($C34="romain",IFERROR(INDEX('romain grading'!$E:$Q,MATCH($A34&"|"&$B34,'romain grading'!$S:$S,0),COLUMN()-3),""),IF($C34="nishita",IFERROR(INDEX('nishita grading'!$E:$Q,MATCH($A34&"|"&$B34,'nishita grading'!$S:$S,0),COLUMN()-3),""),""))) -> 0 | E34: =IF($C34="faizan",IFERROR(INDEX('faizan grading'!$E:$Q,MATCH($A34&"|"&$B34,'faizan grading'!$S:$S,0),COLUMN()-3),""),IF($C34="romain",IFERROR(INDEX('romain grading'!$E:$Q,MATCH($A34&"|"&$B34,'romain grading'!$S:$S,0),COLUMN()-3),""),IF($C34="nishita",IFERROR(INDEX('nishita grading'!$E:$Q,MATCH($A34&"|"&$B34,'nishita grading'!$S:$S,0),COLUMN()-3),""),""))) -> 0 | F34: =IF($C34="faizan",IFERROR(INDEX('faizan grading'!$E:$Q,MATCH($A34&"|"&$B34,'faizan grading'!$S:$S,0),COLUMN()-3),""),IF($C34="romain",IFERROR(INDEX('romain grading'!$E:$Q,MATCH($A34&"|"&$B34,'romain grading'!$S:$S,0),COLUMN()-3),""),IF($C34="nishita",IFERROR(INDEX('nishita grading'!$E:$Q,MATCH($A34&"|"&$B34,'nishita grading'!$S:$S,0),COLUMN()-3),""),""))) -> 0 | G34: =IF($C34="faizan",IFERROR(INDEX('faizan grading'!$E:$Q,MATCH($A34&"|"&$B34,'faizan grading'!$S:$S,0),COLUMN()-3),""),IF($C34="romain",IFERROR(INDEX('romain grading'!$E:$Q,MATCH($A34&"|"&$B34,'romain grading'!$S:$S,0),COLUMN()-3),""),IF($C34="nishita",IFERROR(INDEX('nishita grading'!$E:$Q,MATCH($A34&"|"&$B34,'nishita grading'!$S:$S,0),COLUMN()-3),""),""))) -> 0 | H34: =IF($C34="faizan",IFERROR(INDEX('faizan grading'!$E:$Q,MATCH($A34&"|"&$B34,'faizan grading'!$S:$S,0),COLUMN()-3),""),IF($C34="romain",IFERROR(INDEX('romain grading'!$E:$Q,MATCH($A34&"|"&$B34,'romain grading'!$S:$S,0),COLUMN()-3),""),IF($C34="nishita",IFERROR(INDEX('nishita grading'!$E:$Q,MATCH($A34&"|"&$B34,'nishita grading'!$S:$S,0),COLUMN()-3),""),""))) -> 0 | I34: =IF($C34="faizan",IFERROR(INDEX('faizan grading'!$E:$Q,MATCH($A34&"|"&$B34,'faizan grading'!$S:$S,0),COLUMN()-3),""),IF($C34="romain",IFERROR(INDEX('romain grading'!$E:$Q,MATCH($A34&"|"&$B34,'romain grading'!$S:$S,0),COLUMN()-3),""),IF($C34="nishita",IFERROR(INDEX('nishita grading'!$E:$Q,MATCH($A34&"|"&$B34,'nishita grading'!$S:$S,0),COLUMN()-3),""),""))) -> 0 | J34: =IF($C34="faizan",IFERROR(INDEX('faizan grading'!$E:$Q,MATCH($A34&"|"&$B34,'faizan grading'!$S:$S,0),COLUMN()-3),""),IF($C34="romain",IFERROR(INDEX('romain grading'!$E:$Q,MATCH($A34&"|"&$B34,'romain grading'!$S:$S,0),COLUMN()-3),""),IF($C34="nishita",IFERROR(INDEX('nishita grading'!$E:$Q,MATCH($A34&"|"&$B34,'nishita grading'!$S:$S,0),COLUMN()-3),""),""))) -> 0 | K34: =IF($C34="faizan",IFERROR(INDEX('faizan grading'!$E:$Q,MATCH($A34&"|"&$B34,'faizan grading'!$S:$S,0),COLUMN()-3),""),IF($C34="romain",IFERROR(INDEX('romain grading'!$E:$Q,MATCH($A34&"|"&$B34,'romain grading'!$S:$S,0),COLUMN()-3),""),IF($C34="nishita",IFERROR(INDEX('nishita grading'!$E:$Q,MATCH($A34&"|"&$B34,'nishita grading'!$S:$S,0),COLUMN()-3),""),""))) -> 0 | ... P34: =IF($C34="faizan",IFERROR(INDEX('faizan grading'!$E:$Q,MATCH($A34&"|"&$B34,'faizan grading'!$S:$S,0),COLUMN()-3),""),IF($C34="romain",IFERROR(INDEX('romain grading'!$E:$Q,MATCH($A34&"|"&$B34,'romain grading'!$S:$S,0),COLUMN()-3),""),IF($C34="nishita",IFERROR(INDEX('nishita grading'!$E:$Q,MATCH($A34&"|"&$B34,'nishita grading'!$S:$S,0),COLUMN()-3),""),""))) -> 0 | Q34: =40-SUM(D34:P34) -> 40 | R34: =A34&"|"&B34 -> chaotic|0198
A35: chaotic | B35: 0198 | C35: romain | D35: =IF($C35="faizan",IFERROR(INDEX('faizan grading'!$E:$Q,MATCH($A35&"|"&$B35,'faizan grading'!$S:$S,0),COLUMN()-3),""),IF($C35="romain",IFERROR(INDEX('romain grading'!$E:$Q,MATCH($A35&"|"&$B35,'romain grading'!$S:$S,0),COLUMN()-3),""),IF($C35="nishita",IFERROR(INDEX('nishita grading'!$E:$Q,MATCH($A35&"|"&$B35,'nishita grading'!$S:$S,0),COLUMN()-3),""),""))) -> ✗ | E35: =IF($C35="faizan",IFERROR(INDEX('faizan grading'!$E:$Q,MATCH($A35&"|"&$B35,'faizan grading'!$S:$S,0),COLUMN()-3),""),IF($C35="romain",IFERROR(INDEX('romain grading'!$E:$Q,MATCH($A35&"|"&$B35,'romain grading'!$S:$S,0),COLUMN()-3),""),IF($C35="nishita",IFERROR(INDEX('nishita grading'!$E:$Q,MATCH($A35&"|"&$B35,'nishita grading'!$S:$S,0),COLUMN()-3),""),""))) -> 0 | F35: =IF($C35="faizan",IFERROR(INDEX('faizan grading'!$E:$Q,MATCH($A35&"|"&$B35,'faizan grading'!$S:$S,0),COLUMN()-3),""),IF($C35="romain",IFERROR(INDEX('romain grading'!$E:$Q,MATCH($A35&"|"&$B35,'romain grading'!$S:$S,0),COLUMN()-3),""),IF($C35="nishita",IFERROR(INDEX('nishita grading'!$E:$Q,MATCH($A35&"|"&$B35,'nishita grading'!$S:$S,0),COLUMN()-3),""),""))) -> 0 | G35: =IF($C35="faizan",IFERROR(INDEX('faizan grading'!$E:$Q,MATCH($A35&"|"&$B35,'faizan grading'!$S:$S,0),COLUMN()-3),""),IF($C35="romain",IFERROR(INDEX('romain grading'!$E:$Q,MATCH($A35&"|"&$B35,'romain grading'!$S:$S,0),COLUMN()-3),""),IF($C35="nishita",IFERROR(INDEX('nishita grading'!$E:$Q,MATCH($A35&"|"&$B35,'nishita grading'!$S:$S,0),COLUMN()-3),""),""))) -> 0 | H35: =IF($C35="faizan",IFERROR(INDEX('faizan grading'!$E:$Q,MATCH($A35&"|"&$B35,'faizan grading'!$S:$S,0),COLUMN()-3),""),IF($C35="romain",IFERROR(INDEX('romain grading'!$E:$Q,MATCH($A35&"|"&$B35,'romain grading'!$S:$S,0),COLUMN()-3),""),IF($C35="nishita",IFERROR(INDEX('nishita grading'!$E:$Q,MATCH($A35&"|"&$B35,'nishita grading'!$S:$S,0),COLUMN()-3),""),""))) -> 0 | I35: =IF($C35="faizan",IFERROR(INDEX('faizan grading'!$E:$Q,MATCH($A35&"|"&$B35,'faizan grading'!$S:$S,0),COLUMN()-3),""),IF($C35="romain",IFERROR(INDEX('romain grading'!$E:$Q,MATCH($A35&"|"&$B35,'romain grading'!$S:$S,0),COLUMN()-3),""),IF($C35="nishita",IFERROR(INDEX('nishita grading'!$E:$Q,MATCH($A35&"|"&$B35,'nishita grading'!$S:$S,0),COLUMN()-3),""),""))) -> 0 | J35: =IF($C35="faizan",IFERROR(INDEX('faizan grading'!$E:$Q,MATCH($A35&"|"&$B35,'faizan grading'!$S:$S,0),COLUMN()-3),""),IF($C35="romain",IFERROR(INDEX('romain grading'!$E:$Q,MATCH($A35&"|"&$B35,'romain grading'!$S:$S,0),COLUMN()-3),""),IF($C35="nishita",IFERROR(INDEX('nishita grading'!$E:$Q,MATCH($A35&"|"&$B35,'nishita grading'!$S:$S,0),COLUMN()-3),""),""))) -> 0 | K35: =IF($C35="faizan",IFERROR(INDEX('faizan grading'!$E:$Q,MATCH($A35&"|"&$B35,'faizan grading'!$S:$S,0),COLUMN()-3),""),IF($C35="romain",IFERROR(INDEX('romain grading'!$E:$Q,MATCH($A35&"|"&$B35,'romain grading'!$S:$S,0),COLUMN()-3),""),IF($C35="nishita",IFERROR(INDEX('nishita grading'!$E:$Q,MATCH($A35&"|"&$B35,'nishita grading'!$S:$S,0),COLUMN()-3),""),""))) -> 0 | ... P35: =IF($C35="faizan",IFERROR(INDEX('faizan grading'!$E:$Q,MATCH($A35&"|"&$B35,'faizan grading'!$S:$S,0),COLUMN()-3),""),IF($C35="romain",IFERROR(INDEX('romain grading'!$E:$Q,MATCH($A35&"|"&$B35,'romain grading'!$S:$S,0),COLUMN()-3),""),IF($C35="nishita",IFERROR(INDEX('nishita grading'!$E:$Q,MATCH($A35&"|"&$B35,'nishita grading'!$S:$S,0),COLUMN()-3),""),""))) -> 0 | Q35: =40-SUM(D35:P35) -> 40 | R35: =A35&"|"&B35 -> chaotic|0198
A36: chaotic | B36: 0198 | C36: nishita | D36: =IF($C36="faizan",IFERROR(INDEX('faizan grading'!$E:$Q,MATCH($A36&"|"&$B36,'faizan grading'!$S:$S,0),COLUMN()-3),""),IF($C36="romain",IFERROR(INDEX('romain grading'!$E:$Q,MATCH($A36&"|"&$B36,'romain grading'!$S:$S,0),COLUMN()-3),""),IF($C36="nishita",IFERROR(INDEX('nishita grading'!$E:$Q,MATCH($A36&"|"&$B36,'nishita grading'!$S:$S,0),COLUMN()-3),""),""))) -> 0 | E36: =IF($C36="faizan",IFERROR(INDEX('faizan grading'!$E:$Q,MATCH($A36&"|"&$B36,'faizan grading'!$S:$S,0),COLUMN()-3),""),IF($C36="romain",IFERROR(INDEX('romain grading'!$E:$Q,MATCH($A36&"|"&$B36,'romain grading'!$S:$S,0),COLUMN()-3),""),IF($C36="nishita",IFERROR(INDEX('nishita grading'!$E:$Q,MATCH($A36&"|"&$B36,'nishita grading'!$S:$S,0),COLUMN()-3),""),""))) -> 0 | F36: =IF($C36="faizan",IFERROR(INDEX('faizan grading'!$E:$Q,MATCH($A36&"|"&$B36,'faizan grading'!$S:$S,0),COLUMN()-3),""),IF($C36="romain",IFERROR(INDEX('romain grading'!$E:$Q,MATCH($A36&"|"&$B36,'romain grading'!$S:$S,0),COLUMN()-3),""),IF($C36="nishita",IFERROR(INDEX('nishita grading'!$E:$Q,MATCH($A36&"|"&$B36,'nishita grading'!$S:$S,0),COLUMN()-3),""),""))) -> 0 | G36: =IF($C36="faizan",IFERROR(INDEX('faizan grading'!$E:$Q,MATCH($A36&"|"&$B36,'faizan grading'!$S:$S,0),COLUMN()-3),""),IF($C36="romain",IFERROR(INDEX('romain grading'!$E:$Q,MATCH($A36&"|"&$B36,'romain grading'!$S:$S,0),COLUMN()-3),""),IF($C36="nishita",IFERROR(INDEX('nishita grading'!$E:$Q,MATCH($A36&"|"&$B36,'nishita grading'!$S:$S,0),COLUMN()-3),""),""))) -> 0 | H36: =IF($C36="faizan",IFERROR(INDEX('faizan grading'!$E:$Q,MATCH($A36&"|"&$B36,'faizan grading'!$S:$S,0),COLUMN()-3),""),IF($C36="romain",IFERROR(INDEX('romain grading'!$E:$Q,MATCH($A36&"|"&$B36,'romain grading'!$S:$S,0),COLUMN()-3),""),IF($C36="nishita",IFERROR(INDEX('nishita grading'!$E:$Q,MATCH($A36&"|"&$B36,'nishita grading'!$S:$S,0),COLUMN()-3),""),""))) -> 0 | I36: =IF($C36="faizan",IFERROR(INDEX('faizan grading'!$E:$Q,MATCH($A36&"|"&$B36,'faizan grading'!$S:$S,0),COLUMN()-3),""),IF($C36="romain",IFERROR(INDEX('romain grading'!$E:$Q,MATCH($A36&"|"&$B36,'romain grading'!$S:$S,0),COLUMN()-3),""),IF($C36="nishita",IFERROR(INDEX('nishita grading'!$E:$Q,MATCH($A36&"|"&$B36,'nishita grading'!$S:$S,0),COLUMN()-3),""),""))) -> 0 | J36: =IF($C36="faizan",IFERROR(INDEX('faizan grading'!$E:$Q,MATCH($A36&"|"&$B36,'faizan grading'!$S:$S,0),COLUMN()-3),""),IF($C36="romain",IFERROR(INDEX('romain grading'!$E:$Q,MATCH($A36&"|"&$B36,'romain grading'!$S:$S,0),COLUMN()-3),""),IF($C36="nishita",IFERROR(INDEX('nishita grading'!$E:$Q,MATCH($A36&"|"&$B36,'nishita grading'!$S:$S,0),COLUMN()-3),""),""))) -> 0 | K36: =IF($C36="faizan",IFERROR(INDEX('faizan grading'!$E:$Q,MATCH($A36&"|"&$B36,'faizan grading'!$S:$S,0),COLUMN()-3),""),IF($C36="romain",IFERROR(INDEX('romain grading'!$E:$Q,MATCH($A36&"|"&$B36,'romain grading'!$S:$S,0),COLUMN()-3),""),IF($C36="nishita",IFERROR(INDEX('nishita grading'!$E:$Q,MATCH($A36&"|"&$B36,'nishita grading'!$S:$S,0),COLUMN()-3),""),""))) -> 4 | ... P36: =IF($C36="faizan",IFERROR(INDEX('faizan grading'!$E:$Q,MATCH($A36&"|"&$B36,'faizan grading'!$S:$S,0),COLUMN()-3),""),IF($C36="romain",IFERROR(INDEX('romain grading'!$E:$Q,MATCH($A36&"|"&$B36,'romain grading'!$S:$S,0),COLUMN()-3),""),IF($C36="nishita",IFERROR(INDEX('nishita grading'!$E:$Q,MATCH($A36&"|"&$B36,'nishita grading'!$S:$S,0),COLUMN()-3),""),""))) -> 0 | Q36: =40-SUM(D36:P36) -> 34 | R36: =A36&"|"&B36 -> chaotic|0198
A37: chaotic | B37: 0198 | C37: claude | D37: 0 | E37: 0 | F37: 0 | G37: 0 | H37: 3 | I37: 0 | J37: 0 | K37: 0 | L37: 0 | M37: 0 | N37: 0 | O37: 2 | P37: 0 | Q37: =40-SUM(D37:P37) -> 35 | R37: =A37&"|"&B37 -> chaotic|0198
A38: chaotic | B38: 0228 | C38: faizan | D38: =IF($C38="faizan",IFERROR(INDEX('faizan grading'!$E:$Q,MATCH($A38&"|"&$B38,'faizan grading'!$S:$S,0),COLUMN()-3),""),IF($C38="romain",IFERROR(INDEX('romain grading'!$E:$Q,MATCH($A38&"|"&$B38,'romain grading'!$S:$S,0),COLUMN()-3),""),IF($C38="nishita",IFERROR(INDEX('nishita grading'!$E:$Q,MATCH($A38&"|"&$B38,'nishita grading'!$S:$S,0),COLUMN()-3),""),""))) -> 0 | E38: =IF($C38="faizan",IFERROR(INDEX('faizan grading'!$E:$Q,MATCH($A38&"|"&$B38,'faizan grading'!$S:$S,0),COLUMN()-3),""),IF($C38="romain",IFERROR(INDEX('romain grading'!$E:$Q,MATCH($A38&"|"&$B38,'romain grading'!$S:$S,0),COLUMN()-3),""),IF($C38="nishita",IFERROR(INDEX('nishita grading'!$E:$Q,MATCH($A38&"|"&$B38,'nishita grading'!$S:$S,0),COLUMN()-3),""),""))) -> 0 | F38: =IF($C38="faizan",IFERROR(INDEX('faizan grading'!$E:$Q,MATCH($A38&"|"&$B38,'faizan grading'!$S:$S,0),COLUMN()-3),""),IF($C38="romain",IFERROR(INDEX('romain grading'!$E:$Q,MATCH($A38&"|"&$B38,'romain grading'!$S:$S,0),COLUMN()-3),""),IF($C38="nishita",IFERROR(INDEX('nishita grading'!$E:$Q,MATCH($A38&"|"&$B38,'nishita grading'!$S:$S,0),COLUMN()-3),""),""))) -> 0 | G38: =IF($C38="faizan",IFERROR(INDEX('faizan grading'!$E:$Q,MATCH($A38&"|"&$B38,'faizan grading'!$S:$S,0),COLUMN()-3),""),IF($C38="romain",IFERROR(INDEX('romain grading'!$E:$Q,MATCH($A38&"|"&$B38,'romain grading'!$S:$S,0),COLUMN()-3),""),IF($C38="nishita",IFERROR(INDEX('nishita grading'!$E:$Q,MATCH($A38&"|"&$B38,'nishita grading'!$S:$S,0),COLUMN()-3),""),""))) -> 0 | H38: =IF($C38="faizan",IFERROR(INDEX('faizan grading'!$E:$Q,MATCH($A38&"|"&$B38,'faizan grading'!$S:$S,0),COLUMN()-3),""),IF($C38="romain",IFERROR(INDEX('romain grading'!$E:$Q,MATCH($A38&"|"&$B38,'romain grading'!$S:$S,0),COLUMN()-3),""),IF($C38="nishita",IFERROR(INDEX('nishita grading'!$E:$Q,MATCH($A38&"|"&$B38,'nishita grading'!$S:$S,0),COLUMN()-3),""),""))) -> 0 | I38: =IF($C38="faizan",IFERROR(INDEX('faizan grading'!$E:$Q,MATCH($A38&"|"&$B38,'faizan grading'!$S:$S,0),COLUMN()-3),""),IF($C38="romain",IFERROR(INDEX('romain grading'!$E:$Q,MATCH($A38&"|"&$B38,'romain grading'!$S:$S,0),COLUMN()-3),""),IF($C38="nishita",IFERROR(INDEX('nishita grading'!$E:$Q,MATCH($A38&"|"&$B38,'nishita grading'!$S:$S,0),COLUMN()-3),""),""))) -> 0 | J38: =IF($C38="faizan",IFERROR(INDEX('faizan grading'!$E:$Q,MATCH($A38&"|"&$B38,'faizan grading'!$S:$S,0),COLUMN()-3),""),IF($C38="romain",IFERROR(INDEX('romain grading'!$E:$Q,MATCH($A38&"|"&$B38,'romain grading'!$S:$S,0),COLUMN()-3),""),IF($C38="nishita",IFERROR(INDEX('nishita grading'!$E:$Q,MATCH($A38&"|"&$B38,'nishita grading'!$S:$S,0),COLUMN()-3),""),""))) -> 0 | K38: =IF($C38="faizan",IFERROR(INDEX('faizan grading'!$E:$Q,MATCH($A38&"|"&$B38,'faizan grading'!$S:$S,0),COLUMN()-3),""),IF($C38="romain",IFERROR(INDEX('romain grading'!$E:$Q,MATCH($A38&"|"&$B38,'romain grading'!$S:$S,0),COLUMN()-3),""),IF($C38="nishita",IFERROR(INDEX('nishita grading'!$E:$Q,MATCH($A38&"|"&$B38,'nishita grading'!$S:$S,0),COLUMN()-3),""),""))) -> 0 | ... P38: =IF($C38="faizan",IFERROR(INDEX('faizan grading'!$E:$Q,MATCH($A38&"|"&$B38,'faizan grading'!$S:$S,0),COLUMN()-3),""),IF($C38="romain",IFERROR(INDEX('romain grading'!$E:$Q,MATCH($A38&"|"&$B38,'romain grading'!$S:$S,0),COLUMN()-3),""),IF($C38="nishita",IFERROR(INDEX('nishita grading'!$E:$Q,MATCH($A38&"|"&$B38,'nishita grading'!$S:$S,0),COLUMN()-3),""),""))) -> 0 | Q38: =40-SUM(D38:P38) -> 40 | R38: =A38&"|"&B38 -> chaotic|0228
A39: chaotic | B39: 0228 | C39: romain | D39: =IF($C39="faizan",IFERROR(INDEX('faizan grading'!$E:$Q,MATCH($A39&"|"&$B39,'faizan grading'!$S:$S,0),COLUMN()-3),""),IF($C39="romain",IFERROR(INDEX('romain grading'!$E:$Q,MATCH($A39&"|"&$B39,'romain grading'!$S:$S,0),COLUMN()-3),""),IF($C39="nishita",IFERROR(INDEX('nishita grading'!$E:$Q,MATCH($A39&"|"&$B39,'nishita grading'!$S:$S,0),COLUMN()-3),""),""))) -> 0 | E39: =IF($C39="faizan",IFERROR(INDEX('faizan grading'!$E:$Q,MATCH($A39&"|"&$B39,'faizan grading'!$S:$S,0),COLUMN()-3),""),IF($C39="romain",IFERROR(INDEX('romain grading'!$E:$Q,MATCH($A39&"|"&$B39,'romain grading'!$S:$S,0),COLUMN()-3),""),IF($C39="nishita",IFERROR(INDEX('nishita grading'!$E:$Q,MATCH($A39&"|"&$B39,'nishita grading'!$S:$S,0),COLUMN()-3),""),""))) -> 0 | F39: =IF($C39="faizan",IFERROR(INDEX('faizan grading'!$E:$Q,MATCH($A39&"|"&$B39,'faizan grading'!$S:$S,0),COLUMN()-3),""),IF($C39="romain",IFERROR(INDEX('romain grading'!$E:$Q,MATCH($A39&"|"&$B39,'romain grading'!$S:$S,0),COLUMN()-3),""),IF($C39="nishita",IFERROR(INDEX('nishita grading'!$E:$Q,MATCH($A39&"|"&$B39,'nishita grading'!$S:$S,0),COLUMN()-3),""),""))) -> 0 | G39: =IF($C39="faizan",IFERROR(INDEX('faizan grading'!$E:$Q,MATCH($A39&"|"&$B39,'faizan grading'!$S:$S,0),COLUMN()-3),""),IF($C39="romain",IFERROR(INDEX('romain grading'!$E:$Q,MATCH($A39&"|"&$B39,'romain grading'!$S:$S,0),COLUMN()-3),""),IF($C39="nishita",IFERROR(INDEX('nishita grading'!$E:$Q,MATCH($A39&"|"&$B39,'nishita grading'!$S:$S,0),COLUMN()-3),""),""))) -> 0 | H39: =IF($C39="faizan",IFERROR(INDEX('faizan grading'!$E:$Q,MATCH($A39&"|"&$B39,'faizan grading'!$S:$S,0),COLUMN()-3),""),IF($C39="romain",IFERROR(INDEX('romain grading'!$E:$Q,MATCH($A39&"|"&$B39,'romain grading'!$S:$S,0),COLUMN()-3),""),IF($C39="nishita",IFERROR(INDEX('nishita grading'!$E:$Q,MATCH($A39&"|"&$B39,'nishita grading'!$S:$S,0),COLUMN()-3),""),""))) -> 0 | I39: =IF($C39="faizan",IFERROR(INDEX('faizan grading'!$E:$Q,MATCH($A39&"|"&$B39,'faizan grading'!$S:$S,0),COLUMN()-3),""),IF($C39="romain",IFERROR(INDEX('romain grading'!$E:$Q,MATCH($A39&"|"&$B39,'romain grading'!$S:$S,0),COLUMN()-3),""),IF($C39="nishita",IFERROR(INDEX('nishita grading'!$E:$Q,MATCH($A39&"|"&$B39,'nishita grading'!$S:$S,0),COLUMN()-3),""),""))) -> 0 | J39: =IF($C39="faizan",IFERROR(INDEX('faizan grading'!$E:$Q,MATCH($A39&"|"&$B39,'faizan grading'!$S:$S,0),COLUMN()-3),""),IF($C39="romain",IFERROR(INDEX('romain grading'!$E:$Q,MATCH($A39&"|"&$B39,'romain grading'!$S:$S,0),COLUMN()-3),""),IF($C39="nishita",IFERROR(INDEX('nishita grading'!$E:$Q,MATCH($A39&"|"&$B39,'nishita grading'!$S:$S,0),COLUMN()-3),""),""))) -> 0 | K39: =IF($C39="faizan",IFERROR(INDEX('faizan grading'!$E:$Q,MATCH($A39&"|"&$B39,'faizan grading'!$S:$S,0),COLUMN()-3),""),IF($C39="romain",IFERROR(INDEX('romain grading'!$E:$Q,MATCH($A39&"|"&$B39,'romain grading'!$S:$S,0),COLUMN()-3),""),IF($C39="nishita",IFERROR(INDEX('nishita grading'!$E:$Q,MATCH($A39&"|"&$B39,'nishita grading'!$S:$S,0),COLUMN()-3),""),""))) -> 0 | ... P39: =IF($C39="faizan",IFERROR(INDEX('faizan grading'!$E:$Q,MATCH($A39&"|"&$B39,'faizan grading'!$S:$S,0),COLUMN()-3),""),IF($C39="romain",IFERROR(INDEX('romain grading'!$E:$Q,MATCH($A39&"|"&$B39,'romain grading'!$S:$S,0),COLUMN()-3),""),IF($C39="nishita",IFERROR(INDEX('nishita grading'!$E:$Q,MATCH($A39&"|"&$B39,'nishita grading'!$S:$S,0),COLUMN()-3),""),""))) -> 0 | Q39: =40-SUM(D39:P39) -> 40 | R39: =A39&"|"&B39 -> chaotic|0228
A40: chaotic | B40: 0228 | C40: nishita | D40: =IF($C40="faizan",IFERROR(INDEX('faizan grading'!$E:$Q,MATCH($A40&"|"&$B40,'faizan grading'!$S:$S,0),COLUMN()-3),""),IF($C40="romain",IFERROR(INDEX('romain grading'!$E:$Q,MATCH($A40&"|"&$B40,'romain grading'!$S:$S,0),COLUMN()-3),""),IF($C40="nishita",IFERROR(INDEX('nishita grading'!$E:$Q,MATCH($A40&"|"&$B40,'nishita grading'!$S:$S,0),COLUMN()-3),""),""))) -> 0 | E40: =IF($C40="faizan",IFERROR(INDEX('faizan grading'!$E:$Q,MATCH($A40&"|"&$B40,'faizan grading'!$S:$S,0),COLUMN()-3),""),IF($C40="romain",IFERROR(INDEX('romain grading'!$E:$Q,MATCH($A40&"|"&$B40,'romain grading'!$S:$S,0),COLUMN()-3),""),IF($C40="nishita",IFERROR(INDEX('nishita grading'!$E:$Q,MATCH($A40&"|"&$B40,'nishita grading'!$S:$S,0),COLUMN()-3),""),""))) -> 0 | F40: =IF($C40="faizan",IFERROR(INDEX('faizan grading'!$E:$Q,MATCH($A40&"|"&$B40,'faizan grading'!$S:$S,0),COLUMN()-3),""),IF($C40="romain",IFERROR(INDEX('romain grading'!$E:$Q,MATCH($A40&"|"&$B40,'romain grading'!$S:$S,0),COLUMN()-3),""),IF($C40="nishita",IFERROR(INDEX('nishita grading'!$E:$Q,MATCH($A40&"|"&$B40,'nishita grading'!$S:$S,0),COLUMN()-3),""),""))) -> 0 | G40: =IF($C40="faizan",IFERROR(INDEX('faizan grading'!$E:$Q,MATCH($A40&"|"&$B40,'faizan grading'!$S:$S,0),COLUMN()-3),""),IF($C40="romain",IFERROR(INDEX('romain grading'!$E:$Q,MATCH($A40&"|"&$B40,'romain grading'!$S:$S,0),COLUMN()-3),""),IF($C40="nishita",IFERROR(INDEX('nishita grading'!$E:$Q,MATCH($A40&"|"&$B40,'nishita grading'!$S:$S,0),COLUMN()-3),""),""))) -> 0 | H40: =IF($C40="faizan",IFERROR(INDEX('faizan grading'!$E:$Q,MATCH($A40&"|"&$B40,'faizan grading'!$S:$S,0),COLUMN()-3),""),IF($C40="romain",IFERROR(INDEX('romain grading'!$E:$Q,MATCH($A40&"|"&$B40,'romain grading'!$S:$S,0),COLUMN()-3),""),IF($C40="nishita",IFERROR(INDEX('nishita grading'!$E:$Q,MATCH($A40&"|"&$B40,'nishita grading'!$S:$S,0),COLUMN()-3),""),""))) -> 0 | I40: =IF($C40="faizan",IFERROR(INDEX('faizan grading'!$E:$Q,MATCH($A40&"|"&$B40,'faizan grading'!$S:$S,0),COLUMN()-3),""),IF($C40="romain",IFERROR(INDEX('romain grading'!$E:$Q,MATCH($A40&"|"&$B40,'romain grading'!$S:$S,0),COLUMN()-3),""),IF($C40="nishita",IFERROR(INDEX('nishita grading'!$E:$Q,MATCH($A40&"|"&$B40,'nishita grading'!$S:$S,0),COLUMN()-3),""),""))) -> 0 | J40: =IF($C40="faizan",IFERROR(INDEX('faizan grading'!$E:$Q,MATCH($A40&"|"&$B40,'faizan grading'!$S:$S,0),COLUMN()-3),""),IF($C40="romain",IFERROR(INDEX('romain grading'!$E:$Q,MATCH($A40&"|"&$B40,'romain grading'!$S:$S,0),COLUMN()-3),""),IF($C40="nishita",IFERROR(INDEX('nishita grading'!$E:$Q,MATCH($A40&"|"&$B40,'nishita grading'!$S:$S,0),COLUMN()-3),""),""))) -> 0 | K40: =IF($C40="faizan",IFERROR(INDEX('faizan grading'!$E:$Q,MATCH($A40&"|"&$B40,'faizan grading'!$S:$S,0),COLUMN()-3),""),IF($C40="romain",IFERROR(INDEX('romain grading'!$E:$Q,MATCH($A40&"|"&$B40,'romain grading'!$S:$S,0),COLUMN()-3),""),IF($C40="nishita",IFERROR(INDEX('nishita grading'!$E:$Q,MATCH($A40&"|"&$B40,'nishita grading'!$S:$S,0),COLUMN()-3),""),""))) -> 4 | ... P40: =IF($C40="faizan",IFERROR(INDEX('faizan grading'!$E:$Q,MATCH($A40&"|"&$B40,'faizan grading'!$S:$S,0),COLUMN()-3),""),IF($C40="romain",IFERROR(INDEX('romain grading'!$E:$Q,MATCH($A40&"|"&$B40,'romain grading'!$S:$S,0),COLUMN()-3),""),IF($C40="nishita",IFERROR(INDEX('nishita grading'!$E:$Q,MATCH($A40&"|"&$B40,'nishita grading'!$S:$S,0),COLUMN()-3),""),""))) -> 0 | Q40: =40-SUM(D40:P40) -> 34 | R40: =A40&"|"&B40 -> chaotic|0228
A41: chaotic | B41: 0228 | C41: claude | D41: 0 | E41: 0 | F41: 0 | G41: 0 | H41: 0 | I41: 2 | J41: 0 | K41: 0 | L41: 0 | M41: 0 | N41: 0 | O41: 0 | P41: 0 | Q41: =40-SUM(D41:P41) -> 38 | R41: =A41&"|"&B41 -> chaotic|0228
A42: chaotic | B42: 0243 | C42: faizan | D42: =IF($C42="faizan",IFERROR(INDEX('faizan grading'!$E:$Q,MATCH($A42&"|"&$B42,'faizan grading'!$S:$S,0),COLUMN()-3),""),IF($C42="romain",IFERROR(INDEX('romain grading'!$E:$Q,MATCH($A42&"|"&$B42,'romain grading'!$S:$S,0),COLUMN()-3),""),IF($C42="nishita",IFERROR(INDEX('nishita grading'!$E:$Q,MATCH($A42&"|"&$B42,'nishita grading'!$S:$S,0),COLUMN()-3),""),""))) -> 0 | E42: =IF($C42="faizan",IFERROR(INDEX('faizan grading'!$E:$Q,MATCH($A42&"|"&$B42,'faizan grading'!$S:$S,0),COLUMN()-3),""),IF($C42="romain",IFERROR(INDEX('romain grading'!$E:$Q,MATCH($A42&"|"&$B42,'romain grading'!$S:$S,0),COLUMN()-3),""),IF($C42="nishita",IFERROR(INDEX('nishita grading'!$E:$Q,MATCH($A42&"|"&$B42,'nishita grading'!$S:$S,0),COLUMN()-3),""),""))) -> 0 | F42: =IF($C42="faizan",IFERROR(INDEX('faizan grading'!$E:$Q,MATCH($A42&"|"&$B42,'faizan grading'!$S:$S,0),COLUMN()-3),""),IF($C42="romain",IFERROR(INDEX('romain grading'!$E:$Q,MATCH($A42&"|"&$B42,'romain grading'!$S:$S,0),COLUMN()-3),""),IF($C42="nishita",IFERROR(INDEX('nishita grading'!$E:$Q,MATCH($A42&"|"&$B42,'nishita grading'!$S:$S,0),COLUMN()-3),""),""))) -> 0 | G42: =IF($C42="faizan",IFERROR(INDEX('faizan grading'!$E:$Q,MATCH($A42&"|"&$B42,'faizan grading'!$S:$S,0),COLUMN()-3),""),IF($C42="romain",IFERROR(INDEX('romain grading'!$E:$Q,MATCH($A42&"|"&$B42,'romain grading'!$S:$S,0),COLUMN()-3),""),IF($C42="nishita",IFERROR(INDEX('nishita grading'!$E:$Q,MATCH($A42&"|"&$B42,'nishita grading'!$S:$S,0),COLUMN()-3),""),""))) -> 0 | H42: =IF($C42="faizan",IFERROR(INDEX('faizan grading'!$E:$Q,MATCH($A42&"|"&$B42,'faizan grading'!$S:$S,0),COLUMN()-3),""),IF($C42="romain",IFERROR(INDEX('romain grading'!$E:$Q,MATCH($A42&"|"&$B42,'romain grading'!$S:$S,0),COLUMN()-3),""),IF($C42="nishita",IFERROR(INDEX('nishita grading'!$E:$Q,MATCH($A42&"|"&$B42,'nishita grading'!$S:$S,0),COLUMN()-3),""),""))) -> 0 | I42: =IF($C42="faizan",IFERROR(INDEX('faizan grading'!$E:$Q,MATCH($A42&"|"&$B42,'faizan grading'!$S:$S,0),COLUMN()-3),""),IF($C42="romain",IFERROR(INDEX('romain grading'!$E:$Q,MATCH($A42&"|"&$B42,'romain grading'!$S:$S,0),COLUMN()-3),""),IF($C42="nishita",IFERROR(INDEX('nishita grading'!$E:$Q,MATCH($A42&"|"&$B42,'nishita grading'!$S:$S,0),COLUMN()-3),""),""))) -> 0 | J42: =IF($C42="faizan",IFERROR(INDEX('faizan grading'!$E:$Q,MATCH($A42&"|"&$B42,'faizan grading'!$S:$S,0),COLUMN()-3),""),IF($C42="romain",IFERROR(INDEX('romain grading'!$E:$Q,MATCH($A42&"|"&$B42,'romain grading'!$S:$S,0),COLUMN()-3),""),IF($C42="nishita",IFERROR(INDEX('nishita grading'!$E:$Q,MATCH($A42&"|"&$B42,'nishita grading'!$S:$S,0),COLUMN()-3),""),""))) -> 0 | K42: =IF($C42="faizan",IFERROR(INDEX('faizan grading'!$E:$Q,MATCH($A42&"|"&$B42,'faizan grading'!$S:$S,0),COLUMN()-3),""),IF($C42="romain",IFERROR(INDEX('romain grading'!$E:$Q,MATCH($A42&"|"&$B42,'romain grading'!$S:$S,0),COLUMN()-3),""),IF($C42="nishita",IFERROR(INDEX('nishita grading'!$E:$Q,MATCH($A42&"|"&$B42,'nishita grading'!$S:$S,0),COLUMN()-3),""),""))) -> 0 | ... P42: =IF($C42="faizan",IFERROR(INDEX('faizan grading'!$E:$Q,MATCH($A42&"|"&$B42,'faizan grading'!$S:$S,0),COLUMN()-3),""),IF($C42="romain",IFERROR(INDEX('romain grading'!$E:$Q,MATCH($A42&"|"&$B42,'romain grading'!$S:$S,0),COLUMN()-3),""),IF($C42="nishita",IFERROR(INDEX('nishita grading'!$E:$Q,MATCH($A42&"|"&$B42,'nishita grading'!$S:$S,0),COLUMN()-3),""),""))) -> 0 | Q42: =40-SUM(D42:P42) -> 40 | R42: =A42&"|"&B42 -> chaotic|0243
A43: chaotic | B43: 0243 | C43: romain | D43: =IF($C43="faizan",IFERROR(INDEX('faizan grading'!$E:$Q,MATCH($A43&"|"&$B43,'faizan grading'!$S:$S,0),COLUMN()-3),""),IF($C43="romain",IFERROR(INDEX('romain grading'!$E:$Q,MATCH($A43&"|"&$B43,'romain grading'!$S:$S,0),COLUMN()-3),""),IF($C43="nishita",IFERROR(INDEX('nishita grading'!$E:$Q,MATCH($A43&"|"&$B43,'nishita grading'!$S:$S,0),COLUMN()-3),""),""))) -> 0 | E43: =IF($C43="faizan",IFERROR(INDEX('faizan grading'!$E:$Q,MATCH($A43&"|"&$B43,'faizan grading'!$S:$S,0),COLUMN()-3),""),IF($C43="romain",IFERROR(INDEX('romain grading'!$E:$Q,MATCH($A43&"|"&$B43,'romain grading'!$S:$S,0),COLUMN()-3),""),IF($C43="nishita",IFERROR(INDEX('nishita grading'!$E:$Q,MATCH($A43&"|"&$B43,'nishita grading'!$S:$S,0),COLUMN()-3),""),""))) -> 0 | F43: =IF($C43="faizan",IFERROR(INDEX('faizan grading'!$E:$Q,MATCH($A43&"|"&$B43,'faizan grading'!$S:$S,0),COLUMN()-3),""),IF($C43="romain",IFERROR(INDEX('romain grading'!$E:$Q,MATCH($A43&"|"&$B43,'romain grading'!$S:$S,0),COLUMN()-3),""),IF($C43="nishita",IFERROR(INDEX('nishita grading'!$E:$Q,MATCH($A43&"|"&$B43,'nishita grading'!$S:$S,0),COLUMN()-3),""),""))) -> 0 | G43: =IF($C43="faizan",IFERROR(INDEX('faizan grading'!$E:$Q,MATCH($A43&"|"&$B43,'faizan grading'!$S:$S,0),COLUMN()-3),""),IF($C43="romain",IFERROR(INDEX('romain grading'!$E:$Q,MATCH($A43&"|"&$B43,'romain grading'!$S:$S,0),COLUMN()-3),""),IF($C43="nishita",IFERROR(INDEX('nishita grading'!$E:$Q,MATCH($A43&"|"&$B43,'nishita grading'!$S:$S,0),COLUMN()-3),""),""))) -> 0 | H43: =IF($C43="faizan",IFERROR(INDEX('faizan grading'!$E:$Q,MATCH($A43&"|"&$B43,'faizan grading'!$S:$S,0),COLUMN()-3),""),IF($C43="romain",IFERROR(INDEX('romain grading'!$E:$Q,MATCH($A43&"|"&$B43,'romain grading'!$S:$S,0),COLUMN()-3),""),IF($C43="nishita",IFERROR(INDEX('nishita grading'!$E:$Q,MATCH($A43&"|"&$B43,'nishita grading'!$S:$S,0),COLUMN()-3),""),""))) -> 0 | I43: =IF($C43="faizan",IFERROR(INDEX('faizan grading'!$E:$Q,MATCH($A43&"|"&$B43,'faizan grading'!$S:$S,0),COLUMN()-3),""),IF($C43="romain",IFERROR(INDEX('romain grading'!$E:$Q,MATCH($A43&"|"&$B43,'romain grading'!$S:$S,0),COLUMN()-3),""),IF($C43="nishita",IFERROR(INDEX('nishita grading'!$E:$Q,MATCH($A43&"|"&$B43,'nishita grading'!$S:$S,0),COLUMN()-3),""),""))) -> 0 | J43: =IF($C43="faizan",IFERROR(INDEX('faizan grading'!$E:$Q,MATCH($A43&"|"&$B43,'faizan grading'!$S:$S,0),COLUMN()-3),""),IF($C43="romain",IFERROR(INDEX('romain grading'!$E:$Q,MATCH($A43&"|"&$B43,'romain grading'!$S:$S,0),COLUMN()-3),""),IF($C43="nishita",IFERROR(INDEX('nishita grading'!$E:$Q,MATCH($A43&"|"&$B43,'nishita grading'!$S:$S,0),COLUMN()-3),""),""))) -> 0 | K43: =IF($C43="faizan",IFERROR(INDEX('faizan grading'!$E:$Q,MATCH($A43&"|"&$B43,'faizan grading'!$S:$S,0),COLUMN()-3),""),IF($C43="romain",IFERROR(INDEX('romain grading'!$E:$Q,MATCH($A43&"|"&$B43,'romain grading'!$S:$S,0),COLUMN()-3),""),IF($C43="nishita",IFERROR(INDEX('nishita grading'!$E:$Q,MATCH($A43&"|"&$B43,'nishita grading'!$S:$S,0),COLUMN()-3),""),""))) -> 0 | ... P43: =IF($C43="faizan",IFERROR(INDEX('faizan grading'!$E:$Q,MATCH($A43&"|"&$B43,'faizan grading'!$S:$S,0),COLUMN()-3),""),IF($C43="romain",IFERROR(INDEX('romain grading'!$E:$Q,MATCH($A43&"|"&$B43,'romain grading'!$S:$S,0),COLUMN()-3),""),IF($C43="nishita",IFERROR(INDEX('nishita grading'!$E:$Q,MATCH($A43&"|"&$B43,'nishita grading'!$S:$S,0),COLUMN()-3),""),""))) -> 0 | Q43: =40-SUM(D43:P43) -> 40 | R43: =A43&"|"&B43 -> chaotic|0243
A44: chaotic | B44: 0243 | C44: nishita | D44: =IF($C44="faizan",IFERROR(INDEX('faizan grading'!$E:$Q,MATCH($A44&"|"&$B44,'faizan grading'!$S:$S,0),COLUMN()-3),""),IF($C44="romain",IFERROR(INDEX('romain grading'!$E:$Q,MATCH($A44&"|"&$B44,'romain grading'!$S:$S,0),COLUMN()-3),""),IF($C44="nishita",IFERROR(INDEX('nishita grading'!$E:$Q,MATCH($A44&"|"&$B44,'nishita grading'!$S:$S,0),COLUMN()-3),""),""))) -> 0 | E44: =IF($C44="faizan",IFERROR(INDEX('faizan grading'!$E:$Q,MATCH($A44&"|"&$B44,'faizan grading'!$S:$S,0),COLUMN()-3),""),IF($C44="romain",IFERROR(INDEX('romain grading'!$E:$Q,MATCH($A44&"|"&$B44,'romain grading'!$S:$S,0),COLUMN()-3),""),IF($C44="nishita",IFERROR(INDEX('nishita grading'!$E:$Q,MATCH($A44&"|"&$B44,'nishita grading'!$S:$S,0),COLUMN()-3),""),""))) -> 0 | F44: =IF($C44="faizan",IFERROR(INDEX('faizan grading'!$E:$Q,MATCH($A44&"|"&$B44,'faizan grading'!$S:$S,0),COLUMN()-3),""),IF($C44="romain",IFERROR(INDEX('romain grading'!$E:$Q,MATCH($A44&"|"&$B44,'romain grading'!$S:$S,0),COLUMN()-3),""),IF($C44="nishita",IFERROR(INDEX('nishita grading'!$E:$Q,MATCH($A44&"|"&$B44,'nishita grading'!$S:$S,0),COLUMN()-3),""),""))) -> 0 | G44: =IF($C44="faizan",IFERROR(INDEX('faizan grading'!$E:$Q,MATCH($A44&"|"&$B44,'faizan grading'!$S:$S,0),COLUMN()-3),""),IF($C44="romain",IFERROR(INDEX('romain grading'!$E:$Q,MATCH($A44&"|"&$B44,'romain grading'!$S:$S,0),COLUMN()-3),""),IF($C44="nishita",IFERROR(INDEX('nishita grading'!$E:$Q,MATCH($A44&"|"&$B44,'nishita grading'!$S:$S,0),COLUMN()-3),""),""))) -> 0 | H44: =IF($C44="faizan",IFERROR(INDEX('faizan grading'!$E:$Q,MATCH($A44&"|"&$B44,'faizan grading'!$S:$S,0),COLUMN()-3),""),IF($C44="romain",IFERROR(INDEX('romain grading'!$E:$Q,MATCH($A44&"|"&$B44,'romain grading'!$S:$S,0),COLUMN()-3),""),IF($C44="nishita",IFERROR(INDEX('nishita grading'!$E:$Q,MATCH($A44&"|"&$B44,'nishita grading'!$S:$S,0),COLUMN()-3),""),""))) -> 0 | I44: =IF($C44="faizan",IFERROR(INDEX('faizan grading'!$E:$Q,MATCH($A44&"|"&$B44,'faizan grading'!$S:$S,0),COLUMN()-3),""),IF($C44="romain",IFERROR(INDEX('romain grading'!$E:$Q,MATCH($A44&"|"&$B44,'romain grading'!$S:$S,0),COLUMN()-3),""),IF($C44="nishita",IFERROR(INDEX('nishita grading'!$E:$Q,MATCH($A44&"|"&$B44,'nishita grading'!$S:$S,0),COLUMN()-3),""),""))) -> 0 | J44: =IF($C44="faizan",IFERROR(INDEX('faizan grading'!$E:$Q,MATCH($A44&"|"&$B44,'faizan grading'!$S:$S,0),COLUMN()-3),""),IF($C44="romain",IFERROR(INDEX('romain grading'!$E:$Q,MATCH($A44&"|"&$B44,'romain grading'!$S:$S,0),COLUMN()-3),""),IF($C44="nishita",IFERROR(INDEX('nishita grading'!$E:$Q,MATCH($A44&"|"&$B44,'nishita grading'!$S:$S,0),COLUMN()-3),""),""))) -> 0 | K44: =IF($C44="faizan",IFERROR(INDEX('faizan grading'!$E:$Q,MATCH($A44&"|"&$B44,'faizan grading'!$S:$S,0),COLUMN()-3),""),IF($C44="romain",IFERROR(INDEX('romain grading'!$E:$Q,MATCH($A44&"|"&$B44,'romain grading'!$S:$S,0),COLUMN()-3),""),IF($C44="nishita",IFERROR(INDEX('nishita grading'!$E:$Q,MATCH($A44&"|"&$B44,'nishita grading'!$S:$S,0),COLUMN()-3),""),""))) -> 4 | ... P44: =IF($C44="faizan",IFERROR(INDEX('faizan grading'!$E:$Q,MATCH($A44&"|"&$B44,'faizan grading'!$S:$S,0),COLUMN()-3),""),IF($C44="romain",IFERROR(INDEX('romain grading'!$E:$Q,MATCH($A44&"|"&$B44,'romain grading'!$S:$S,0),COLUMN()-3),""),IF($C44="nishita",IFERROR(INDEX('nishita grading'!$E:$Q,MATCH($A44&"|"&$B44,'nishita grading'!$S:$S,0),COLUMN()-3),""),""))) -> 0 | Q44: =40-SUM(D44:P44) -> 34 | R44: =A44&"|"&B44 -> chaotic|0243
A45: chaotic | B45: 0243 | C45: claude | D45: 0 | E45: 0 | F45: 0 | G45: 0 | H45: 0 | I45: 0 | J45: 0 | K45: 0 | L45: 0 | M45: 0 | N45: 0 | O45: 0 | P45: 0 | Q45: =40-SUM(D45:P45) -> 40 | R45: =A45&"|"&B45 -> chaotic|0243
A46: clueless | B46: 0013 | C46: faizan | D46: =IF($C46="faizan",IFERROR(INDEX('faizan grading'!$E:$Q,MATCH($A46&"|"&$B46,'faizan grading'!$S:$S,0),COLUMN()-3),""),IF($C46="romain",IFERROR(INDEX('romain grading'!$E:$Q,MATCH($A46&"|"&$B46,'romain grading'!$S:$S,0),COLUMN()-3),""),IF($C46="nishita",IFERROR(INDEX('nishita grading'!$E:$Q,MATCH($A46&"|"&$B46,'nishita grading'!$S:$S,0),COLUMN()-3),""),""))) -> 0 | E46: =IF($C46="faizan",IFERROR(INDEX('faizan grading'!$E:$Q,MATCH($A46&"|"&$B46,'faizan grading'!$S:$S,0),COLUMN()-3),""),IF($C46="romain",IFERROR(INDEX('romain grading'!$E:$Q,MATCH($A46&"|"&$B46,'romain grading'!$S:$S,0),COLUMN()-3),""),IF($C46="nishita",IFERROR(INDEX('nishita grading'!$E:$Q,MATCH($A46&"|"&$B46,'nishita grading'!$S:$S,0),COLUMN()-3),""),""))) -> 0 | F46: =IF($C46="faizan",IFERROR(INDEX('faizan grading'!$E:$Q,MATCH($A46&"|"&$B46,'faizan grading'!$S:$S,0),COLUMN()-3),""),IF($C46="romain",IFERROR(INDEX('romain grading'!$E:$Q,MATCH($A46&"|"&$B46,'romain grading'!$S:$S,0),COLUMN()-3),""),IF($C46="nishita",IFERROR(INDEX('nishita grading'!$E:$Q,MATCH($A46&"|"&$B46,'nishita grading'!$S:$S,0),COLUMN()-3),""),""))) -> 0 | G46: =IF($C46="faizan",IFERROR(INDEX('faizan grading'!$E:$Q,MATCH($A46&"|"&$B46,'faizan grading'!$S:$S,0),COLUMN()-3),""),IF($C46="romain",IFERROR(INDEX('romain grading'!$E:$Q,MATCH($A46&"|"&$B46,'romain grading'!$S:$S,0),COLUMN()-3),""),IF($C46="nishita",IFERROR(INDEX('nishita grading'!$E:$Q,MATCH($A46&"|"&$B46,'nishita grading'!$S:$S,0),COLUMN()-3),""),""))) -> 0 | H46: =IF($C46="faizan",IFERROR(INDEX('faizan grading'!$E:$Q,MATCH($A46&"|"&$B46,'faizan grading'!$S:$S,0),COLUMN()-3),""),IF($C46="romain",IFERROR(INDEX('romain grading'!$E:$Q,MATCH($A46&"|"&$B46,'romain grading'!$S:$S,0),COLUMN()-3),""),IF($C46="nishita",IFERROR(INDEX('nishita grading'!$E:$Q,MATCH($A46&"|"&$B46,'nishita grading'!$S:$S,0),COLUMN()-3),""),""))) -> 0 | I46: =IF($C46="faizan",IFERROR(INDEX('faizan grading'!$E:$Q,MATCH($A46&"|"&$B46,'faizan grading'!$S:$S,0),COLUMN()-3),""),IF($C46="romain",IFERROR(INDEX('romain grading'!$E:$Q,MATCH($A46&"|"&$B46,'romain grading'!$S:$S,0),COLUMN()-3),""),IF($C46="nishita",IFERROR(INDEX('nishita grading'!$E:$Q,MATCH($A46&"|"&$B46,'nishita grading'!$S:$S,0),COLUMN()-3),""),""))) -> 0 | J46: =IF($C46="faizan",IFERROR(INDEX('faizan grading'!$E:$Q,MATCH($A46&"|"&$B46,'faizan grading'!$S:$S,0),COLUMN()-3),""),IF($C46="romain",IFERROR(INDEX('romain grading'!$E:$Q,MATCH($A46&"|"&$B46,'romain grading'!$S:$S,0),COLUMN()-3),""),IF($C46="nishita",IFERROR(INDEX('nishita grading'!$E:$Q,MATCH($A46&"|"&$B46,'nishita grading'!$S:$S,0),COLUMN()-3),""),""))) -> 0 | K46: =IF($C46="faizan",IFERROR(INDEX('faizan grading'!$E:$Q,MATCH($A46&"|"&$B46,'faizan grading'!$S:$S,0),COLUMN()-3),""),IF($C46="romain",IFERROR(INDEX('romain grading'!$E:$Q,MATCH($A46&"|"&$B46,'romain grading'!$S:$S,0),COLUMN()-3),""),IF($C46="nishita",IFERROR(INDEX('nishita grading'!$E:$Q,MATCH($A46&"|"&$B46,'nishita grading'!$S:$S,0),COLUMN()-3),""),""))) -> 0 | ... P46: =IF($C46="faizan",IFERROR(INDEX('faizan grading'!$E:$Q,MATCH($A46&"|"&$B46,'faizan grading'!$S:$S,0),COLUMN()-3),""),IF($C46="romain",IFERROR(INDEX('romain grading'!$E:$Q,MATCH($A46&"|"&$B46,'romain grading'!$S:$S,0),COLUMN()-3),""),IF($C46="nishita",IFERROR(INDEX('nishita grading'!$E:$Q,MATCH($A46&"|"&$B46,'nishita grading'!$S:$S,0),COLUMN()-3),""),""))) -> 0 | Q46: =40-SUM(D46:P46) -> 40 | R46: =A46&"|"&B46 -> clueless|0013
A47: clueless | B47: 0013 | C47: romain | D47: =IF($C47="faizan",IFERROR(INDEX('faizan grading'!$E:$Q,MATCH($A47&"|"&$B47,'faizan grading'!$S:$S,0),COLUMN()-3),""),IF($C47="romain",IFERROR(INDEX('romain grading'!$E:$Q,MATCH($A47&"|"&$B47,'romain grading'!$S:$S,0),COLUMN()-3),""),IF($C47="nishita",IFERROR(INDEX('nishita grading'!$E:$Q,MATCH($A47&"|"&$B47,'nishita grading'!$S:$S,0),COLUMN()-3),""),""))) -> 0 | E47: =IF($C47="faizan",IFERROR(INDEX('faizan grading'!$E:$Q,MATCH($A47&"|"&$B47,'faizan grading'!$S:$S,0),COLUMN()-3),""),IF($C47="romain",IFERROR(INDEX('romain grading'!$E:$Q,MATCH($A47&"|"&$B47,'romain grading'!$S:$S,0),COLUMN()-3),""),IF($C47="nishita",IFERROR(INDEX('nishita grading'!$E:$Q,MATCH($A47&"|"&$B47,'nishita grading'!$S:$S,0),COLUMN()-3),""),""))) -> 0 | F47: =IF($C47="faizan",IFERROR(INDEX('faizan grading'!$E:$Q,MATCH($A47&"|"&$B47,'faizan grading'!$S:$S,0),COLUMN()-3),""),IF($C47="romain",IFERROR(INDEX('romain grading'!$E:$Q,MATCH($A47&"|"&$B47,'romain grading'!$S:$S,0),COLUMN()-3),""),IF($C47="nishita",IFERROR(INDEX('nishita grading'!$E:$Q,MATCH($A47&"|"&$B47,'nishita grading'!$S:$S,0),COLUMN()-3),""),""))) -> 0 | G47: =IF($C47="faizan",IFERROR(INDEX('faizan grading'!$E:$Q,MATCH($A47&"|"&$B47,'faizan grading'!$S:$S,0),COLUMN()-3),""),IF($C47="romain",IFERROR(INDEX('romain grading'!$E:$Q,MATCH($A47&"|"&$B47,'romain grading'!$S:$S,0),COLUMN()-3),""),IF($C47="nishita",IFERROR(INDEX('nishita grading'!$E:$Q,MATCH($A47&"|"&$B47,'nishita grading'!$S:$S,0),COLUMN()-3),""),""))) -> 0 | H47: =IF($C47="faizan",IFERROR(INDEX('faizan grading'!$E:$Q,MATCH($A47&"|"&$B47,'faizan grading'!$S:$S,0),COLUMN()-3),""),IF($C47="romain",IFERROR(INDEX('romain grading'!$E:$Q,MATCH($A47&"|"&$B47,'romain grading'!$S:$S,0),COLUMN()-3),""),IF($C47="nishita",IFERROR(INDEX('nishita grading'!$E:$Q,MATCH($A47&"|"&$B47,'nishita grading'!$S:$S,0),COLUMN()-3),""),""))) -> 6 | I47: =IF($C47="faizan",IFERROR(INDEX('faizan grading'!$E:$Q,MATCH($A47&"|"&$B47,'faizan grading'!$S:$S,0),COLUMN()-3),""),IF($C47="romain",IFERROR(INDEX('romain grading'!$E:$Q,MATCH($A47&"|"&$B47,'romain grading'!$S:$S,0),COLUMN()-3),""),IF($C47="nishita",IFERROR(INDEX('nishita grading'!$E:$Q,MATCH($A47&"|"&$B47,'nishita grading'!$S:$S,0),COLUMN()-3),""),""))) -> 0 | J47: =IF($C47="faizan",IFERROR(INDEX('faizan grading'!$E:$Q,MATCH($A47&"|"&$B47,'faizan grading'!$S:$S,0),COLUMN()-3),""),IF($C47="romain",IFERROR(INDEX('romain grading'!$E:$Q,MATCH($A47&"|"&$B47,'romain grading'!$S:$S,0),COLUMN()-3),""),IF($C47="nishita",IFERROR(INDEX('nishita grading'!$E:$Q,MATCH($A47&"|"&$B47,'nishita grading'!$S:$S,0),COLUMN()-3),""),""))) -> 0 | K47: =IF($C47="faizan",IFERROR(INDEX('faizan grading'!$E:$Q,MATCH($A47&"|"&$B47,'faizan grading'!$S:$S,0),COLUMN()-3),""),IF($C47="romain",IFERROR(INDEX('romain grading'!$E:$Q,MATCH($A47&"|"&$B47,'romain grading'!$S:$S,0),COLUMN()-3),""),IF($C47="nishita",IFERROR(INDEX('nishita grading'!$E:$Q,MATCH($A47&"|"&$B47,'nishita grading'!$S:$S,0),COLUMN()-3),""),""))) -> 0 | ... P47: =IF($C47="faizan",IFERROR(INDEX('faizan grading'!$E:$Q,MATCH($A47&"|"&$B47,'faizan grading'!$S:$S,0),COLUMN()-3),""),IF($C47="romain",IFERROR(INDEX('romain grading'!$E:$Q,MATCH($A47&"|"&$B47,'romain grading'!$S:$S,0),COLUMN()-3),""),IF($C47="nishita",IFERROR(INDEX('nishita grading'!$E:$Q,MATCH($A47&"|"&$B47,'nishita grading'!$S:$S,0),COLUMN()-3),""),""))) -> 0 | Q47: =40-SUM(D47:P47) -> 34 | R47: =A47&"|"&B47 -> clueless|0013
A48: clueless | B48: 0013 | C48: nishita | D48: =IF($C48="faizan",IFERROR(INDEX('faizan grading'!$E:$Q,MATCH($A48&"|"&$B48,'faizan grading'!$S:$S,0),COLUMN()-3),""),IF($C48="romain",IFERROR(INDEX('romain grading'!$E:$Q,MATCH($A48&"|"&$B48,'romain grading'!$S:$S,0),COLUMN()-3),""),IF($C48="nishita",IFERROR(INDEX('nishita grading'!$E:$Q,MATCH($A48&"|"&$B48,'nishita grading'!$S:$S,0),COLUMN()-3),""),""))) -> 0 | E48: =IF($C48="faizan",IFERROR(INDEX('faizan grading'!$E:$Q,MATCH($A48&"|"&$B48,'faizan grading'!$S:$S,0),COLUMN()-3),""),IF($C48="romain",IFERROR(INDEX('romain grading'!$E:$Q,MATCH($A48&"|"&$B48,'romain grading'!$S:$S,0),COLUMN()-3),""),IF($C48="nishita",IFERROR(INDEX('nishita grading'!$E:$Q,MATCH($A48&"|"&$B48,'nishita grading'!$S:$S,0),COLUMN()-3),""),""))) -> 0 | F48: =IF($C48="faizan",IFERROR(INDEX('faizan grading'!$E:$Q,MATCH($A48&"|"&$B48,'faizan grading'!$S:$S,0),COLUMN()-3),""),IF($C48="romain",IFERROR(INDEX('romain grading'!$E:$Q,MATCH($A48&"|"&$B48,'romain grading'!$S:$S,0),COLUMN()-3),""),IF($C48="nishita",IFERROR(INDEX('nishita grading'!$E:$Q,MATCH($A48&"|"&$B48,'nishita grading'!$S:$S,0),COLUMN()-3),""),""))) -> 0 | G48: =IF($C48="faizan",IFERROR(INDEX('faizan grading'!$E:$Q,MATCH($A48&"|"&$B48,'faizan grading'!$S:$S,0),COLUMN()-3),""),IF($C48="romain",IFERROR(INDEX('romain grading'!$E:$Q,MATCH($A48&"|"&$B48,'romain grading'!$S:$S,0),COLUMN()-3),""),IF($C48="nishita",IFERROR(INDEX('nishita grading'!$E:$Q,MATCH($A48&"|"&$B48,'nishita grading'!$S:$S,0),COLUMN()-3),""),""))) -> 0 | H48: =IF($C48="faizan",IFERROR(INDEX('faizan grading'!$E:$Q,MATCH($A48&"|"&$B48,'faizan grading'!$S:$S,0),COLUMN()-3),""),IF($C48="romain",IFERROR(INDEX('romain grading'!$E:$Q,MATCH($A48&"|"&$B48,'romain grading'!$S:$S,0),COLUMN()-3),""),IF($C48="nishita",IFERROR(INDEX('nishita grading'!$E:$Q,MATCH($A48&"|"&$B48,'nishita grading'!$S:$S,0),COLUMN()-3),""),""))) -> 0 | I48: =IF($C48="faizan",IFERROR(INDEX('faizan grading'!$E:$Q,MATCH($A48&"|"&$B48,'faizan grading'!$S:$S,0),COLUMN()-3),""),IF($C48="romain",IFERROR(INDEX('romain grading'!$E:$Q,MATCH($A48&"|"&$B48,'romain grading'!$S:$S,0),COLUMN()-3),""),IF($C48="nishita",IFERROR(INDEX('nishita grading'!$E:$Q,MATCH($A48&"|"&$B48,'nishita grading'!$S:$S,0),COLUMN()-3),""),""))) -> 0 | J48: =IF($C48="faizan",IFERROR(INDEX('faizan grading'!$E:$Q,MATCH($A48&"|"&$B48,'faizan grading'!$S:$S,0),COLUMN()-3),""),IF($C48="romain",IFERROR(INDEX('romain grading'!$E:$Q,MATCH($A48&"|"&$B48,'romain grading'!$S:$S,0),COLUMN()-3),""),IF($C48="nishita",IFERROR(INDEX('nishita grading'!$E:$Q,MATCH($A48&"|"&$B48,'nishita grading'!$S:$S,0),COLUMN()-3),""),""))) -> 0 | K48: =IF($C48="faizan",IFERROR(INDEX('faizan grading'!$E:$Q,MATCH($A48&"|"&$B48,'faizan grading'!$S:$S,0),COLUMN()-3),""),IF($C48="romain",IFERROR(INDEX('romain grading'!$E:$Q,MATCH($A48&"|"&$B48,'romain grading'!$S:$S,0),COLUMN()-3),""),IF($C48="nishita",IFERROR(INDEX('nishita grading'!$E:$Q,MATCH($A48&"|"&$B48,'nishita grading'!$S:$S,0),COLUMN()-3),""),""))) -> 4 | ... P48: =IF($C48="faizan",IFERROR(INDEX('faizan grading'!$E:$Q,MATCH($A48&"|"&$B48,'faizan grading'!$S:$S,0),COLUMN()-3),""),IF($C48="romain",IFERROR(INDEX('romain grading'!$E:$Q,MATCH($A48&"|"&$B48,'romain grading'!$S:$S,0),COLUMN()-3),""),IF($C48="nishita",IFERROR(INDEX('nishita grading'!$E:$Q,MATCH($A48&"|"&$B48,'nishita grading'!$S:$S,0),COLUMN()-3),""),""))) -> 0 | Q48: =40-SUM(D48:P48) -> 34 | R48: =A48&"|"&B48 -> clueless|0013
A49: clueless | B49: 0013 | C49: claude | D49: 0 | E49: 0 | F49: 0 | G49: 0 | H49: 3 | I49: 0 | J49: 0 | K49: 4 | L49: 0 | M49: 0 | N49: 4 | O49: 0 | P49: 0 | Q49: =40-SUM(D49:P49) -> 29 | R49: =A49&"|"&B49 -> clueless|0013
A50: clueless | B50: 0025 | C50: faizan | D50: =IF($C50="faizan",IFERROR(INDEX('faizan grading'!$E:$Q,MATCH($A50&"|"&$B50,'faizan grading'!$S:$S,0),COLUMN()-3),""),IF($C50="romain",IFERROR(INDEX('romain grading'!$E:$Q,MATCH($A50&"|"&$B50,'romain grading'!$S:$S,0),COLUMN()-3),""),IF($C50="nishita",IFERROR(INDEX('nishita grading'!$E:$Q,MATCH($A50&"|"&$B50,'nishita grading'!$S:$S,0),COLUMN()-3),""),""))) -> 0 | E50: =IF($C50="faizan",IFERROR(INDEX('faizan grading'!$E:$Q,MATCH($A50&"|"&$B50,'faizan grading'!$S:$S,0),COLUMN()-3),""),IF($C50="romain",IFERROR(INDEX('romain grading'!$E:$Q,MATCH($A50&"|"&$B50,'romain grading'!$S:$S,0),COLUMN()-3),""),IF($C50="nishita",IFERROR(INDEX('nishita grading'!$E:$Q,MATCH($A50&"|"&$B50,'nishita grading'!$S:$S,0),COLUMN()-3),""),""))) -> 0 | F50: =IF($C50="faizan",IFERROR(INDEX('faizan grading'!$E:$Q,MATCH($A50&"|"&$B50,'faizan grading'!$S:$S,0),COLUMN()-3),""),IF($C50="romain",IFERROR(INDEX('romain grading'!$E:$Q,MATCH($A50&"|"&$B50,'romain grading'!$S:$S,0),COLUMN()-3),""),IF($C50="nishita",IFERROR(INDEX('nishita grading'!$E:$Q,MATCH($A50&"|"&$B50,'nishita grading'!$S:$S,0),COLUMN()-3),""),""))) -> 0 | G50: =IF($C50="faizan",IFERROR(INDEX('faizan grading'!$E:$Q,MATCH($A50&"|"&$B50,'faizan grading'!$S:$S,0),COLUMN()-3),""),IF($C50="romain",IFERROR(INDEX('romain grading'!$E:$Q,MATCH($A50&"|"&$B50,'romain grading'!$S:$S,0),COLUMN()-3),""),IF($C50="nishita",IFERROR(INDEX('nishita grading'!$E:$Q,MATCH($A50&"|"&$B50,'nishita grading'!$S:$S,0),COLUMN()-3),""),""))) -> 0 | H50: =IF($C50="faizan",IFERROR(INDEX('faizan grading'!$E:$Q,MATCH($A50&"|"&$B50,'faizan grading'!$S:$S,0),COLUMN()-3),""),IF($C50="romain",IFERROR(INDEX('romain grading'!$E:$Q,MATCH($A50&"|"&$B50,'romain grading'!$S:$S,0),COLUMN()-3),""),IF($C50="nishita",IFERROR(INDEX('nishita grading'!$E:$Q,MATCH($A50&"|"&$B50,'nishita grading'!$S:$S,0),COLUMN()-3),""),""))) -> 0 | I50: =IF($C50="faizan",IFERROR(INDEX('faizan grading'!$E:$Q,MATCH($A50&"|"&$B50,'faizan grading'!$S:$S,0),COLUMN()-3),""),IF($C50="romain",IFERROR(INDEX('romain grading'!$E:$Q,MATCH($A50&"|"&$B50,'romain grading'!$S:$S,0),COLUMN()-3),""),IF($C50="nishita",IFERROR(INDEX('nishita grading'!$E:$Q,MATCH($A50&"|"&$B50,'nishita grading'!$S:$S,0),COLUMN()-3),""),""))) -> 0 | J50: =IF($C50="faizan",IFERROR(INDEX('faizan grading'!$E:$Q,MATCH($A50&"|"&$B50,'faizan grading'!$S:$S,0),COLUMN()-3),""),IF($C50="romain",IFERROR(INDEX('romain grading'!$E:$Q,MATCH($A50&"|"&$B50,'romain grading'!$S:$S,0),COLUMN()-3),""),IF($C50="nishita",IFERROR(INDEX('nishita grading'!$E:$Q,MATCH($A50&"|"&$B50,'nishita grading'!$S:$S,0),COLUMN()-3),""),""))) -> 0 | K50: =IF($C50="faizan",IFERROR(INDEX('faizan grading'!$E:$Q,MATCH($A50&"|"&$B50,'faizan grading'!$S:$S,0),COLUMN()-3),""),IF($C50="romain",IFERROR(INDEX('romain grading'!$E:$Q,MATCH($A50&"|"&$B50,'romain grading'!$S:$S,0),COLUMN()-3),""),IF($C50="nishita",IFERROR(INDEX('nishita grading'!$E:$Q,MATCH($A50&"|"&$B50,'nishita grading'!$S:$S,0),COLUMN()-3),""),""))) -> 0 | ... P50: =IF($C50="faizan",IFERROR(INDEX('faizan grading'!$E:$Q,MATCH($A50&"|"&$B50,'faizan grading'!$S:$S,0),COLUMN()-3),""),IF($C50="romain",IFERROR(INDEX('romain grading'!$E:$Q,MATCH($A50&"|"&$B50,'romain grading'!$S:$S,0),COLUMN()-3),""),IF($C50="nishita",IFERROR(INDEX('nishita grading'!$E:$Q,MATCH($A50&"|"&$B50,'nishita grading'!$S:$S,0),COLUMN()-3),""),""))) -> 0 | Q50: =40-SUM(D50:P50) -> 40 | R50: =A50&"|"&B50 -> clueless|0025
A51: clueless | B51: 0025 | C51: romain | D51: =IF($C51="faizan",IFERROR(INDEX('faizan grading'!$E:$Q,MATCH($A51&"|"&$B51,'faizan grading'!$S:$S,0),COLUMN()-3),""),IF($C51="romain",IFERROR(INDEX('romain grading'!$E:$Q,MATCH($A51&"|"&$B51,'romain grading'!$S:$S,0),COLUMN()-3),""),IF($C51="nishita",IFERROR(INDEX('nishita grading'!$E:$Q,MATCH($A51&"|"&$B51,'nishita grading'!$S:$S,0),COLUMN()-3),""),""))) -> 0 | E51: =IF($C51="faizan",IFERROR(INDEX('faizan grading'!$E:$Q,MATCH($A51&"|"&$B51,'faizan grading'!$S:$S,0),COLUMN()-3),""),IF($C51="romain",IFERROR(INDEX('romain grading'!$E:$Q,MATCH($A51&"|"&$B51,'romain grading'!$S:$S,0),COLUMN()-3),""),IF($C51="nishita",IFERROR(INDEX('nishita grading'!$E:$Q,MATCH($A51&"|"&$B51,'nishita grading'!$S:$S,0),COLUMN()-3),""),""))) -> 0 | F51: =IF($C51="faizan",IFERROR(INDEX('faizan grading'!$E:$Q,MATCH($A51&"|"&$B51,'faizan grading'!$S:$S,0),COLUMN()-3),""),IF($C51="romain",IFERROR(INDEX('romain grading'!$E:$Q,MATCH($A51&"|"&$B51,'romain grading'!$S:$S,0),COLUMN()-3),""),IF($C51="nishita",IFERROR(INDEX('nishita grading'!$E:$Q,MATCH($A51&"|"&$B51,'nishita grading'!$S:$S,0),COLUMN()-3),""),""))) -> 0 | G51: =IF($C51="faizan",IFERROR(INDEX('faizan grading'!$E:$Q,MATCH($A51&"|"&$B51,'faizan grading'!$S:$S,0),COLUMN()-3),""),IF($C51="romain",IFERROR(INDEX('romain grading'!$E:$Q,MATCH($A51&"|"&$B51,'romain grading'!$S:$S,0),COLUMN()-3),""),IF($C51="nishita",IFERROR(INDEX('nishita grading'!$E:$Q,MATCH($A51&"|"&$B51,'nishita grading'!$S:$S,0),COLUMN()-3),""),""))) -> 0 | H51: =IF($C51="faizan",IFERROR(INDEX('faizan grading'!$E:$Q,MATCH($A51&"|"&$B51,'faizan grading'!$S:$S,0),COLUMN()-3),""),IF($C51="romain",IFERROR(INDEX('romain grading'!$E:$Q,MATCH($A51&"|"&$B51,'romain grading'!$S:$S,0),COLUMN()-3),""),IF($C51="nishita",IFERROR(INDEX('nishita grading'!$E:$Q,MATCH($A51&"|"&$B51,'nishita grading'!$S:$S,0),COLUMN()-3),""),""))) -> 0 | I51: =IF($C51="faizan",IFERROR(INDEX('faizan grading'!$E:$Q,MATCH($A51&"|"&$B51,'faizan grading'!$S:$S,0),COLUMN()-3),""),IF($C51="romain",IFERROR(INDEX('romain grading'!$E:$Q,MATCH($A51&"|"&$B51,'romain grading'!$S:$S,0),COLUMN()-3),""),IF($C51="nishita",IFERROR(INDEX('nishita grading'!$E:$Q,MATCH($A51&"|"&$B51,'nishita grading'!$S:$S,0),COLUMN()-3),""),""))) -> 0 | J51: =IF($C51="faizan",IFERROR(INDEX('faizan grading'!$E:$Q,MATCH($A51&"|"&$B51,'faizan grading'!$S:$S,0),COLUMN()-3),""),IF($C51="romain",IFERROR(INDEX('romain grading'!$E:$Q,MATCH($A51&"|"&$B51,'romain grading'!$S:$S,0),COLUMN()-3),""),IF($C51="nishita",IFERROR(INDEX('nishita grading'!$E:$Q,MATCH($A51&"|"&$B51,'nishita grading'!$S:$S,0),COLUMN()-3),""),""))) -> 0 | K51: =IF($C51="faizan",IFERROR(INDEX('faizan grading'!$E:$Q,MATCH($A51&"|"&$B51,'faizan grading'!$S:$S,0),COLUMN()-3),""),IF($C51="romain",IFERROR(INDEX('romain grading'!$E:$Q,MATCH($A51&"|"&$B51,'romain grading'!$S:$S,0),COLUMN()-3),""),IF($C51="nishita",IFERROR(INDEX('nishita grading'!$E:$Q,MATCH($A51&"|"&$B51,'nishita grading'!$S:$S,0),COLUMN()-3),""),""))) -> 0 | ... P51: =IF($C51="faizan",IFERROR(INDEX('faizan grading'!$E:$Q,MATCH($A51&"|"&$B51,'faizan grading'!$S:$S,0),COLUMN()-3),""),IF($C51="romain",IFERROR(INDEX('romain grading'!$E:$Q,MATCH($A51&"|"&$B51,'romain grading'!$S:$S,0),COLUMN()-3),""),IF($C51="nishita",IFERROR(INDEX('nishita grading'!$E:$Q,MATCH($A51&"|"&$B51,'nishita grading'!$S:$S,0),COLUMN()-3),""),""))) -> 0 | Q51: =40-SUM(D51:P51) -> 36 | R51: =A51&"|"&B51 -> clueless|0025
A52: clueless | B52: 0025 | C52: nishita | D52: =IF($C52="faizan",IFERROR(INDEX('faizan grading'!$E:$Q,MATCH($A52&"|"&$B52,'faizan grading'!$S:$S,0),COLUMN()-3),""),IF($C52="romain",IFERROR(INDEX('romain grading'!$E:$Q,MATCH($A52&"|"&$B52,'romain grading'!$S:$S,0),COLUMN()-3),""),IF($C52="nishita",IFERROR(INDEX('nishita grading'!$E:$Q,MATCH($A52&"|"&$B52,'nishita grading'!$S:$S,0),COLUMN()-3),""),""))) -> 0 | E52: =IF($C52="faizan",IFERROR(INDEX('faizan grading'!$E:$Q,MATCH($A52&"|"&$B52,'faizan grading'!$S:$S,0),COLUMN()-3),""),IF($C52="romain",IFERROR(INDEX('romain grading'!$E:$Q,MATCH($A52&"|"&$B52,'romain grading'!$S:$S,0),COLUMN()-3),""),IF($C52="nishita",IFERROR(INDEX('nishita grading'!$E:$Q,MATCH($A52&"|"&$B52,'nishita grading'!$S:$S,0),COLUMN()-3),""),""))) -> 0 | F52: =IF($C52="faizan",IFERROR(INDEX('faizan grading'!$E:$Q,MATCH($A52&"|"&$B52,'faizan grading'!$S:$S,0),COLUMN()-3),""),IF($C52="romain",IFERROR(INDEX('romain grading'!$E:$Q,MATCH($A52&"|"&$B52,'romain grading'!$S:$S,0),COLUMN()-3),""),IF($C52="nishita",IFERROR(INDEX('nishita grading'!$E:$Q,MATCH($A52&"|"&$B52,'nishita grading'!$S:$S,0),COLUMN()-3),""),""))) -> 6 | G52: =IF($C52="faizan",IFERROR(INDEX('faizan grading'!$E:$Q,MATCH($A52&"|"&$B52,'faizan grading'!$S:$S,0),COLUMN()-3),""),IF($C52="romain",IFERROR(INDEX('romain grading'!$E:$Q,MATCH($A52&"|"&$B52,'romain grading'!$S:$S,0),COLUMN()-3),""),IF($C52="nishita",IFERROR(INDEX('nishita grading'!$E:$Q,MATCH($A52&"|"&$B52,'nishita grading'!$S:$S,0),COLUMN()-3),""),""))) -> 0 | H52: =IF($C52="faizan",IFERROR(INDEX('faizan grading'!$E:$Q,MATCH($A52&"|"&$B52,'faizan grading'!$S:$S,0),COLUMN()-3),""),IF($C52="romain",IFERROR(INDEX('romain grading'!$E:$Q,MATCH($A52&"|"&$B52,'romain grading'!$S:$S,0),COLUMN()-3),""),IF($C52="nishita",IFERROR(INDEX('nishita grading'!$E:$Q,MATCH($A52&"|"&$B52,'nishita grading'!$S:$S,0),COLUMN()-3),""),""))) -> 0 | I52: =IF($C52="faizan",IFERROR(INDEX('faizan grading'!$E:$Q,MATCH($A52&"|"&$B52,'faizan grading'!$S:$S,0),COLUMN()-3),""),IF($C52="romain",IFERROR(INDEX('romain grading'!$E:$Q,MATCH($A52&"|"&$B52,'romain grading'!$S:$S,0),COLUMN()-3),""),IF($C52="nishita",IFERROR(INDEX('nishita grading'!$E:$Q,MATCH($A52&"|"&$B52,'nishita grading'!$S:$S,0),COLUMN()-3),""),""))) -> 0 | J52: =IF($C52="faizan",IFERROR(INDEX('faizan grading'!$E:$Q,MATCH($A52&"|"&$B52,'faizan grading'!$S:$S,0),COLUMN()-3),""),IF($C52="romain",IFERROR(INDEX('romain grading'!$E:$Q,MATCH($A52&"|"&$B52,'romain grading'!$S:$S,0),COLUMN()-3),""),IF($C52="nishita",IFERROR(INDEX('nishita grading'!$E:$Q,MATCH($A52&"|"&$B52,'nishita grading'!$S:$S,0),COLUMN()-3),""),""))) -> 0 | K52: =IF($C52="faizan",IFERROR(INDEX('faizan grading'!$E:$Q,MATCH($A52&"|"&$B52,'faizan grading'!$S:$S,0),COLUMN()-3),""),IF($C52="romain",IFERROR(INDEX('romain grading'!$E:$Q,MATCH($A52&"|"&$B52,'romain grading'!$S:$S,0),COLUMN()-3),""),IF($C52="nishita",IFERROR(INDEX('nishita grading'!$E:$Q,MATCH($A52&"|"&$B52,'nishita grading'!$S:$S,0),COLUMN()-3),""),""))) -> 4 | ... P52: =IF($C52="faizan",IFERROR(INDEX('faizan grading'!$E:$Q,MATCH($A52&"|"&$B52,'faizan grading'!$S:$S,0),COLUMN()-3),""),IF($C52="romain",IFERROR(INDEX('romain grading'!$E:$Q,MATCH($A52&"|"&$B52,'romain grading'!$S:$S,0),COLUMN()-3),""),IF($C52="nishita",IFERROR(INDEX('nishita grading'!$E:$Q,MATCH($A52&"|"&$B52,'nishita grading'!$S:$S,0),COLUMN()-3),""),""))) -> 0 | Q52: =40-SUM(D52:P52) -> 30 | R52: =A52&"|"&B52 -> clueless|0025
A53: clueless | B53: 0025 | C53: claude | D53: 0 | E53: 0 | F53: 0 | G53: 0 | H53: 3 | I53: 0 | J53: 0 | K53: 4 | L53: 0 | M53: 0 | N53: 4 | O53: 0 | P53: 0 | Q53: =40-SUM(D53:P53) -> 29 | R53: =A53&"|"&B53 -> clueless|0025
A54: clueless | B54: 0044 | C54: faizan | D54: =IF($C54="faizan",IFERROR(INDEX('faizan grading'!$E:$Q,MATCH($A54&"|"&$B54,'faizan grading'!$S:$S,0),COLUMN()-3),""),IF($C54="romain",IFERROR(INDEX('romain grading'!$E:$Q,MATCH($A54&"|"&$B54,'romain grading'!$S:$S,0),COLUMN()-3),""),IF($C54="nishita",IFERROR(INDEX('nishita grading'!$E:$Q,MATCH($A54&"|"&$B54,'nishita grading'!$S:$S,0),COLUMN()-3),""),""))) -> 0 | E54: =IF($C54="faizan",IFERROR(INDEX('faizan grading'!$E:$Q,MATCH($A54&"|"&$B54,'faizan grading'!$S:$S,0),COLUMN()-3),""),IF($C54="romain",IFERROR(INDEX('romain grading'!$E:$Q,MATCH($A54&"|"&$B54,'romain grading'!$S:$S,0),COLUMN()-3),""),IF($C54="nishita",IFERROR(INDEX('nishita grading'!$E:$Q,MATCH($A54&"|"&$B54,'nishita grading'!$S:$S,0),COLUMN()-3),""),""))) -> 0 | F54: =IF($C54="faizan",IFERROR(INDEX('faizan grading'!$E:$Q,MATCH($A54&"|"&$B54,'faizan grading'!$S:$S,0),COLUMN()-3),""),IF($C54="romain",IFERROR(INDEX('romain grading'!$E:$Q,MATCH($A54&"|"&$B54,'romain grading'!$S:$S,0),COLUMN()-3),""),IF($C54="nishita",IFERROR(INDEX('nishita grading'!$E:$Q,MATCH($A54&"|"&$B54,'nishita grading'!$S:$S,0),COLUMN()-3),""),""))) -> 0 | G54: =IF($C54="faizan",IFERROR(INDEX('faizan grading'!$E:$Q,MATCH($A54&"|"&$B54,'faizan grading'!$S:$S,0),COLUMN()-3),""),IF($C54="romain",IFERROR(INDEX('romain grading'!$E:$Q,MATCH($A54&"|"&$B54,'romain grading'!$S:$S,0),COLUMN()-3),""),IF($C54="nishita",IFERROR(INDEX('nishita grading'!$E:$Q,MATCH($A54&"|"&$B54,'nishita grading'!$S:$S,0),COLUMN()-3),""),""))) -> 0 | H54: =IF($C54="faizan",IFERROR(INDEX('faizan grading'!$E:$Q,MATCH($A54&"|"&$B54,'faizan grading'!$S:$S,0),COLUMN()-3),""),IF($C54="romain",IFERROR(INDEX('romain grading'!$E:$Q,MATCH($A54&"|"&$B54,'romain grading'!$S:$S,0),COLUMN()-3),""),IF($C54="nishita",IFERROR(INDEX('nishita grading'!$E:$Q,MATCH($A54&"|"&$B54,'nishita grading'!$S:$S,0),COLUMN()-3),""),""))) -> 0 | I54: =IF($C54="faizan",IFERROR(INDEX('faizan grading'!$E:$Q,MATCH($A54&"|"&$B54,'faizan grading'!$S:$S,0),COLUMN()-3),""),IF($C54="romain",IFERROR(INDEX('romain grading'!$E:$Q,MATCH($A54&"|"&$B54,'romain grading'!$S:$S,0),COLUMN()-3),""),IF($C54="nishita",IFERROR(INDEX('nishita grading'!$E:$Q,MATCH($A54&"|"&$B54,'nishita grading'!$S:$S,0),COLUMN()-3),""),""))) -> 0 | J54: =IF($C54="faizan",IFERROR(INDEX('faizan grading'!$E:$Q,MATCH($A54&"|"&$B54,'faizan grading'!$S:$S,0),COLUMN()-3),""),IF($C54="romain",IFERROR(INDEX('romain grading'!$E:$Q,MATCH($A54&"|"&$B54,'romain grading'!$S:$S,0),COLUMN()-3),""),IF($C54="nishita",IFERROR(INDEX('nishita grading'!$E:$Q,MATCH($A54&"|"&$B54,'nishita grading'!$S:$S,0),COLUMN()-3),""),""))) -> 0 | K54: =IF($C54="faizan",IFERROR(INDEX('faizan grading'!$E:$Q,MATCH($A54&"|"&$B54,'faizan grading'!$S:$S,0),COLUMN()-3),""),IF($C54="romain",IFERROR(INDEX('romain grading'!$E:$Q,MATCH($A54&"|"&$B54,'romain grading'!$S:$S,0),COLUMN()-3),""),IF($C54="nishita",IFERROR(INDEX('nishita grading'!$E:$Q,MATCH($A54&"|"&$B54,'nishita grading'!$S:$S,0),COLUMN()-3),""),""))) -> 0 | ... P54: =IF($C54="faizan",IFERROR(INDEX('faizan grading'!$E:$Q,MATCH($A54&"|"&$B54,'faizan grading'!$S:$S,0),COLUMN()-3),""),IF($C54="romain",IFERROR(INDEX('romain grading'!$E:$Q,MATCH($A54&"|"&$B54,'romain grading'!$S:$S,0),COLUMN()-3),""),IF($C54="nishita",IFERROR(INDEX('nishita grading'!$E:$Q,MATCH($A54&"|"&$B54,'nishita grading'!$S:$S,0),COLUMN()-3),""),""))) -> 0 | Q54: =40-SUM(D54:P54) -> 40 | R54: =A54&"|"&B54 -> clueless|0044
A55: clueless | B55: 0044 | C55: romain | D55: =IF($C55="faizan",IFERROR(INDEX('faizan grading'!$E:$Q,MATCH($A55&"|"&$B55,'faizan grading'!$S:$S,0),COLUMN()-3),""),IF($C55="romain",IFERROR(INDEX('romain grading'!$E:$Q,MATCH($A55&"|"&$B55,'romain grading'!$S:$S,0),COLUMN()-3),""),IF($C55="nishita",IFERROR(INDEX('nishita grading'!$E:$Q,MATCH($A55&"|"&$B55,'nishita grading'!$S:$S,0),COLUMN()-3),""),""))) -> 0 | E55: =IF($C55="faizan",IFERROR(INDEX('faizan grading'!$E:$Q,MATCH($A55&"|"&$B55,'faizan grading'!$S:$S,0),COLUMN()-3),""),IF($C55="romain",IFERROR(INDEX('romain grading'!$E:$Q,MATCH($A55&"|"&$B55,'romain grading'!$S:$S,0),COLUMN()-3),""),IF($C55="nishita",IFERROR(INDEX('nishita grading'!$E:$Q,MATCH($A55&"|"&$B55,'nishita grading'!$S:$S,0),COLUMN()-3),""),""))) -> 0 | F55: =IF($C55="faizan",IFERROR(INDEX('faizan grading'!$E:$Q,MATCH($A55&"|"&$B55,'faizan grading'!$S:$S,0),COLUMN()-3),""),IF($C55="romain",IFERROR(INDEX('romain grading'!$E:$Q,MATCH($A55&"|"&$B55,'romain grading'!$S:$S,0),COLUMN()-3),""),IF($C55="nishita",IFERROR(INDEX('nishita grading'!$E:$Q,MATCH($A55&"|"&$B55,'nishita grading'!$S:$S,0),COLUMN()-3),""),""))) -> 0 | G55: =IF($C55="faizan",IFERROR(INDEX('faizan grading'!$E:$Q,MATCH($A55&"|"&$B55,'faizan grading'!$S:$S,0),COLUMN()-3),""),IF($C55="romain",IFERROR(INDEX('romain grading'!$E:$Q,MATCH($A55&"|"&$B55,'romain grading'!$S:$S,0),COLUMN()-3),""),IF($C55="nishita",IFERROR(INDEX('nishita grading'!$E:$Q,MATCH($A55&"|"&$B55,'nishita grading'!$S:$S,0),COLUMN()-3),""),""))) -> 0 | H55: =IF($C55="faizan",IFERROR(INDEX('faizan grading'!$E:$Q,MATCH($A55&"|"&$B55,'faizan grading'!$S:$S,0),COLUMN()-3),""),IF($C55="romain",IFERROR(INDEX('romain grading'!$E:$Q,MATCH($A55&"|"&$B55,'romain grading'!$S:$S,0),COLUMN()-3),""),IF($C55="nishita",IFERROR(INDEX('nishita grading'!$E:$Q,MATCH($A55&"|"&$B55,'nishita grading'!$S:$S,0),COLUMN()-3),""),""))) -> 0 | I55: =IF($C55="faizan",IFERROR(INDEX('faizan grading'!$E:$Q,MATCH($A55&"|"&$B55,'faizan grading'!$S:$S,0),COLUMN()-3),""),IF($C55="romain",IFERROR(INDEX('romain grading'!$E:$Q,MATCH($A55&"|"&$B55,'romain grading'!$S:$S,0),COLUMN()-3),""),IF($C55="nishita",IFERROR(INDEX('nishita grading'!$E:$Q,MATCH($A55&"|"&$B55,'nishita grading'!$S:$S,0),COLUMN()-3),""),""))) -> 0 | J55: =IF($C55="faizan",IFERROR(INDEX('faizan grading'!$E:$Q,MATCH($A55&"|"&$B55,'faizan grading'!$S:$S,0),COLUMN()-3),""),IF($C55="romain",IFERROR(INDEX('romain grading'!$E:$Q,MATCH($A55&"|"&$B55,'romain grading'!$S:$S,0),COLUMN()-3),""),IF($C55="nishita",IFERROR(INDEX('nishita grading'!$E:$Q,MATCH($A55&"|"&$B55,'nishita grading'!$S:$S,0),COLUMN()-3),""),""))) -> 0 | K55: =IF($C55="faizan",IFERROR(INDEX('faizan grading'!$E:$Q,MATCH($A55&"|"&$B55,'faizan grading'!$S:$S,0),COLUMN()-3),""),IF($C55="romain",IFERROR(INDEX('romain grading'!$E:$Q,MATCH($A55&"|"&$B55,'romain grading'!$S:$S,0),COLUMN()-3),""),IF($C55="nishita",IFERROR(INDEX('nishita grading'!$E:$Q,MATCH($A55&"|"&$B55,'nishita grading'!$S:$S,0),COLUMN()-3),""),""))) -> 0 | ... P55: =IF($C55="faizan",IFERROR(INDEX('faizan grading'!$E:$Q,MATCH($A55&"|"&$B55,'faizan grading'!$S:$S,0),COLUMN()-3),""),IF($C55="romain",IFERROR(INDEX('romain grading'!$E:$Q,MATCH($A55&"|"&$B55,'romain grading'!$S:$S,0),COLUMN()-3),""),IF($C55="nishita",IFERROR(INDEX('nishita grading'!$E:$Q,MATCH($A55&"|"&$B55,'nishita grading'!$S:$S,0),COLUMN()-3),""),""))) -> 0 | Q55: =40-SUM(D55:P55) -> 38 | R55: =A55&"|"&B55 -> clueless|0044
A56: clueless | B56: 0044 | C56: nishita | D56: =IF($C56="faizan",IFERROR(INDEX('faizan grading'!$E:$Q,MATCH($A56&"|"&$B56,'faizan grading'!$S:$S,0),COLUMN()-3),""),IF($C56="romain",IFERROR(INDEX('romain grading'!$E:$Q,MATCH($A56&"|"&$B56,'romain grading'!$S:$S,0),COLUMN()-3),""),IF($C56="nishita",IFERROR(INDEX('nishita grading'!$E:$Q,MATCH($A56&"|"&$B56,'nishita grading'!$S:$S,0),COLUMN()-3),""),""))) -> 0 | E56: =IF($C56="faizan",IFERROR(INDEX('faizan grading'!$E:$Q,MATCH($A56&"|"&$B56,'faizan grading'!$S:$S,0),COLUMN()-3),""),IF($C56="romain",IFERROR(INDEX('romain grading'!$E:$Q,MATCH($A56&"|"&$B56,'romain grading'!$S:$S,0),COLUMN()-3),""),IF($C56="nishita",IFERROR(INDEX('nishita grading'!$E:$Q,MATCH($A56&"|"&$B56,'nishita grading'!$S:$S,0),COLUMN()-3),""),""))) -> 0 | F56: =IF($C56="faizan",IFERROR(INDEX('faizan grading'!$E:$Q,MATCH($A56&"|"&$B56,'faizan grading'!$S:$S,0),COLUMN()-3),""),IF($C56="romain",IFERROR(INDEX('romain grading'!$E:$Q,MATCH($A56&"|"&$B56,'romain grading'!$S:$S,0),COLUMN()-3),""),IF($C56="nishita",IFERROR(INDEX('nishita grading'!$E:$Q,MATCH($A56&"|"&$B56,'nishita grading'!$S:$S,0),COLUMN()-3),""),""))) -> 6 | G56: =IF($C56="faizan",IFERROR(INDEX('faizan grading'!$E:$Q,MATCH($A56&"|"&$B56,'faizan grading'!$S:$S,0),COLUMN()-3),""),IF($C56="romain",IFERROR(INDEX('romain grading'!$E:$Q,MATCH($A56&"|"&$B56,'romain grading'!$S:$S,0),COLUMN()-3),""),IF($C56="nishita",IFERROR(INDEX('nishita grading'!$E:$Q,MATCH($A56&"|"&$B56,'nishita grading'!$S:$S,0),COLUMN()-3),""),""))) -> 0 | H56: =IF($C56="faizan",IFERROR(INDEX('faizan grading'!$E:$Q,MATCH($A56&"|"&$B56,'faizan grading'!$S:$S,0),COLUMN()-3),""),IF($C56="romain",IFERROR(INDEX('romain grading'!$E:$Q,MATCH($A56&"|"&$B56,'romain grading'!$S:$S,0),COLUMN()-3),""),IF($C56="nishita",IFERROR(INDEX('nishita grading'!$E:$Q,MATCH($A56&"|"&$B56,'nishita grading'!$S:$S,0),COLUMN()-3),""),""))) -> 0 | I56: =IF($C56="faizan",IFERROR(INDEX('faizan grading'!$E:$Q,MATCH($A56&"|"&$B56,'faizan grading'!$S:$S,0),COLUMN()-3),""),IF($C56="romain",IFERROR(INDEX('romain grading'!$E:$Q,MATCH($A56&"|"&$B56,'romain grading'!$S:$S,0),COLUMN()-3),""),IF($C56="nishita",IFERROR(INDEX('nishita grading'!$E:$Q,MATCH($A56&"|"&$B56,'nishita grading'!$S:$S,0),COLUMN()-3),""),""))) -> 0 | J56: =IF($C56="faizan",IFERROR(INDEX('faizan grading'!$E:$Q,MATCH($A56&"|"&$B56,'faizan grading'!$S:$S,0),COLUMN()-3),""),IF($C56="romain",IFERROR(INDEX('romain grading'!$E:$Q,MATCH($A56&"|"&$B56,'romain grading'!$S:$S,0),COLUMN()-3),""),IF($C56="nishita",IFERROR(INDEX('nishita grading'!$E:$Q,MATCH($A56&"|"&$B56,'nishita grading'!$S:$S,0),COLUMN()-3),""),""))) -> 0 | K56: =IF($C56="faizan",IFERROR(INDEX('faizan grading'!$E:$Q,MATCH($A56&"|"&$B56,'faizan grading'!$S:$S,0),COLUMN()-3),""),IF($C56="romain",IFERROR(INDEX('romain grading'!$E:$Q,MATCH($A56&"|"&$B56,'romain grading'!$S:$S,0),COLUMN()-3),""),IF($C56="nishita",IFERROR(INDEX('nishita grading'!$E:$Q,MATCH($A56&"|"&$B56,'nishita grading'!$S:$S,0),COLUMN()-3),""),""))) -> 4 | ... P56: =IF($C56="faizan",IFERROR(INDEX('faizan grading'!$E:$Q,MATCH($A56&"|"&$B56,'faizan grading'!$S:$S,0),COLUMN()-3),""),IF($C56="romain",IFERROR(INDEX('romain grading'!$E:$Q,MATCH($A56&"|"&$B56,'romain grading'!$S:$S,0),COLUMN()-3),""),IF($C56="nishita",IFERROR(INDEX('nishita grading'!$E:$Q,MATCH($A56&"|"&$B56,'nishita grading'!$S:$S,0),COLUMN()-3),""),""))) -> 0 | Q56: =40-SUM(D56:P56) -> 30 | R56: =A56&"|"&B56 -> clueless|0044
A57: clueless | B57: 0044 | C57: claude | D57: 0 | E57: 0 | F57: 6 | G57: 0 | H57: 3 | I57: 0 | J57: 0 | K57: 4 | L57: 0 | M57: 0 | N57: 0 | O57: 0 | P57: 0 | Q57: =40-SUM(D57:P57) -> 27 | R57: =A57&"|"&B57 -> clueless|0044
A58: clueless | B58: 0123 | C58: faizan | D58: =IF($C58="faizan",IFERROR(INDEX('faizan grading'!$E:$Q,MATCH($A58&"|"&$B58,'faizan grading'!$S:$S,0),COLUMN()-3),""),IF($C58="romain",IFERROR(INDEX('romain grading'!$E:$Q,MATCH($A58&"|"&$B58,'romain grading'!$S:$S,0),COLUMN()-3),""),IF($C58="nishita",IFERROR(INDEX('nishita grading'!$E:$Q,MATCH($A58&"|"&$B58,'nishita grading'!$S:$S,0),COLUMN()-3),""),""))) -> 0 | E58: =IF($C58="faizan",IFERROR(INDEX('faizan grading'!$E:$Q,MATCH($A58&"|"&$B58,'faizan grading'!$S:$S,0),COLUMN()-3),""),IF($C58="romain",IFERROR(INDEX('romain grading'!$E:$Q,MATCH($A58&"|"&$B58,'romain grading'!$S:$S,0),COLUMN()-3),""),IF($C58="nishita",IFERROR(INDEX('nishita grading'!$E:$Q,MATCH($A58&"|"&$B58,'nishita grading'!$S:$S,0),COLUMN()-3),""),""))) -> 0 | F58: =IF($C58="faizan",IFERROR(INDEX('faizan grading'!$E:$Q,MATCH($A58&"|"&$B58,'faizan grading'!$S:$S,0),COLUMN()-3),""),IF($C58="romain",IFERROR(INDEX('romain grading'!$E:$Q,MATCH($A58&"|"&$B58,'romain grading'!$S:$S,0),COLUMN()-3),""),IF($C58="nishita",IFERROR(INDEX('nishita grading'!$E:$Q,MATCH($A58&"|"&$B58,'nishita grading'!$S:$S,0),COLUMN()-3),""),""))) -> 0 | G58: =IF($C58="faizan",IFERROR(INDEX('faizan grading'!$E:$Q,MATCH($A58&"|"&$B58,'faizan grading'!$S:$S,0),COLUMN()-3),""),IF($C58="romain",IFERROR(INDEX('romain grading'!$E:$Q,MATCH($A58&"|"&$B58,'romain grading'!$S:$S,0),COLUMN()-3),""),IF($C58="nishita",IFERROR(INDEX('nishita grading'!$E:$Q,MATCH($A58&"|"&$B58,'nishita grading'!$S:$S,0),COLUMN()-3),""),""))) -> 0 | H58: =IF($C58="faizan",IFERROR(INDEX('faizan grading'!$E:$Q,MATCH($A58&"|"&$B58,'faizan grading'!$S:$S,0),COLUMN()-3),""),IF($C58="romain",IFERROR(INDEX('romain grading'!$E:$Q,MATCH($A58&"|"&$B58,'romain grading'!$S:$S,0),COLUMN()-3),""),IF($C58="nishita",IFERROR(INDEX('nishita grading'!$E:$Q,MATCH($A58&"|"&$B58,'nishita grading'!$S:$S,0),COLUMN()-3),""),""))) -> 0 | I58: =IF($C58="faizan",IFERROR(INDEX('faizan grading'!$E:$Q,MATCH($A58&"|"&$B58,'faizan grading'!$S:$S,0),COLUMN()-3),""),IF($C58="romain",IFERROR(INDEX('romain grading'!$E:$Q,MATCH($A58&"|"&$B58,'romain grading'!$S:$S,0),COLUMN()-3),""),IF($C58="nishita",IFERROR(INDEX('nishita grading'!$E:$Q,MATCH($A58&"|"&$B58,'nishita grading'!$S:$S,0),COLUMN()-3),""),""))) -> 0 | J58: =IF($C58="faizan",IFERROR(INDEX('faizan grading'!$E:$Q,MATCH($A58&"|"&$B58,'faizan grading'!$S:$S,0),COLUMN()-3),""),IF($C58="romain",IFERROR(INDEX('romain grading'!$E:$Q,MATCH($A58&"|"&$B58,'romain grading'!$S:$S,0),COLUMN()-3),""),IF($C58="nishita",IFERROR(INDEX('nishita grading'!$E:$Q,MATCH($A58&"|"&$B58,'nishita grading'!$S:$S,0),COLUMN()-3),""),""))) -> 0 | K58: =IF($C58="faizan",IFERROR(INDEX('faizan grading'!$E:$Q,MATCH($A58&"|"&$B58,'faizan grading'!$S:$S,0),COLUMN()-3),""),IF($C58="romain",IFERROR(INDEX('romain grading'!$E:$Q,MATCH($A58&"|"&$B58,'romain grading'!$S:$S,0),COLUMN()-3),""),IF($C58="nishita",IFERROR(INDEX('nishita grading'!$E:$Q,MATCH($A58&"|"&$B58,'nishita grading'!$S:$S,0),COLUMN()-3),""),""))) -> 0 | ... P58: =IF($C58="faizan",IFERROR(INDEX('faizan grading'!$E:$Q,MATCH($A58&"|"&$B58,'faizan grading'!$S:$S,0),COLUMN()-3),""),IF($C58="romain",IFERROR(INDEX('romain grading'!$E:$Q,MATCH($A58&"|"&$B58,'romain grading'!$S:$S,0),COLUMN()-3),""),IF($C58="nishita",IFERROR(INDEX('nishita grading'!$E:$Q,MATCH($A58&"|"&$B58,'nishita grading'!$S:$S,0),COLUMN()-3),""),""))) -> 0 | Q58: =40-SUM(D58:P58) -> 40 | R58: =A58&"|"&B58 -> clueless|0123
A59: clueless | B59: 0123 | C59: romain | D59: =IF($C59="faizan",IFERROR(INDEX('faizan grading'!$E:$Q,MATCH($A59&"|"&$B59,'faizan grading'!$S:$S,0),COLUMN()-3),""),IF($C59="romain",IFERROR(INDEX('romain grading'!$E:$Q,MATCH($A59&"|"&$B59,'romain grading'!$S:$S,0),COLUMN()-3),""),IF($C59="nishita",IFERROR(INDEX('nishita grading'!$E:$Q,MATCH($A59&"|"&$B59,'nishita grading'!$S:$S,0),COLUMN()-3),""),""))) -> 0 | E59: =IF($C59="faizan",IFERROR(INDEX('faizan grading'!$E:$Q,MATCH($A59&"|"&$B59,'faizan grading'!$S:$S,0),COLUMN()-3),""),IF($C59="romain",IFERROR(INDEX('romain grading'!$E:$Q,MATCH($A59&"|"&$B59,'romain grading'!$S:$S,0),COLUMN()-3),""),IF($C59="nishita",IFERROR(INDEX('nishita grading'!$E:$Q,MATCH($A59&"|"&$B59,'nishita grading'!$S:$S,0),COLUMN()-3),""),""))) -> 0 | F59: =IF($C59="faizan",IFERROR(INDEX('faizan grading'!$E:$Q,MATCH($A59&"|"&$B59,'faizan grading'!$S:$S,0),COLUMN()-3),""),IF($C59="romain",IFERROR(INDEX('romain grading'!$E:$Q,MATCH($A59&"|"&$B59,'romain grading'!$S:$S,0),COLUMN()-3),""),IF($C59="nishita",IFERROR(INDEX('nishita grading'!$E:$Q,MATCH($A59&"|"&$B59,'nishita grading'!$S:$S,0),COLUMN()-3),""),""))) -> 0 | G59: =IF($C59="faizan",IFERROR(INDEX('faizan grading'!$E:$Q,MATCH($A59&"|"&$B59,'faizan grading'!$S:$S,0),COLUMN()-3),""),IF($C59="romain",IFERROR(INDEX('romain grading'!$E:$Q,MATCH($A59&"|"&$B59,'romain grading'!$S:$S,0),COLUMN()-3),""),IF($C59="nishita",IFERROR(INDEX('nishita grading'!$E:$Q,MATCH($A59&"|"&$B59,'nishita grading'!$S:$S,0),COLUMN()-3),""),""))) -> 0 | H59: =IF($C59="faizan",IFERROR(INDEX('faizan grading'!$E:$Q,MATCH($A59&"|"&$B59,'faizan grading'!$S:$S,0),COLUMN()-3),""),IF($C59="romain",IFERROR(INDEX('romain grading'!$E:$Q,MATCH($A59&"|"&$B59,'romain grading'!$S:$S,0),COLUMN()-3),""),IF($C59="nishita",IFERROR(INDEX('nishita grading'!$E:$Q,MATCH($A59&"|"&$B59,'nishita grading'!$S:$S,0),COLUMN()-3),""),""))) -> 0 | I59: =IF($C59="faizan",IFERROR(INDEX('faizan grading'!$E:$Q,MATCH($A59&"|"&$B59,'faizan grading'!$S:$S,0),COLUMN()-3),""),IF($C59="romain",IFERROR(INDEX('romain grading'!$E:$Q,MATCH($A59&"|"&$B59,'romain grading'!$S:$S,0),COLUMN()-3),""),IF($C59="nishita",IFERROR(INDEX('nishita grading'!$E:$Q,MATCH($A59&"|"&$B59,'nishita grading'!$S:$S,0),COLUMN()-3),""),""))) -> 0 | J59: =IF($C59="faizan",IFERROR(INDEX('faizan grading'!$E:$Q,MATCH($A59&"|"&$B59,'faizan grading'!$S:$S,0),COLUMN()-3),""),IF($C59="romain",IFERROR(INDEX('romain grading'!$E:$Q,MATCH($A59&"|"&$B59,'romain grading'!$S:$S,0),COLUMN()-3),""),IF($C59="nishita",IFERROR(INDEX('nishita grading'!$E:$Q,MATCH($A59&"|"&$B59,'nishita grading'!$S:$S,0),COLUMN()-3),""),""))) -> 0 | K59: =IF($C59="faizan",IFERROR(INDEX('faizan grading'!$E:$Q,MATCH($A59&"|"&$B59,'faizan grading'!$S:$S,0),COLUMN()-3),""),IF($C59="romain",IFERROR(INDEX('romain grading'!$E:$Q,MATCH($A59&"|"&$B59,'romain grading'!$S:$S,0),COLUMN()-3),""),IF($C59="nishita",IFERROR(INDEX('nishita grading'!$E:$Q,MATCH($A59&"|"&$B59,'nishita grading'!$S:$S,0),COLUMN()-3),""),""))) -> 0 | ... P59: =IF($C59="faizan",IFERROR(INDEX('faizan grading'!$E:$Q,MATCH($A59&"|"&$B59,'faizan grading'!$S:$S,0),COLUMN()-3),""),IF($C59="romain",IFERROR(INDEX('romain grading'!$E:$Q,MATCH($A59&"|"&$B59,'romain grading'!$S:$S,0),COLUMN()-3),""),IF($C59="nishita",IFERROR(INDEX('nishita grading'!$E:$Q,MATCH($A59&"|"&$B59,'nishita grading'!$S:$S,0),COLUMN()-3),""),""))) -> 0 | Q59: =40-SUM(D59:P59) -> 40 | R59: =A59&"|"&B59 -> clueless|0123
A60: clueless | B60: 0123 | C60: nishita | D60: =IF($C60="faizan",IFERROR(INDEX('faizan grading'!$E:$Q,MATCH($A60&"|"&$B60,'faizan grading'!$S:$S,0),COLUMN()-3),""),IF($C60="romain",IFERROR(INDEX('romain grading'!$E:$Q,MATCH($A60&"|"&$B60,'romain grading'!$S:$S,0),COLUMN()-3),""),IF($C60="nishita",IFERROR(INDEX('nishita grading'!$E:$Q,MATCH($A60&"|"&$B60,'nishita grading'!$S:$S,0),COLUMN()-3),""),""))) -> 0 | E60: =IF($C60="faizan",IFERROR(INDEX('faizan grading'!$E:$Q,MATCH($A60&"|"&$B60,'faizan grading'!$S:$S,0),COLUMN()-3),""),IF($C60="romain",IFERROR(INDEX('romain grading'!$E:$Q,MATCH($A60&"|"&$B60,'romain grading'!$S:$S,0),COLUMN()-3),""),IF($C60="nishita",IFERROR(INDEX('nishita grading'!$E:$Q,MATCH($A60&"|"&$B60,'nishita grading'!$S:$S,0),COLUMN()-3),""),""))) -> 0 | F60: =IF($C60="faizan",IFERROR(INDEX('faizan grading'!$E:$Q,MATCH($A60&"|"&$B60,'faizan grading'!$S:$S,0),COLUMN()-3),""),IF($C60="romain",IFERROR(INDEX('romain grading'!$E:$Q,MATCH($A60&"|"&$B60,'romain grading'!$S:$S,0),COLUMN()-3),""),IF($C60="nishita",IFERROR(INDEX('nishita grading'!$E:$Q,MATCH($A60&"|"&$B60,'nishita grading'!$S:$S,0),COLUMN()-3),""),""))) -> 0 | G60: =IF($C60="faizan",IFERROR(INDEX('faizan grading'!$E:$Q,MATCH($A60&"|"&$B60,'faizan grading'!$S:$S,0),COLUMN()-3),""),IF($C60="romain",IFERROR(INDEX('romain grading'!$E:$Q,MATCH($A60&"|"&$B60,'romain grading'!$S:$S,0),COLUMN()-3),""),IF($C60="nishita",IFERROR(INDEX('nishita grading'!$E:$Q,MATCH($A60&"|"&$B60,'nishita grading'!$S:$S,0),COLUMN()-3),""),""))) -> 0 | H60: =IF($C60="faizan",IFERROR(INDEX('faizan grading'!$E:$Q,MATCH($A60&"|"&$B60,'faizan grading'!$S:$S,0),COLUMN()-3),""),IF($C60="romain",IFERROR(INDEX('romain grading'!$E:$Q,MATCH($A60&"|"&$B60,'romain grading'!$S:$S,0),COLUMN()-3),""),IF($C60="nishita",IFERROR(INDEX('nishita grading'!$E:$Q,MATCH($A60&"|"&$B60,'nishita grading'!$S:$S,0),COLUMN()-3),""),""))) -> 0 | I60: =IF($C60="faizan",IFERROR(INDEX('faizan grading'!$E:$Q,MATCH($A60&"|"&$B60,'faizan grading'!$S:$S,0),COLUMN()-3),""),IF($C60="romain",IFERROR(INDEX('romain grading'!$E:$Q,MATCH($A60&"|"&$B60,'romain grading'!$S:$S,0),COLUMN()-3),""),IF($C60="nishita",IFERROR(INDEX('nishita grading'!$E:$Q,MATCH($A60&"|"&$B60,'nishita grading'!$S:$S,0),COLUMN()-3),""),""))) -> 0 | J60: =IF($C60="faizan",IFERROR(INDEX('faizan grading'!$E:$Q,MATCH($A60&"|"&$B60,'faizan grading'!$S:$S,0),COLUMN()-3),""),IF($C60="romain",IFERROR(INDEX('romain grading'!$E:$Q,MATCH($A60&"|"&$B60,'romain grading'!$S:$S,0),COLUMN()-3),""),IF($C60="nishita",IFERROR(INDEX('nishita grading'!$E:$Q,MATCH($A60&"|"&$B60,'nishita grading'!$S:$S,0),COLUMN()-3),""),""))) -> 0 | K60: =IF($C60="faizan",IFERROR(INDEX('faizan grading'!$E:$Q,MATCH($A60&"|"&$B60,'faizan grading'!$S:$S,0),COLUMN()-3),""),IF($C60="romain",IFERROR(INDEX('romain grading'!$E:$Q,MATCH($A60&"|"&$B60,'romain grading'!$S:$S,0),COLUMN()-3),""),IF($C60="nishita",IFERROR(INDEX('nishita grading'!$E:$Q,MATCH($A60&"|"&$B60,'nishita grading'!$S:$S,0),COLUMN()-3),""),""))) -> 4 | ... P60: =IF($C60="faizan",IFERROR(INDEX('faizan grading'!$E:$Q,MATCH($A60&"|"&$B60,'faizan grading'!$S:$S,0),COLUMN()-3),""),IF($C60="romain",IFERROR(INDEX('romain grading'!$E:$Q,MATCH($A60&"|"&$B60,'romain grading'!$S:$S,0),COLUMN()-3),""),IF($C60="nishita",IFERROR(INDEX('nishita grading'!$E:$Q,MATCH($A60&"|"&$B60,'nishita grading'!$S:$S,0),COLUMN()-3),""),""))) -> 0 | Q60: =40-SUM(D60:P60) -> 36 | R60: =A60&"|"&B60 -> clueless|0123
A61: clueless | B61: 0123 | C61: claude | D61: 0 | E61: 0 | F61: 0 | G61: 0 | H61: 0 | I61: 2 | J61: 0 | K61: 4 | L61: 0 | M61: 0 | N61: 0 | O61: 0 | P61: 0 | Q61: =40-SUM(D61:P61) -> 34 | R61: =A61&"|"&B61 -> clueless|0123
A62: clueless | B62: 0144 | C62: faizan | D62: =IF($C62="faizan",IFERROR(INDEX('faizan grading'!$E:$Q,MATCH($A62&"|"&$B62,'faizan grading'!$S:$S,0),COLUMN()-3),""),IF($C62="romain",IFERROR(INDEX('romain grading'!$E:$Q,MATCH($A62&"|"&$B62,'romain grading'!$S:$S,0),COLUMN()-3),""),IF($C62="nishita",IFERROR(INDEX('nishita grading'!$E:$Q,MATCH($A62&"|"&$B62,'nishita grading'!$S:$S,0),COLUMN()-3),""),""))) -> 0 | E62: =IF($C62="faizan",IFERROR(INDEX('faizan grading'!$E:$Q,MATCH($A62&"|"&$B62,'faizan grading'!$S:$S,0),COLUMN()-3),""),IF($C62="romain",IFERROR(INDEX('romain grading'!$E:$Q,MATCH($A62&"|"&$B62,'romain grading'!$S:$S,0),COLUMN()-3),""),IF($C62="nishita",IFERROR(INDEX('nishita grading'!$E:$Q,MATCH($A62&"|"&$B62,'nishita grading'!$S:$S,0),COLUMN()-3),""),""))) -> 0 | F62: =IF($C62="faizan",IFERROR(INDEX('faizan grading'!$E:$Q,MATCH($A62&"|"&$B62,'faizan grading'!$S:$S,0),COLUMN()-3),""),IF($C62="romain",IFERROR(INDEX('romain grading'!$E:$Q,MATCH($A62&"|"&$B62,'romain grading'!$S:$S,0),COLUMN()-3),""),IF($C62="nishita",IFERROR(INDEX('nishita grading'!$E:$Q,MATCH($A62&"|"&$B62,'nishita grading'!$S:$S,0),COLUMN()-3),""),""))) -> 0 | G62: =IF($C62="faizan",IFERROR(INDEX('faizan grading'!$E:$Q,MATCH($A62&"|"&$B62,'faizan grading'!$S:$S,0),COLUMN()-3),""),IF($C62="romain",IFERROR(INDEX('romain grading'!$E:$Q,MATCH($A62&"|"&$B62,'romain grading'!$S:$S,0),COLUMN()-3),""),IF($C62="nishita",IFERROR(INDEX('nishita grading'!$E:$Q,MATCH($A62&"|"&$B62,'nishita grading'!$S:$S,0),COLUMN()-3),""),""))) -> 0 | H62: =IF($C62="faizan",IFERROR(INDEX('faizan grading'!$E:$Q,MATCH($A62&"|"&$B62,'faizan grading'!$S:$S,0),COLUMN()-3),""),IF($C62="romain",IFERROR(INDEX('romain grading'!$E:$Q,MATCH($A62&"|"&$B62,'romain grading'!$S:$S,0),COLUMN()-3),""),IF($C62="nishita",IFERROR(INDEX('nishita grading'!$E:$Q,MATCH($A62&"|"&$B62,'nishita grading'!$S:$S,0),COLUMN()-3),""),""))) -> 0 | I62: =IF($C62="faizan",IFERROR(INDEX('faizan grading'!$E:$Q,MATCH($A62&"|"&$B62,'faizan grading'!$S:$S,0),COLUMN()-3),""),IF($C62="romain",IFERROR(INDEX('romain grading'!$E:$Q,MATCH($A62&"|"&$B62,'romain grading'!$S:$S,0),COLUMN()-3),""),IF($C62="nishita",IFERROR(INDEX('nishita grading'!$E:$Q,MATCH($A62&"|"&$B62,'nishita grading'!$S:$S,0),COLUMN()-3),""),""))) -> 0 | J62: =IF($C62="faizan",IFERROR(INDEX('faizan grading'!$E:$Q,MATCH($A62&"|"&$B62,'faizan grading'!$S:$S,0),COLUMN()-3),""),IF($C62="romain",IFERROR(INDEX('romain grading'!$E:$Q,MATCH($A62&"|"&$B62,'romain grading'!$S:$S,0),COLUMN()-3),""),IF($C62="nishita",IFERROR(INDEX('nishita grading'!$E:$Q,MATCH($A62&"|"&$B62,'nishita grading'!$S:$S,0),COLUMN()-3),""),""))) -> 0 | K62: =IF($C62="faizan",IFERROR(INDEX('faizan grading'!$E:$Q,MATCH($A62&"|"&$B62,'faizan grading'!$S:$S,0),COLUMN()-3),""),IF($C62="romain",IFERROR(INDEX('romain grading'!$E:$Q,MATCH($A62&"|"&$B62,'romain grading'!$S:$S,0),COLUMN()-3),""),IF($C62="nishita",IFERROR(INDEX('nishita grading'!$E:$Q,MATCH($A62&"|"&$B62,'nishita grading'!$S:$S,0),COLUMN()-3),""),""))) -> 0 | ... P62: =IF($C62="faizan",IFERROR(INDEX('faizan grading'!$E:$Q,MATCH($A62&"|"&$B62,'faizan grading'!$S:$S,0),COLUMN()-3),""),IF($C62="romain",IFERROR(INDEX('romain grading'!$E:$Q,MATCH($A62&"|"&$B62,'romain grading'!$S:$S,0),COLUMN()-3),""),IF($C62="nishita",IFERROR(INDEX('nishita grading'!$E:$Q,MATCH($A62&"|"&$B62,'nishita grading'!$S:$S,0),COLUMN()-3),""),""))) -> 0 | Q62: =40-SUM(D62:P62) -> 40 | R62: =A62&"|"&B62 -> clueless|0144
A63: clueless | B63: 0144 | C63: romain | D63: =IF($C63="faizan",IFERROR(INDEX('faizan grading'!$E:$Q,MATCH($A63&"|"&$B63,'faizan grading'!$S:$S,0),COLUMN()-3),""),IF($C63="romain",IFERROR(INDEX('romain grading'!$E:$Q,MATCH($A63&"|"&$B63,'romain grading'!$S:$S,0),COLUMN()-3),""),IF($C63="nishita",IFERROR(INDEX('nishita grading'!$E:$Q,MATCH($A63&"|"&$B63,'nishita grading'!$S:$S,0),COLUMN()-3),""),""))) -> 0 | E63: =IF($C63="faizan",IFERROR(INDEX('faizan grading'!$E:$Q,MATCH($A63&"|"&$B63,'faizan grading'!$S:$S,0),COLUMN()-3),""),IF($C63="romain",IFERROR(INDEX('romain grading'!$E:$Q,MATCH($A63&"|"&$B63,'romain grading'!$S:$S,0),COLUMN()-3),""),IF($C63="nishita",IFERROR(INDEX('nishita grading'!$E:$Q,MATCH($A63&"|"&$B63,'nishita grading'!$S:$S,0),COLUMN()-3),""),""))) -> 0 | F63: =IF($C63="faizan",IFERROR(INDEX('faizan grading'!$E:$Q,MATCH($A63&"|"&$B63,'faizan grading'!$S:$S,0),COLUMN()-3),""),IF($C63="romain",IFERROR(INDEX('romain grading'!$E:$Q,MATCH($A63&"|"&$B63,'romain grading'!$S:$S,0),COLUMN()-3),""),IF($C63="nishita",IFERROR(INDEX('nishita grading'!$E:$Q,MATCH($A63&"|"&$B63,'nishita grading'!$S:$S,0),COLUMN()-3),""),""))) -> 0 | G63: =IF($C63="faizan",IFERROR(INDEX('faizan grading'!$E:$Q,MATCH($A63&"|"&$B63,'faizan grading'!$S:$S,0),COLUMN()-3),""),IF($C63="romain",IFERROR(INDEX('romain grading'!$E:$Q,MATCH($A63&"|"&$B63,'romain grading'!$S:$S,0),COLUMN()-3),""),IF($C63="nishita",IFERROR(INDEX('nishita grading'!$E:$Q,MATCH($A63&"|"&$B63,'nishita grading'!$S:$S,0),COLUMN()-3),""),""))) -> 0 | H63: =IF($C63="faizan",IFERROR(INDEX('faizan grading'!$E:$Q,MATCH($A63&"|"&$B63,'faizan grading'!$S:$S,0),COLUMN()-3),""),IF($C63="romain",IFERROR(INDEX('romain grading'!$E:$Q,MATCH($A63&"|"&$B63,'romain grading'!$S:$S,0),COLUMN()-3),""),IF($C63="nishita",IFERROR(INDEX('nishita grading'!$E:$Q,MATCH($A63&"|"&$B63,'nishita grading'!$S:$S,0),COLUMN()-3),""),""))) -> 0 | I63: =IF($C63="faizan",IFERROR(INDEX('faizan grading'!$E:$Q,MATCH($A63&"|"&$B63,'faizan grading'!$S:$S,0),COLUMN()-3),""),IF($C63="romain",IFERROR(INDEX('romain grading'!$E:$Q,MATCH($A63&"|"&$B63,'romain grading'!$S:$S,0),COLUMN()-3),""),IF($C63="nishita",IFERROR(INDEX('nishita grading'!$E:$Q,MATCH($A63&"|"&$B63,'nishita grading'!$S:$S,0),COLUMN()-3),""),""))) -> 0 | J63: =IF($C63="faizan",IFERROR(INDEX('faizan grading'!$E:$Q,MATCH($A63&"|"&$B63,'faizan grading'!$S:$S,0),COLUMN()-3),""),IF($C63="romain",IFERROR(INDEX('romain grading'!$E:$Q,MATCH($A63&"|"&$B63,'romain grading'!$S:$S,0),COLUMN()-3),""),IF($C63="nishita",IFERROR(INDEX('nishita grading'!$E:$Q,MATCH($A63&"|"&$B63,'nishita grading'!$S:$S,0),COLUMN()-3),""),""))) -> 0 | K63: =IF($C63="faizan",IFERROR(INDEX('faizan grading'!$E:$Q,MATCH($A63&"|"&$B63,'faizan grading'!$S:$S,0),COLUMN()-3),""),IF($C63="romain",IFERROR(INDEX('romain grading'!$E:$Q,MATCH($A63&"|"&$B63,'romain grading'!$S:$S,0),COLUMN()-3),""),IF($C63="nishita",IFERROR(INDEX('nishita grading'!$E:$Q,MATCH($A63&"|"&$B63,'nishita grading'!$S:$S,0),COLUMN()-3),""),""))) -> 0 | ... P63: =IF($C63="faizan",IFERROR(INDEX('faizan grading'!$E:$Q,MATCH($A63&"|"&$B63,'faizan grading'!$S:$S,0),COLUMN()-3),""),IF($C63="romain",IFERROR(INDEX('romain grading'!$E:$Q,MATCH($A63&"|"&$B63,'romain grading'!$S:$S,0),COLUMN()-3),""),IF($C63="nishita",IFERROR(INDEX('nishita grading'!$E:$Q,MATCH($A63&"|"&$B63,'nishita grading'!$S:$S,0),COLUMN()-3),""),""))) -> 0 | Q63: =40-SUM(D63:P63) -> 40 | R63: =A63&"|"&B63 -> clueless|0144
A64: clueless | B64: 0144 | C64: nishita | D64: =IF($C64="faizan",IFERROR(INDEX('faizan grading'!$E:$Q,MATCH($A64&"|"&$B64,'faizan grading'!$S:$S,0),COLUMN()-3),""),IF($C64="romain",IFERROR(INDEX('romain grading'!$E:$Q,MATCH($A64&"|"&$B64,'romain grading'!$S:$S,0),COLUMN()-3),""),IF($C64="nishita",IFERROR(INDEX('nishita grading'!$E:$Q,MATCH($A64&"|"&$B64,'nishita grading'!$S:$S,0),COLUMN()-3),""),""))) -> 0 | E64: =IF($C64="faizan",IFERROR(INDEX('faizan grading'!$E:$Q,MATCH($A64&"|"&$B64,'faizan grading'!$S:$S,0),COLUMN()-3),""),IF($C64="romain",IFERROR(INDEX('romain grading'!$E:$Q,MATCH($A64&"|"&$B64,'romain grading'!$S:$S,0),COLUMN()-3),""),IF($C64="nishita",IFERROR(INDEX('nishita grading'!$E:$Q,MATCH($A64&"|"&$B64,'nishita grading'!$S:$S,0),COLUMN()-3),""),""))) -> 0 | F64: =IF($C64="faizan",IFERROR(INDEX('faizan grading'!$E:$Q,MATCH($A64&"|"&$B64,'faizan grading'!$S:$S,0),COLUMN()-3),""),IF($C64="romain",IFERROR(INDEX('romain grading'!$E:$Q,MATCH($A64&"|"&$B64,'romain grading'!$S:$S,0),COLUMN()-3),""),IF($C64="nishita",IFERROR(INDEX('nishita grading'!$E:$Q,MATCH($A64&"|"&$B64,'nishita grading'!$S:$S,0),COLUMN()-3),""),""))) -> 0 | G64: =IF($C64="faizan",IFERROR(INDEX('faizan grading'!$E:$Q,MATCH($A64&"|"&$B64,'faizan grading'!$S:$S,0),COLUMN()-3),""),IF($C64="romain",IFERROR(INDEX('romain grading'!$E:$Q,MATCH($A64&"|"&$B64,'romain grading'!$S:$S,0),COLUMN()-3),""),IF($C64="nishita",IFERROR(INDEX('nishita grading'!$E:$Q,MATCH($A64&"|"&$B64,'nishita grading'!$S:$S,0),COLUMN()-3),""),""))) -> 0 | H64: =IF($C64="faizan",IFERROR(INDEX('faizan grading'!$E:$Q,MATCH($A64&"|"&$B64,'faizan grading'!$S:$S,0),COLUMN()-3),""),IF($C64="romain",IFERROR(INDEX('romain grading'!$E:$Q,MATCH($A64&"|"&$B64,'romain grading'!$S:$S,0),COLUMN()-3),""),IF($C64="nishita",IFERROR(INDEX('nishita grading'!$E:$Q,MATCH($A64&"|"&$B64,'nishita grading'!$S:$S,0),COLUMN()-3),""),""))) -> 0 | I64: =IF($C64="faizan",IFERROR(INDEX('faizan grading'!$E:$Q,MATCH($A64&"|"&$B64,'faizan grading'!$S:$S,0),COLUMN()-3),""),IF($C64="romain",IFERROR(INDEX('romain grading'!$E:$Q,MATCH($A64&"|"&$B64,'romain grading'!$S:$S,0),COLUMN()-3),""),IF($C64="nishita",IFERROR(INDEX('nishita grading'!$E:$Q,MATCH($A64&"|"&$B64,'nishita grading'!$S:$S,0),COLUMN()-3),""),""))) -> 0 | J64: =IF($C64="faizan",IFERROR(INDEX('faizan grading'!$E:$Q,MATCH($A64&"|"&$B64,'faizan grading'!$S:$S,0),COLUMN()-3),""),IF($C64="romain",IFERROR(INDEX('romain grading'!$E:$Q,MATCH($A64&"|"&$B64,'romain grading'!$S:$S,0),COLUMN()-3),""),IF($C64="nishita",IFERROR(INDEX('nishita grading'!$E:$Q,MATCH($A64&"|"&$B64,'nishita grading'!$S:$S,0),COLUMN()-3),""),""))) -> 0 | K64: =IF($C64="faizan",IFERROR(INDEX('faizan grading'!$E:$Q,MATCH($A64&"|"&$B64,'faizan grading'!$S:$S,0),COLUMN()-3),""),IF($C64="romain",IFERROR(INDEX('romain grading'!$E:$Q,MATCH($A64&"|"&$B64,'romain grading'!$S:$S,0),COLUMN()-3),""),IF($C64="nishita",IFERROR(INDEX('nishita grading'!$E:$Q,MATCH($A64&"|"&$B64,'nishita grading'!$S:$S,0),COLUMN()-3),""),""))) -> 4 | ... P64: =IF($C64="faizan",IFERROR(INDEX('faizan grading'!$E:$Q,MATCH($A64&"|"&$B64,'faizan grading'!$S:$S,0),COLUMN()-3),""),IF($C64="romain",IFERROR(INDEX('romain grading'!$E:$Q,MATCH($A64&"|"&$B64,'romain grading'!$S:$S,0),COLUMN()-3),""),IF($C64="nishita",IFERROR(INDEX('nishita grading'!$E:$Q,MATCH($A64&"|"&$B64,'nishita grading'!$S:$S,0),COLUMN()-3),""),""))) -> 0 | Q64: =40-SUM(D64:P64) -> 36 | R64: =A64&"|"&B64 -> clueless|0144
A65: clueless | B65: 0144 | C65: claude | D65: 0 | E65: 0 | F65: 0 | G65: 0 | H65: 0 | I65: 0 | J65: 0 | K65: 4 | L65: 0 | M65: 0 | N65: 0 | O65: 0 | P65: 0 | Q65: =40-SUM(D65:P65) -> 36 | R65: =A65&"|"&B65 -> clueless|0144
A66: clueless | B66: 0218 | C66: faizan | D66: =IF($C66="faizan",IFERROR(INDEX('faizan grading'!$E:$Q,MATCH($A66&"|"&$B66,'faizan grading'!$S:$S,0),COLUMN()-3),""),IF($C66="romain",IFERROR(INDEX('romain grading'!$E:$Q,MATCH($A66&"|"&$B66,'romain grading'!$S:$S,0),COLUMN()-3),""),IF($C66="nishita",IFERROR(INDEX('nishita grading'!$E:$Q,MATCH($A66&"|"&$B66,'nishita grading'!$S:$S,0),COLUMN()-3),""),""))) -> 0 | E66: =IF($C66="faizan",IFERROR(INDEX('faizan grading'!$E:$Q,MATCH($A66&"|"&$B66,'faizan grading'!$S:$S,0),COLUMN()-3),""),IF($C66="romain",IFERROR(INDEX('romain grading'!$E:$Q,MATCH($A66&"|"&$B66,'romain grading'!$S:$S,0),COLUMN()-3),""),IF($C66="nishita",IFERROR(INDEX('nishita grading'!$E:$Q,MATCH($A66&"|"&$B66,'nishita grading'!$S:$S,0),COLUMN()-3),""),""))) -> 0 | F66: =IF($C66="faizan",IFERROR(INDEX('faizan grading'!$E:$Q,MATCH($A66&"|"&$B66,'faizan grading'!$S:$S,0),COLUMN()-3),""),IF($C66="romain",IFERROR(INDEX('romain grading'!$E:$Q,MATCH($A66&"|"&$B66,'romain grading'!$S:$S,0),COLUMN()-3),""),IF($C66="nishita",IFERROR(INDEX('nishita grading'!$E:$Q,MATCH($A66&"|"&$B66,'nishita grading'!$S:$S,0),COLUMN()-3),""),""))) -> 0 | G66: =IF($C66="faizan",IFERROR(INDEX('faizan grading'!$E:$Q,MATCH($A66&"|"&$B66,'faizan grading'!$S:$S,0),COLUMN()-3),""),IF($C66="romain",IFERROR(INDEX('romain grading'!$E:$Q,MATCH($A66&"|"&$B66,'romain grading'!$S:$S,0),COLUMN()-3),""),IF($C66="nishita",IFERROR(INDEX('nishita grading'!$E:$Q,MATCH($A66&"|"&$B66,'nishita grading'!$S:$S,0),COLUMN()-3),""),""))) -> 0 | H66: =IF($C66="faizan",IFERROR(INDEX('faizan grading'!$E:$Q,MATCH($A66&"|"&$B66,'faizan grading'!$S:$S,0),COLUMN()-3),""),IF($C66="romain",IFERROR(INDEX('romain grading'!$E:$Q,MATCH($A66&"|"&$B66,'romain grading'!$S:$S,0),COLUMN()-3),""),IF($C66="nishita",IFERROR(INDEX('nishita grading'!$E:$Q,MATCH($A66&"|"&$B66,'nishita grading'!$S:$S,0),COLUMN()-3),""),""))) -> 0 | I66: =IF($C66="faizan",IFERROR(INDEX('faizan grading'!$E:$Q,MATCH($A66&"|"&$B66,'faizan grading'!$S:$S,0),COLUMN()-3),""),IF($C66="romain",IFERROR(INDEX('romain grading'!$E:$Q,MATCH($A66&"|"&$B66,'romain grading'!$S:$S,0),COLUMN()-3),""),IF($C66="nishita",IFERROR(INDEX('nishita grading'!$E:$Q,MATCH($A66&"|"&$B66,'nishita grading'!$S:$S,0),COLUMN()-3),""),""))) -> 0 | J66: =IF($C66="faizan",IFERROR(INDEX('faizan grading'!$E:$Q,MATCH($A66&"|"&$B66,'faizan grading'!$S:$S,0),COLUMN()-3),""),IF($C66="romain",IFERROR(INDEX('romain grading'!$E:$Q,MATCH($A66&"|"&$B66,'romain grading'!$S:$S,0),COLUMN()-3),""),IF($C66="nishita",IFERROR(INDEX('nishita grading'!$E:$Q,MATCH($A66&"|"&$B66,'nishita grading'!$S:$S,0),COLUMN()-3),""),""))) -> 0 | K66: =IF($C66="faizan",IFERROR(INDEX('faizan grading'!$E:$Q,MATCH($A66&"|"&$B66,'faizan grading'!$S:$S,0),COLUMN()-3),""),IF($C66="romain",IFERROR(INDEX('romain grading'!$E:$Q,MATCH($A66&"|"&$B66,'romain grading'!$S:$S,0),COLUMN()-3),""),IF($C66="nishita",IFERROR(INDEX('nishita grading'!$E:$Q,MATCH($A66&"|"&$B66,'nishita grading'!$S:$S,0),COLUMN()-3),""),""))) -> 0 | ... P66: =IF($C66="faizan",IFERROR(INDEX('faizan grading'!$E:$Q,MATCH($A66&"|"&$B66,'faizan grading'!$S:$S,0),COLUMN()-3),""),IF($C66="romain",IFERROR(INDEX('romain grading'!$E:$Q,MATCH($A66&"|"&$B66,'romain grading'!$S:$S,0),COLUMN()-3),""),IF($C66="nishita",IFERROR(INDEX('nishita grading'!$E:$Q,MATCH($A66&"|"&$B66,'nishita grading'!$S:$S,0),COLUMN()-3),""),""))) -> 0 | Q66: =40-SUM(D66:P66) -> 40 | R66: =A66&"|"&B66 -> clueless|0218
A67: clueless | B67: 0218 | C67: romain | D67: =IF($C67="faizan",IFERROR(INDEX('faizan grading'!$E:$Q,MATCH($A67&"|"&$B67,'faizan grading'!$S:$S,0),COLUMN()-3),""),IF($C67="romain",IFERROR(INDEX('romain grading'!$E:$Q,MATCH($A67&"|"&$B67,'romain grading'!$S:$S,0),COLUMN()-3),""),IF($C67="nishita",IFERROR(INDEX('nishita grading'!$E:$Q,MATCH($A67&"|"&$B67,'nishita grading'!$S:$S,0),COLUMN()-3),""),""))) -> 0 | E67: =IF($C67="faizan",IFERROR(INDEX('faizan grading'!$E:$Q,MATCH($A67&"|"&$B67,'faizan grading'!$S:$S,0),COLUMN()-3),""),IF($C67="romain",IFERROR(INDEX('romain grading'!$E:$Q,MATCH($A67&"|"&$B67,'romain grading'!$S:$S,0),COLUMN()-3),""),IF($C67="nishita",IFERROR(INDEX('nishita grading'!$E:$Q,MATCH($A67&"|"&$B67,'nishita grading'!$S:$S,0),COLUMN()-3),""),""))) -> 0 | F67: =IF($C67="faizan",IFERROR(INDEX('faizan grading'!$E:$Q,MATCH($A67&"|"&$B67,'faizan grading'!$S:$S,0),COLUMN()-3),""),IF($C67="romain",IFERROR(INDEX('romain grading'!$E:$Q,MATCH($A67&"|"&$B67,'romain grading'!$S:$S,0),COLUMN()-3),""),IF($C67="nishita",IFERROR(INDEX('nishita grading'!$E:$Q,MATCH($A67&"|"&$B67,'nishita grading'!$S:$S,0),COLUMN()-3),""),""))) -> 0 | G67: =IF($C67="faizan",IFERROR(INDEX('faizan grading'!$E:$Q,MATCH($A67&"|"&$B67,'faizan grading'!$S:$S,0),COLUMN()-3),""),IF($C67="romain",IFERROR(INDEX('romain grading'!$E:$Q,MATCH($A67&"|"&$B67,'romain grading'!$S:$S,0),COLUMN()-3),""),IF($C67="nishita",IFERROR(INDEX('nishita grading'!$E:$Q,MATCH($A67&"|"&$B67,'nishita grading'!$S:$S,0),COLUMN()-3),""),""))) -> 0 | H67: =IF($C67="faizan",IFERROR(INDEX('faizan grading'!$E:$Q,MATCH($A67&"|"&$B67,'faizan grading'!$S:$S,0),COLUMN()-3),""),IF($C67="romain",IFERROR(INDEX('romain grading'!$E:$Q,MATCH($A67&"|"&$B67,'romain grading'!$S:$S,0),COLUMN()-3),""),IF($C67="nishita",IFERROR(INDEX('nishita grading'!$E:$Q,MATCH($A67&"|"&$B67,'nishita grading'!$S:$S,0),COLUMN()-3),""),""))) -> 0 | I67: =IF($C67="faizan",IFERROR(INDEX('faizan grading'!$E:$Q,MATCH($A67&"|"&$B67,'faizan grading'!$S:$S,0),COLUMN()-3),""),IF($C67="romain",IFERROR(INDEX('romain grading'!$E:$Q,MATCH($A67&"|"&$B67,'romain grading'!$S:$S,0),COLUMN()-3),""),IF($C67="nishita",IFERROR(INDEX('nishita grading'!$E:$Q,MATCH($A67&"|"&$B67,'nishita grading'!$S:$S,0),COLUMN()-3),""),""))) -> 0 | J67: =IF($C67="faizan",IFERROR(INDEX('faizan grading'!$E:$Q,MATCH($A67&"|"&$B67,'faizan grading'!$S:$S,0),COLUMN()-3),""),IF($C67="romain",IFERROR(INDEX('romain grading'!$E:$Q,MATCH($A67&"|"&$B67,'romain grading'!$S:$S,0),COLUMN()-3),""),IF($C67="nishita",IFERROR(INDEX('nishita grading'!$E:$Q,MATCH($A67&"|"&$B67,'nishita grading'!$S:$S,0),COLUMN()-3),""),""))) -> 0 | K67: =IF($C67="faizan",IFERROR(INDEX('faizan grading'!$E:$Q,MATCH($A67&"|"&$B67,'faizan grading'!$S:$S,0),COLUMN()-3),""),IF($C67="romain",IFERROR(INDEX('romain grading'!$E:$Q,MATCH($A67&"|"&$B67,'romain grading'!$S:$S,0),COLUMN()-3),""),IF($C67="nishita",IFERROR(INDEX('nishita grading'!$E:$Q,MATCH($A67&"|"&$B67,'nishita grading'!$S:$S,0),COLUMN()-3),""),""))) -> 0 | ... P67: =IF($C67="faizan",IFERROR(INDEX('faizan grading'!$E:$Q,MATCH($A67&"|"&$B67,'faizan grading'!$S:$S,0),COLUMN()-3),""),IF($C67="romain",IFERROR(INDEX('romain grading'!$E:$Q,MATCH($A67&"|"&$B67,'romain grading'!$S:$S,0),COLUMN()-3),""),IF($C67="nishita",IFERROR(INDEX('nishita grading'!$E:$Q,MATCH($A67&"|"&$B67,'nishita grading'!$S:$S,0),COLUMN()-3),""),""))) -> 0 | Q67: =40-SUM(D67:P67) -> 38 | R67: =A67&"|"&B67 -> clueless|0218
A68: clueless | B68: 0218 | C68: nishita | D68: =IF($C68="faizan",IFERROR(INDEX('faizan grading'!$E:$Q,MATCH($A68&"|"&$B68,'faizan grading'!$S:$S,0),COLUMN()-3),""),IF($C68="romain",IFERROR(INDEX('romain grading'!$E:$Q,MATCH($A68&"|"&$B68,'romain grading'!$S:$S,0),COLUMN()-3),""),IF($C68="nishita",IFERROR(INDEX('nishita grading'!$E:$Q,MATCH($A68&"|"&$B68,'nishita grading'!$S:$S,0),COLUMN()-3),""),""))) -> 0 | E68: =IF($C68="faizan",IFERROR(INDEX('faizan grading'!$E:$Q,MATCH($A68&"|"&$B68,'faizan grading'!$S:$S,0),COLUMN()-3),""),IF($C68="romain",IFERROR(INDEX('romain grading'!$E:$Q,MATCH($A68&"|"&$B68,'romain grading'!$S:$S,0),COLUMN()-3),""),IF($C68="nishita",IFERROR(INDEX('nishita grading'!$E:$Q,MATCH($A68&"|"&$B68,'nishita grading'!$S:$S,0),COLUMN()-3),""),""))) -> 0 | F68: =IF($C68="faizan",IFERROR(INDEX('faizan grading'!$E:$Q,MATCH($A68&"|"&$B68,'faizan grading'!$S:$S,0),COLUMN()-3),""),IF($C68="romain",IFERROR(INDEX('romain grading'!$E:$Q,MATCH($A68&"|"&$B68,'romain grading'!$S:$S,0),COLUMN()-3),""),IF($C68="nishita",IFERROR(INDEX('nishita grading'!$E:$Q,MATCH($A68&"|"&$B68,'nishita grading'!$S:$S,0),COLUMN()-3),""),""))) -> 6 | G68: =IF($C68="faizan",IFERROR(INDEX('faizan grading'!$E:$Q,MATCH($A68&"|"&$B68,'faizan grading'!$S:$S,0),COLUMN()-3),""),IF($C68="romain",IFERROR(INDEX('romain grading'!$E:$Q,MATCH($A68&"|"&$B68,'romain grading'!$S:$S,0),COLUMN()-3),""),IF($C68="nishita",IFERROR(INDEX('nishita grading'!$E:$Q,MATCH($A68&"|"&$B68,'nishita grading'!$S:$S,0),COLUMN()-3),""),""))) -> 0 | H68: =IF($C68="faizan",IFERROR(INDEX('faizan grading'!$E:$Q,MATCH($A68&"|"&$B68,'faizan grading'!$S:$S,0),COLUMN()-3),""),IF($C68="romain",IFERROR(INDEX('romain grading'!$E:$Q,MATCH($A68&"|"&$B68,'romain grading'!$S:$S,0),COLUMN()-3),""),IF($C68="nishita",IFERROR(INDEX('nishita grading'!$E:$Q,MATCH($A68&"|"&$B68,'nishita grading'!$S:$S,0),COLUMN()-3),""),""))) -> 0 | I68: =IF($C68="faizan",IFERROR(INDEX('faizan grading'!$E:$Q,MATCH($A68&"|"&$B68,'faizan grading'!$S:$S,0),COLUMN()-3),""),IF($C68="romain",IFERROR(INDEX('romain grading'!$E:$Q,MATCH($A68&"|"&$B68,'romain grading'!$S:$S,0),COLUMN()-3),""),IF($C68="nishita",IFERROR(INDEX('nishita grading'!$E:$Q,MATCH($A68&"|"&$B68,'nishita grading'!$S:$S,0),COLUMN()-3),""),""))) -> 0 | J68: =IF($C68="faizan",IFERROR(INDEX('faizan grading'!$E:$Q,MATCH($A68&"|"&$B68,'faizan grading'!$S:$S,0),COLUMN()-3),""),IF($C68="romain",IFERROR(INDEX('romain grading'!$E:$Q,MATCH($A68&"|"&$B68,'romain grading'!$S:$S,0),COLUMN()-3),""),IF($C68="nishita",IFERROR(INDEX('nishita grading'!$E:$Q,MATCH($A68&"|"&$B68,'nishita grading'!$S:$S,0),COLUMN()-3),""),""))) -> 0 | K68: =IF($C68="faizan",IFERROR(INDEX('faizan grading'!$E:$Q,MATCH($A68&"|"&$B68,'faizan grading'!$S:$S,0),COLUMN()-3),""),IF($C68="romain",IFERROR(INDEX('romain grading'!$E:$Q,MATCH($A68&"|"&$B68,'romain grading'!$S:$S,0),COLUMN()-3),""),IF($C68="nishita",IFERROR(INDEX('nishita grading'!$E:$Q,MATCH($A68&"|"&$B68,'nishita grading'!$S:$S,0),COLUMN()-3),""),""))) -> 4 | ... P68: =IF($C68="faizan",IFERROR(INDEX('faizan grading'!$E:$Q,MATCH($A68&"|"&$B68,'faizan grading'!$S:$S,0),COLUMN()-3),""),IF($C68="romain",IFERROR(INDEX('romain grading'!$E:$Q,MATCH($A68&"|"&$B68,'romain grading'!$S:$S,0),COLUMN()-3),""),IF($C68="nishita",IFERROR(INDEX('nishita grading'!$E:$Q,MATCH($A68&"|"&$B68,'nishita grading'!$S:$S,0),COLUMN()-3),""),""))) -> 0 | Q68: =40-SUM(D68:P68) -> 28 | R68: =A68&"|"&B68 -> clueless|0218
A69: clueless | B69: 0218 | C69: claude | D69: 0 | E69: 0 | F69: 6 | G69: 0 | H69: 3 | I69: 0 | J69: 0 | K69: 4 | L69: 0 | M69: 0 | N69: 0 | O69: 2 | P69: 0 | Q69: =40-SUM(D69:P69) -> 25 | R69: =A69&"|"&B69 -> clueless|0218
A70: clueless | B70: 0242 | C70: faizan | D70: =IF($C70="faizan",IFERROR(INDEX('faizan grading'!$E:$Q,MATCH($A70&"|"&$B70,'faizan grading'!$S:$S,0),COLUMN()-3),""),IF($C70="romain",IFERROR(INDEX('romain grading'!$E:$Q,MATCH($A70&"|"&$B70,'romain grading'!$S:$S,0),COLUMN()-3),""),IF($C70="nishita",IFERROR(INDEX('nishita grading'!$E:$Q,MATCH($A70&"|"&$B70,'nishita grading'!$S:$S,0),COLUMN()-3),""),""))) -> 0 | E70: =IF($C70="faizan",IFERROR(INDEX('faizan grading'!$E:$Q,MATCH($A70&"|"&$B70,'faizan grading'!$S:$S,0),COLUMN()-3),""),IF($C70="romain",IFERROR(INDEX('romain grading'!$E:$Q,MATCH($A70&"|"&$B70,'romain grading'!$S:$S,0),COLUMN()-3),""),IF($C70="nishita",IFERROR(INDEX('nishita grading'!$E:$Q,MATCH($A70&"|"&$B70,'nishita grading'!$S:$S,0),COLUMN()-3),""),""))) -> 0 | F70: =IF($C70="faizan",IFERROR(INDEX('faizan grading'!$E:$Q,MATCH($A70&"|"&$B70,'faizan grading'!$S:$S,0),COLUMN()-3),""),IF($C70="romain",IFERROR(INDEX('romain grading'!$E:$Q,MATCH($A70&"|"&$B70,'romain grading'!$S:$S,0),COLUMN()-3),""),IF($C70="nishita",IFERROR(INDEX('nishita grading'!$E:$Q,MATCH($A70&"|"&$B70,'nishita grading'!$S:$S,0),COLUMN()-3),""),""))) -> 0 | G70: =IF($C70="faizan",IFERROR(INDEX('faizan grading'!$E:$Q,MATCH($A70&"|"&$B70,'faizan grading'!$S:$S,0),COLUMN()-3),""),IF($C70="romain",IFERROR(INDEX('romain grading'!$E:$Q,MATCH($A70&"|"&$B70,'romain grading'!$S:$S,0),COLUMN()-3),""),IF($C70="nishita",IFERROR(INDEX('nishita grading'!$E:$Q,MATCH($A70&"|"&$B70,'nishita grading'!$S:$S,0),COLUMN()-3),""),""))) -> 0 | H70: =IF($C70="faizan",IFERROR(INDEX('faizan grading'!$E:$Q,MATCH($A70&"|"&$B70,'faizan grading'!$S:$S,0),COLUMN()-3),""),IF($C70="romain",IFERROR(INDEX('romain grading'!$E:$Q,MATCH($A70&"|"&$B70,'romain grading'!$S:$S,0),COLUMN()-3),""),IF($C70="nishita",IFERROR(INDEX('nishita grading'!$E:$Q,MATCH($A70&"|"&$B70,'nishita grading'!$S:$S,0),COLUMN()-3),""),""))) -> 0 | I70: =IF($C70="faizan",IFERROR(INDEX('faizan grading'!$E:$Q,MATCH($A70&"|"&$B70,'faizan grading'!$S:$S,0),COLUMN()-3),""),IF($C70="romain",IFERROR(INDEX('romain grading'!$E:$Q,MATCH($A70&"|"&$B70,'romain grading'!$S:$S,0),COLUMN()-3),""),IF($C70="nishita",IFERROR(INDEX('nishita grading'!$E:$Q,MATCH($A70&"|"&$B70,'nishita grading'!$S:$S,0),COLUMN()-3),""),""))) -> 0 | J70: =IF($C70="faizan",IFERROR(INDEX('faizan grading'!$E:$Q,MATCH($A70&"|"&$B70,'faizan grading'!$S:$S,0),COLUMN()-3),""),IF($C70="romain",IFERROR(INDEX('romain grading'!$E:$Q,MATCH($A70&"|"&$B70,'romain grading'!$S:$S,0),COLUMN()-3),""),IF($C70="nishita",IFERROR(INDEX('nishita grading'!$E:$Q,MATCH($A70&"|"&$B70,'nishita grading'!$S:$S,0),COLUMN()-3),""),""))) -> 0 | K70: =IF($C70="faizan",IFERROR(INDEX('faizan grading'!$E:$Q,MATCH($A70&"|"&$B70,'faizan grading'!$S:$S,0),COLUMN()-3),""),IF($C70="romain",IFERROR(INDEX('romain grading'!$E:$Q,MATCH($A70&"|"&$B70,'romain grading'!$S:$S,0),COLUMN()-3),""),IF($C70="nishita",IFERROR(INDEX('nishita grading'!$E:$Q,MATCH($A70&"|"&$B70,'nishita grading'!$S:$S,0),COLUMN()-3),""),""))) -> 0 | ... P70: =IF($C70="faizan",IFERROR(INDEX('faizan grading'!$E:$Q,MATCH($A70&"|"&$B70,'faizan grading'!$S:$S,0),COLUMN()-3),""),IF($C70="romain",IFERROR(INDEX('romain grading'!$E:$Q,MATCH($A70&"|"&$B70,'romain grading'!$S:$S,0),COLUMN()-3),""),IF($C70="nishita",IFERROR(INDEX('nishita grading'!$E:$Q,MATCH($A70&"|"&$B70,'nishita grading'!$S:$S,0),COLUMN()-3),""),""))) -> 0 | Q70: =40-SUM(D70:P70) -> 40 | R70: =A70&"|"&B70 -> clueless|0242
A71: clueless | B71: 0242 | C71: romain | D71: =IF($C71="faizan",IFERROR(INDEX('faizan grading'!$E:$Q,MATCH($A71&"|"&$B71,'faizan grading'!$S:$S,0),COLUMN()-3),""),IF($C71="romain",IFERROR(INDEX('romain grading'!$E:$Q,MATCH($A71&"|"&$B71,'romain grading'!$S:$S,0),COLUMN()-3),""),IF($C71="nishita",IFERROR(INDEX('nishita grading'!$E:$Q,MATCH($A71&"|"&$B71,'nishita grading'!$S:$S,0),COLUMN()-3),""),""))) -> 0 | E71: =IF($C71="faizan",IFERROR(INDEX('faizan grading'!$E:$Q,MATCH($A71&"|"&$B71,'faizan grading'!$S:$S,0),COLUMN()-3),""),IF($C71="romain",IFERROR(INDEX('romain grading'!$E:$Q,MATCH($A71&"|"&$B71,'romain grading'!$S:$S,0),COLUMN()-3),""),IF($C71="nishita",IFERROR(INDEX('nishita grading'!$E:$Q,MATCH($A71&"|"&$B71,'nishita grading'!$S:$S,0),COLUMN()-3),""),""))) -> 0 | F71: =IF($C71="faizan",IFERROR(INDEX('faizan grading'!$E:$Q,MATCH($A71&"|"&$B71,'faizan grading'!$S:$S,0),COLUMN()-3),""),IF($C71="romain",IFERROR(INDEX('romain grading'!$E:$Q,MATCH($A71&"|"&$B71,'romain grading'!$S:$S,0),COLUMN()-3),""),IF($C71="nishita",IFERROR(INDEX('nishita grading'!$E:$Q,MATCH($A71&"|"&$B71,'nishita grading'!$S:$S,0),COLUMN()-3),""),""))) -> 0 | G71: =IF($C71="faizan",IFERROR(INDEX('faizan grading'!$E:$Q,MATCH($A71&"|"&$B71,'faizan grading'!$S:$S,0),COLUMN()-3),""),IF($C71="romain",IFERROR(INDEX('romain grading'!$E:$Q,MATCH($A71&"|"&$B71,'romain grading'!$S:$S,0),COLUMN()-3),""),IF($C71="nishita",IFERROR(INDEX('nishita grading'!$E:$Q,MATCH($A71&"|"&$B71,'nishita grading'!$S:$S,0),COLUMN()-3),""),""))) -> 0 | H71: =IF($C71="faizan",IFERROR(INDEX('faizan grading'!$E:$Q,MATCH($A71&"|"&$B71,'faizan grading'!$S:$S,0),COLUMN()-3),""),IF($C71="romain",IFERROR(INDEX('romain grading'!$E:$Q,MATCH($A71&"|"&$B71,'romain grading'!$S:$S,0),COLUMN()-3),""),IF($C71="nishita",IFERROR(INDEX('nishita grading'!$E:$Q,MATCH($A71&"|"&$B71,'nishita grading'!$S:$S,0),COLUMN()-3),""),""))) -> 0 | I71: =IF($C71="faizan",IFERROR(INDEX('faizan grading'!$E:$Q,MATCH($A71&"|"&$B71,'faizan grading'!$S:$S,0),COLUMN()-3),""),IF($C71="romain",IFERROR(INDEX('romain grading'!$E:$Q,MATCH($A71&"|"&$B71,'romain grading'!$S:$S,0),COLUMN()-3),""),IF($C71="nishita",IFERROR(INDEX('nishita grading'!$E:$Q,MATCH($A71&"|"&$B71,'nishita grading'!$S:$S,0),COLUMN()-3),""),""))) -> 0 | J71: =IF($C71="faizan",IFERROR(INDEX('faizan grading'!$E:$Q,MATCH($A71&"|"&$B71,'faizan grading'!$S:$S,0),COLUMN()-3),""),IF($C71="romain",IFERROR(INDEX('romain grading'!$E:$Q,MATCH($A71&"|"&$B71,'romain grading'!$S:$S,0),COLUMN()-3),""),IF($C71="nishita",IFERROR(INDEX('nishita grading'!$E:$Q,MATCH($A71&"|"&$B71,'nishita grading'!$S:$S,0),COLUMN()-3),""),""))) -> 0 | K71: =IF($C71="faizan",IFERROR(INDEX('faizan grading'!$E:$Q,MATCH($A71&"|"&$B71,'faizan grading'!$S:$S,0),COLUMN()-3),""),IF($C71="romain",IFERROR(INDEX('romain grading'!$E:$Q,MATCH($A71&"|"&$B71,'romain grading'!$S:$S,0),COLUMN()-3),""),IF($C71="nishita",IFERROR(INDEX('nishita grading'!$E:$Q,MATCH($A71&"|"&$B71,'nishita grading'!$S:$S,0),COLUMN()-3),""),""))) -> 0 | ... P71: =IF($C71="faizan",IFERROR(INDEX('faizan grading'!$E:$Q,MATCH($A71&"|"&$B71,'faizan grading'!$S:$S,0),COLUMN()-3),""),IF($C71="romain",IFERROR(INDEX('romain grading'!$E:$Q,MATCH($A71&"|"&$B71,'romain grading'!$S:$S,0),COLUMN()-3),""),IF($C71="nishita",IFERROR(INDEX('nishita grading'!$E:$Q,MATCH($A71&"|"&$B71,'nishita grading'!$S:$S,0),COLUMN()-3),""),""))) -> 0 | Q71: =40-SUM(D71:P71) -> 36 | R71: =A71&"|"&B71 -> clueless|0242
A72: clueless | B72: 0242 | C72: nishita | D72: =IF($C72="faizan",IFERROR(INDEX('faizan grading'!$E:$Q,MATCH($A72&"|"&$B72,'faizan grading'!$S:$S,0),COLUMN()-3),""),IF($C72="romain",IFERROR(INDEX('romain grading'!$E:$Q,MATCH($A72&"|"&$B72,'romain grading'!$S:$S,0),COLUMN()-3),""),IF($C72="nishita",IFERROR(INDEX('nishita grading'!$E:$Q,MATCH($A72&"|"&$B72,'nishita grading'!$S:$S,0),COLUMN()-3),""),""))) -> 0 | E72: =IF($C72="faizan",IFERROR(INDEX('faizan grading'!$E:$Q,MATCH($A72&"|"&$B72,'faizan grading'!$S:$S,0),COLUMN()-3),""),IF($C72="romain",IFERROR(INDEX('romain grading'!$E:$Q,MATCH($A72&"|"&$B72,'romain grading'!$S:$S,0),COLUMN()-3),""),IF($C72="nishita",IFERROR(INDEX('nishita grading'!$E:$Q,MATCH($A72&"|"&$B72,'nishita grading'!$S:$S,0),COLUMN()-3),""),""))) -> 0 | F72: =IF($C72="faizan",IFERROR(INDEX('faizan grading'!$E:$Q,MATCH($A72&"|"&$B72,'faizan grading'!$S:$S,0),COLUMN()-3),""),IF($C72="romain",IFERROR(INDEX('romain grading'!$E:$Q,MATCH($A72&"|"&$B72,'romain grading'!$S:$S,0),COLUMN()-3),""),IF($C72="nishita",IFERROR(INDEX('nishita grading'!$E:$Q,MATCH($A72&"|"&$B72,'nishita grading'!$S:$S,0),COLUMN()-3),""),""))) -> 0 | G72: =IF($C72="faizan",IFERROR(INDEX('faizan grading'!$E:$Q,MATCH($A72&"|"&$B72,'faizan grading'!$S:$S,0),COLUMN()-3),""),IF($C72="romain",IFERROR(INDEX('romain grading'!$E:$Q,MATCH($A72&"|"&$B72,'romain grading'!$S:$S,0),COLUMN()-3),""),IF($C72="nishita",IFERROR(INDEX('nishita grading'!$E:$Q,MATCH($A72&"|"&$B72,'nishita grading'!$S:$S,0),COLUMN()-3),""),""))) -> 0 | H72: =IF($C72="faizan",IFERROR(INDEX('faizan grading'!$E:$Q,MATCH($A72&"|"&$B72,'faizan grading'!$S:$S,0),COLUMN()-3),""),IF($C72="romain",IFERROR(INDEX('romain grading'!$E:$Q,MATCH($A72&"|"&$B72,'romain grading'!$S:$S,0),COLUMN()-3),""),IF($C72="nishita",IFERROR(INDEX('nishita grading'!$E:$Q,MATCH($A72&"|"&$B72,'nishita grading'!$S:$S,0),COLUMN()-3),""),""))) -> 3 | I72: =IF($C72="faizan",IFERROR(INDEX('faizan grading'!$E:$Q,MATCH($A72&"|"&$B72,'faizan grading'!$S:$S,0),COLUMN()-3),""),IF($C72="romain",IFERROR(INDEX('romain grading'!$E:$Q,MATCH($A72&"|"&$B72,'romain grading'!$S:$S,0),COLUMN()-3),""),IF($C72="nishita",IFERROR(INDEX('nishita grading'!$E:$Q,MATCH($A72&"|"&$B72,'nishita grading'!$S:$S,0),COLUMN()-3),""),""))) -> 0 | J72: =IF($C72="faizan",IFERROR(INDEX('faizan grading'!$E:$Q,MATCH($A72&"|"&$B72,'faizan grading'!$S:$S,0),COLUMN()-3),""),IF($C72="romain",IFERROR(INDEX('romain grading'!$E:$Q,MATCH($A72&"|"&$B72,'romain grading'!$S:$S,0),COLUMN()-3),""),IF($C72="nishita",IFERROR(INDEX('nishita grading'!$E:$Q,MATCH($A72&"|"&$B72,'nishita grading'!$S:$S,0),COLUMN()-3),""),""))) -> 0 | K72: =IF($C72="faizan",IFERROR(INDEX('faizan grading'!$E:$Q,MATCH($A72&"|"&$B72,'faizan grading'!$S:$S,0),COLUMN()-3),""),IF($C72="romain",IFERROR(INDEX('romain grading'!$E:$Q,MATCH($A72&"|"&$B72,'romain grading'!$S:$S,0),COLUMN()-3),""),IF($C72="nishita",IFERROR(INDEX('nishita grading'!$E:$Q,MATCH($A72&"|"&$B72,'nishita grading'!$S:$S,0),COLUMN()-3),""),""))) -> 4 | ... P72: =IF($C72="faizan",IFERROR(INDEX('faizan grading'!$E:$Q,MATCH($A72&"|"&$B72,'faizan grading'!$S:$S,0),COLUMN()-3),""),IF($C72="romain",IFERROR(INDEX('romain grading'!$E:$Q,MATCH($A72&"|"&$B72,'romain grading'!$S:$S,0),COLUMN()-3),""),IF($C72="nishita",IFERROR(INDEX('nishita grading'!$E:$Q,MATCH($A72&"|"&$B72,'nishita grading'!$S:$S,0),COLUMN()-3),""),""))) -> 0 | Q72: =40-SUM(D72:P72) -> 33 | R72: =A72&"|"&B72 -> clueless|0242
A73: clueless | B73: 0242 | C73: claude | D73: 0 | E73: 0 | F73: 0 | G73: 0 | H73: 3 | I73: 2 | J73: 0 | K73: 4 | L73: 0 | M73: 0 | N73: 0 | O73: 0 | P73: 0 | Q73: =40-SUM(D73:P73) -> 31 | R73: =A73&"|"&B73 -> clueless|0242
A74: clueless | B74: 0248 | C74: faizan | D74: =IF($C74="faizan",IFERROR(INDEX('faizan grading'!$E:$Q,MATCH($A74&"|"&$B74,'faizan grading'!$S:$S,0),COLUMN()-3),""),IF($C74="romain",IFERROR(INDEX('romain grading'!$E:$Q,MATCH($A74&"|"&$B74,'romain grading'!$S:$S,0),COLUMN()-3),""),IF($C74="nishita",IFERROR(INDEX('nishita grading'!$E:$Q,MATCH($A74&"|"&$B74,'nishita grading'!$S:$S,0),COLUMN()-3),""),""))) -> 0 | E74: =IF($C74="faizan",IFERROR(INDEX('faizan grading'!$E:$Q,MATCH($A74&"|"&$B74,'faizan grading'!$S:$S,0),COLUMN()-3),""),IF($C74="romain",IFERROR(INDEX('romain grading'!$E:$Q,MATCH($A74&"|"&$B74,'romain grading'!$S:$S,0),COLUMN()-3),""),IF($C74="nishita",IFERROR(INDEX('nishita grading'!$E:$Q,MATCH($A74&"|"&$B74,'nishita grading'!$S:$S,0),COLUMN()-3),""),""))) -> 0 | F74: =IF($C74="faizan",IFERROR(INDEX('faizan grading'!$E:$Q,MATCH($A74&"|"&$B74,'faizan grading'!$S:$S,0),COLUMN()-3),""),IF($C74="romain",IFERROR(INDEX('romain grading'!$E:$Q,MATCH($A74&"|"&$B74,'romain grading'!$S:$S,0),COLUMN()-3),""),IF($C74="nishita",IFERROR(INDEX('nishita grading'!$E:$Q,MATCH($A74&"|"&$B74,'nishita grading'!$S:$S,0),COLUMN()-3),""),""))) -> 0 | G74: =IF($C74="faizan",IFERROR(INDEX('faizan grading'!$E:$Q,MATCH($A74&"|"&$B74,'faizan grading'!$S:$S,0),COLUMN()-3),""),IF($C74="romain",IFERROR(INDEX('romain grading'!$E:$Q,MATCH($A74&"|"&$B74,'romain grading'!$S:$S,0),COLUMN()-3),""),IF($C74="nishita",IFERROR(INDEX('nishita grading'!$E:$Q,MATCH($A74&"|"&$B74,'nishita grading'!$S:$S,0),COLUMN()-3),""),""))) -> 0 | H74: =IF($C74="faizan",IFERROR(INDEX('faizan grading'!$E:$Q,MATCH($A74&"|"&$B74,'faizan grading'!$S:$S,0),COLUMN()-3),""),IF($C74="romain",IFERROR(INDEX('romain grading'!$E:$Q,MATCH($A74&"|"&$B74,'romain grading'!$S:$S,0),COLUMN()-3),""),IF($C74="nishita",IFERROR(INDEX('nishita grading'!$E:$Q,MATCH($A74&"|"&$B74,'nishita grading'!$S:$S,0),COLUMN()-3),""),""))) -> 0 | I74: =IF($C74="faizan",IFERROR(INDEX('faizan grading'!$E:$Q,MATCH($A74&"|"&$B74,'faizan grading'!$S:$S,0),COLUMN()-3),""),IF($C74="romain",IFERROR(INDEX('romain grading'!$E:$Q,MATCH($A74&"|"&$B74,'romain grading'!$S:$S,0),COLUMN()-3),""),IF($C74="nishita",IFERROR(INDEX('nishita grading'!$E:$Q,MATCH($A74&"|"&$B74,'nishita grading'!$S:$S,0),COLUMN()-3),""),""))) -> 0 | J74: =IF($C74="faizan",IFERROR(INDEX('faizan grading'!$E:$Q,MATCH($A74&"|"&$B74,'faizan grading'!$S:$S,0),COLUMN()-3),""),IF($C74="romain",IFERROR(INDEX('romain grading'!$E:$Q,MATCH($A74&"|"&$B74,'romain grading'!$S:$S,0),COLUMN()-3),""),IF($C74="nishita",IFERROR(INDEX('nishita grading'!$E:$Q,MATCH($A74&"|"&$B74,'nishita grading'!$S:$S,0),COLUMN()-3),""),""))) -> 0 | K74: =IF($C74="faizan",IFERROR(INDEX('faizan grading'!$E:$Q,MATCH($A74&"|"&$B74,'faizan grading'!$S:$S,0),COLUMN()-3),""),IF($C74="romain",IFERROR(INDEX('romain grading'!$E:$Q,MATCH($A74&"|"&$B74,'romain grading'!$S:$S,0),COLUMN()-3),""),IF($C74="nishita",IFERROR(INDEX('nishita grading'!$E:$Q,MATCH($A74&"|"&$B74,'nishita grading'!$S:$S,0),COLUMN()-3),""),""))) -> 0 | ... P74: =IF($C74="faizan",IFERROR(INDEX('faizan grading'!$E:$Q,MATCH($A74&"|"&$B74,'faizan grading'!$S:$S,0),COLUMN()-3),""),IF($C74="romain",IFERROR(INDEX('romain grading'!$E:$Q,MATCH($A74&"|"&$B74,'romain grading'!$S:$S,0),COLUMN()-3),""),IF($C74="nishita",IFERROR(INDEX('nishita grading'!$E:$Q,MATCH($A74&"|"&$B74,'nishita grading'!$S:$S,0),COLUMN()-3),""),""))) -> 0 | Q74: =40-SUM(D74:P74) -> 40 | R74: =A74&"|"&B74 -> clueless|0248
A75: clueless | B75: 0248 | C75: romain | D75: =IF($C75="faizan",IFERROR(INDEX('faizan grading'!$E:$Q,MATCH($A75&"|"&$B75,'faizan grading'!$S:$S,0),COLUMN()-3),""),IF($C75="romain",IFERROR(INDEX('romain grading'!$E:$Q,MATCH($A75&"|"&$B75,'romain grading'!$S:$S,0),COLUMN()-3),""),IF($C75="nishita",IFERROR(INDEX('nishita grading'!$E:$Q,MATCH($A75&"|"&$B75,'nishita grading'!$S:$S,0),COLUMN()-3),""),""))) -> 0 | E75: =IF($C75="faizan",IFERROR(INDEX('faizan grading'!$E:$Q,MATCH($A75&"|"&$B75,'faizan grading'!$S:$S,0),COLUMN()-3),""),IF($C75="romain",IFERROR(INDEX('romain grading'!$E:$Q,MATCH($A75&"|"&$B75,'romain grading'!$S:$S,0),COLUMN()-3),""),IF($C75="nishita",IFERROR(INDEX('nishita grading'!$E:$Q,MATCH($A75&"|"&$B75,'nishita grading'!$S:$S,0),COLUMN()-3),""),""))) -> 0 | F75: =IF($C75="faizan",IFERROR(INDEX('faizan grading'!$E:$Q,MATCH($A75&"|"&$B75,'faizan grading'!$S:$S,0),COLUMN()-3),""),IF($C75="romain",IFERROR(INDEX('romain grading'!$E:$Q,MATCH($A75&"|"&$B75,'romain grading'!$S:$S,0),COLUMN()-3),""),IF($C75="nishita",IFERROR(INDEX('nishita grading'!$E:$Q,MATCH($A75&"|"&$B75,'nishita grading'!$S:$S,0),COLUMN()-3),""),""))) -> 0 | G75: =IF($C75="faizan",IFERROR(INDEX('faizan grading'!$E:$Q,MATCH($A75&"|"&$B75,'faizan grading'!$S:$S,0),COLUMN()-3),""),IF($C75="romain",IFERROR(INDEX('romain grading'!$E:$Q,MATCH($A75&"|"&$B75,'romain grading'!$S:$S,0),COLUMN()-3),""),IF($C75="nishita",IFERROR(INDEX('nishita grading'!$E:$Q,MATCH($A75&"|"&$B75,'nishita grading'!$S:$S,0),COLUMN()-3),""),""))) -> 0 | H75: =IF($C75="faizan",IFERROR(INDEX('faizan grading'!$E:$Q,MATCH($A75&"|"&$B75,'faizan grading'!$S:$S,0),COLUMN()-3),""),IF($C75="romain",IFERROR(INDEX('romain grading'!$E:$Q,MATCH($A75&"|"&$B75,'romain grading'!$S:$S,0),COLUMN()-3),""),IF($C75="nishita",IFERROR(INDEX('nishita grading'!$E:$Q,MATCH($A75&"|"&$B75,'nishita grading'!$S:$S,0),COLUMN()-3),""),""))) -> 0 | I75: =IF($C75="faizan",IFERROR(INDEX('faizan grading'!$E:$Q,MATCH($A75&"|"&$B75,'faizan grading'!$S:$S,0),COLUMN()-3),""),IF($C75="romain",IFERROR(INDEX('romain grading'!$E:$Q,MATCH($A75&"|"&$B75,'romain grading'!$S:$S,0),COLUMN()-3),""),IF($C75="nishita",IFERROR(INDEX('nishita grading'!$E:$Q,MATCH($A75&"|"&$B75,'nishita grading'!$S:$S,0),COLUMN()-3),""),""))) -> 2 | J75: =IF($C75="faizan",IFERROR(INDEX('faizan grading'!$E:$Q,MATCH($A75&"|"&$B75,'faizan grading'!$S:$S,0),COLUMN()-3),""),IF($C75="romain",IFERROR(INDEX('romain grading'!$E:$Q,MATCH($A75&"|"&$B75,'romain grading'!$S:$S,0),COLUMN()-3),""),IF($C75="nishita",IFERROR(INDEX('nishita grading'!$E:$Q,MATCH($A75&"|"&$B75,'nishita grading'!$S:$S,0),COLUMN()-3),""),""))) -> 0 | K75: =IF($C75="faizan",IFERROR(INDEX('faizan grading'!$E:$Q,MATCH($A75&"|"&$B75,'faizan grading'!$S:$S,0),COLUMN()-3),""),IF($C75="romain",IFERROR(INDEX('romain grading'!$E:$Q,MATCH($A75&"|"&$B75,'romain grading'!$S:$S,0),COLUMN()-3),""),IF($C75="nishita",IFERROR(INDEX('nishita grading'!$E:$Q,MATCH($A75&"|"&$B75,'nishita grading'!$S:$S,0),COLUMN()-3),""),""))) -> 0 | ... P75: =IF($C75="faizan",IFERROR(INDEX('faizan grading'!$E:$Q,MATCH($A75&"|"&$B75,'faizan grading'!$S:$S,0),COLUMN()-3),""),IF($C75="romain",IFERROR(INDEX('romain grading'!$E:$Q,MATCH($A75&"|"&$B75,'romain grading'!$S:$S,0),COLUMN()-3),""),IF($C75="nishita",IFERROR(INDEX('nishita grading'!$E:$Q,MATCH($A75&"|"&$B75,'nishita grading'!$S:$S,0),COLUMN()-3),""),""))) -> 0 | Q75: =40-SUM(D75:P75) -> 38 | R75: =A75&"|"&B75 -> clueless|0248
A76: clueless | B76: 0248 | C76: nishita | D76: =IF($C76="faizan",IFERROR(INDEX('faizan grading'!$E:$Q,MATCH($A76&"|"&$B76,'faizan grading'!$S:$S,0),COLUMN()-3),""),IF($C76="romain",IFERROR(INDEX('romain grading'!$E:$Q,MATCH($A76&"|"&$B76,'romain grading'!$S:$S,0),COLUMN()-3),""),IF($C76="nishita",IFERROR(INDEX('nishita grading'!$E:$Q,MATCH($A76&"|"&$B76,'nishita grading'!$S:$S,0),COLUMN()-3),""),""))) -> 0 | E76: =IF($C76="faizan",IFERROR(INDEX('faizan grading'!$E:$Q,MATCH($A76&"|"&$B76,'faizan grading'!$S:$S,0),COLUMN()-3),""),IF($C76="romain",IFERROR(INDEX('romain grading'!$E:$Q,MATCH($A76&"|"&$B76,'romain grading'!$S:$S,0),COLUMN()-3),""),IF($C76="nishita",IFERROR(INDEX('nishita grading'!$E:$Q,MATCH($A76&"|"&$B76,'nishita grading'!$S:$S,0),COLUMN()-3),""),""))) -> 0 | F76: =IF($C76="faizan",IFERROR(INDEX('faizan grading'!$E:$Q,MATCH($A76&"|"&$B76,'faizan grading'!$S:$S,0),COLUMN()-3),""),IF($C76="romain",IFERROR(INDEX('romain grading'!$E:$Q,MATCH($A76&"|"&$B76,'romain grading'!$S:$S,0),COLUMN()-3),""),IF($C76="nishita",IFERROR(INDEX('nishita grading'!$E:$Q,MATCH($A76&"|"&$B76,'nishita grading'!$S:$S,0),COLUMN()-3),""),""))) -> 0 | G76: =IF($C76="faizan",IFERROR(INDEX('faizan grading'!$E:$Q,MATCH($A76&"|"&$B76,'faizan grading'!$S:$S,0),COLUMN()-3),""),IF($C76="romain",IFERROR(INDEX('romain grading'!$E:$Q,MATCH($A76&"|"&$B76,'romain grading'!$S:$S,0),COLUMN()-3),""),IF($C76="nishita",IFERROR(INDEX('nishita grading'!$E:$Q,MATCH($A76&"|"&$B76,'nishita grading'!$S:$S,0),COLUMN()-3),""),""))) -> 0 | H76: =IF($C76="faizan",IFERROR(INDEX('faizan grading'!$E:$Q,MATCH($A76&"|"&$B76,'faizan grading'!$S:$S,0),COLUMN()-3),""),IF($C76="romain",IFERROR(INDEX('romain grading'!$E:$Q,MATCH($A76&"|"&$B76,'romain grading'!$S:$S,0),COLUMN()-3),""),IF($C76="nishita",IFERROR(INDEX('nishita grading'!$E:$Q,MATCH($A76&"|"&$B76,'nishita grading'!$S:$S,0),COLUMN()-3),""),""))) -> 3 | I76: =IF($C76="faizan",IFERROR(INDEX('faizan grading'!$E:$Q,MATCH($A76&"|"&$B76,'faizan grading'!$S:$S,0),COLUMN()-3),""),IF($C76="romain",IFERROR(INDEX('romain grading'!$E:$Q,MATCH($A76&"|"&$B76,'romain grading'!$S:$S,0),COLUMN()-3),""),IF($C76="nishita",IFERROR(INDEX('nishita grading'!$E:$Q,MATCH($A76&"|"&$B76,'nishita grading'!$S:$S,0),COLUMN()-3),""),""))) -> 0 | J76: =IF($C76="faizan",IFERROR(INDEX('faizan grading'!$E:$Q,MATCH($A76&"|"&$B76,'faizan grading'!$S:$S,0),COLUMN()-3),""),IF($C76="romain",IFERROR(INDEX('romain grading'!$E:$Q,MATCH($A76&"|"&$B76,'romain grading'!$S:$S,0),COLUMN()-3),""),IF($C76="nishita",IFERROR(INDEX('nishita grading'!$E:$Q,MATCH($A76&"|"&$B76,'nishita grading'!$S:$S,0),COLUMN()-3),""),""))) -> 0 | K76: =IF($C76="faizan",IFERROR(INDEX('faizan grading'!$E:$Q,MATCH($A76&"|"&$B76,'faizan grading'!$S:$S,0),COLUMN()-3),""),IF($C76="romain",IFERROR(INDEX('romain grading'!$E:$Q,MATCH($A76&"|"&$B76,'romain grading'!$S:$S,0),COLUMN()-3),""),IF($C76="nishita",IFERROR(INDEX('nishita grading'!$E:$Q,MATCH($A76&"|"&$B76,'nishita grading'!$S:$S,0),COLUMN()-3),""),""))) -> 4 | ... P76: =IF($C76="faizan",IFERROR(INDEX('faizan grading'!$E:$Q,MATCH($A76&"|"&$B76,'faizan grading'!$S:$S,0),COLUMN()-3),""),IF($C76="romain",IFERROR(INDEX('romain grading'!$E:$Q,MATCH($A76&"|"&$B76,'romain grading'!$S:$S,0),COLUMN()-3),""),IF($C76="nishita",IFERROR(INDEX('nishita grading'!$E:$Q,MATCH($A76&"|"&$B76,'nishita grading'!$S:$S,0),COLUMN()-3),""),""))) -> 0 | Q76: =40-SUM(D76:P76) -> 33 | R76: =A76&"|"&B76 -> clueless|0248
A77: clueless | B77: 0248 | C77: claude | D77: 0 | E77: 0 | F77: 0 | G77: 0 | H77: 3 | I77: 0 | J77: 0 | K77: 4 | L77: 0 | M77: 0 | N77: 0 | O77: 0 | P77: 0 | Q77: =40-SUM(D77:P77) -> 33 | R77: =A77&"|"&B77 -> clueless|0248
